Workbook
Name yearvalue: #REF!

Sheet Temp-PPT
A1: Subject | B1: Domain | C1: 472 | F1: MOM | I1: NOC | K1: Total Tasks | L1: D | M1: New | N1: 472 | Q1: MOM | T1: T0-T5 | U1: NOC | W1: Total Tasks
D2: Closed | E2: Open | G2: Closed | H2: Open | J2: Closed | K2: Open | L2: Old | M2: A | O2: Closed | P2: Open | R2: Closed | S2: Open | V2: Closed | W2: Open
A3: DC/NOC | B3: Network | C3: 57 | D3: 22 | E3: =C3-D3 -> 35 | F3: 294 | G3: 43 | H3: =F3-G3 -> 251 | N3: 53 | O3: 31 | P3: 22 | Q3: 272 | R3: 169 | S3: 103
A4: DC/NOC | B4: Security | C4: 45 | D4: 6 | E4: =C4-D4 -> 39 | F4: 109 | G4: 0 | H4: 109 | N4: 46 | O4: 16 | P4: 30 | Q4: 158 | R4: 19 | S4: 139
A5: DC/NOC | B5: Servers
A6: DC/NOC | B6: Virtulization
A7: DC/NOC | B7: Storage
A8: DC/NOC | B8: Backup
A9: DC/NOC | B9: Applications/Tools | C9: 189 | D9: =45+13 -> 58 | E9: 131 | F9: 597 | G9: 22 | H9: =F9-G9 -> 575 | I9: 678 | J9: 0 | K9: =I9-J9 -> 678 | N9: 194 | O9: 74 | P9: 120 | Q9: =615+14 -> 629 | R9: =172+8 -> 180 | S9: =443+6 -> 449 | U9: 678 | V9: 254 | W9: 424
A10: DC/NOC | B10: Process Flows
A11: DC/NOC | B11: Helpdesk (Contact Center) | F11: 83 | G11: 4 | H11: 79 | Q11: 83 | R11: 3 | S11: 80
A12: ISP &TSP | B12: Perimeter
A13: ISP &TSP | B13: Security
A14: ISP &TSP | B14: DWDM | C14: 25 | D14: 11 | E14: =C14-D14 -> 14 | F14: 2 | G14: 0 | H14: 2 | N14: 25 | O14: 12 | P14: 13 | Q14: 2 | S14: 2
A15: ISP &TSP | B15: IPMPLS | C15: 37 | D15: 16 | E15: =C15-D15 -> 21 | F15: 1 | G15: 0 | H15: 1 | N15: 35 | O15: 17 | P15: 18
A16: ISP &TSP | B16: GPON | C16: 101 | D16: 81 | E16: =C16-D16 -> 20 | F16: 5 | G16: 0 | H16: 5 | N16: 101 | O16: 91 | P16: 10 | Q16: 3 | R16: 3 | S16: 1
B17: Active Infrastructure | Q17: 4 | R17: 1 | S17: 3
A18: Infrastructure | B18: Passive Infrastructure
A19: DR | C19: 18 | D19: 9 | E19: =C19-D19 -> 9 | F19: 3 | G19: 0 | H19: 3 | N19: 18 | O19: 9 | P19: 9 | Q19: 3 | R19: 1 | S19: 2
A20: AT | F20: 1 | G20: 0 | H20: 1
A21: BBNL | F21: 5 | G21: 4 | H21: 1
A22: Field Related issues | F22: 24 | G22: 0 | H22: 24 | Q22: 24 | R22: 2 | S22: 22
A23: OEM Related Issues | F23: 100 | G23: 5 | H23: 95 | Q23: 100 | R23: 66 | S23: 34
A24: Regulatory | F24: 45 | G24: 0 | H24: 45
A25: WhatsApp | F25: 2 | G25: 0 | H25: 2
A26: Test Lab | F26: 7 | G26: 0 | H26: 7
C27: =SUM(C3:C19) -> 472 | D27: =SUM(D3:D19) -> 203 | E27: =SUM(E3:E19) -> 269 | F27: =SUM(F3:F26) -> 1278 | G27: =SUM(G3:G26) -> 78 | H27: =SUM(H3:H26) -> 1200 | I27: =SUM(I3:I26) -> 678 | J27: =SUM(J3:J26) -> 0 | K27: =SUM(K3:K26) -> 678 | N27: =SUM(N3:N26) -> 472 | O27: =SUM(O3:O26) -> 250 | P27: =SUM(P3:P26) -> 222 | Q27: =SUM(Q3:Q26) -> 1278 | R27: =SUM(R3:R26) -> 444 | S27: =SUM(S3:S26) -> 835 | T27: =SUM(T3:T26) -> 0 | U27: =SUM(U3:U26) -> 678 | ... W27: =SUM(W3:W26) -> 424
AF56: Count of UniqueID
AG57: CLOSED | AH57: OPEN | AI57: (blank) | AJ57: Grand Total
AF58: 472 | AG58: 250 | AH58: 222 | AJ58: 472
AF59: Applications/Tools | AG59: 74 | AH59: 120 | AJ59: 194
AF60: DR | AG60: 9 | AH60: 9 | AJ60: 18
AF61: DWDM | AG61: 12 | AH61: 13 | AJ61: 25
AF62: GPON | AG62: 91 | AH62: 10 | AJ62: 101
AF63: IPMPLS | AG63: 17 | AH63: 18 | AJ63: 35
AF64: Network | AG64: 31 | AH64: 22 | AJ64: 53
AF65: Security | AG65: 16 | AH65: 30 | AJ65: 46
AF66: MOM | AG66: 443 | AH66: 835 | AJ66: 1278
AF67: Applications | AG67: 8 | AH67: 6 | AJ67: 14
AF68: Applications/Tools | AG68: 172 | AH68: 443 | AJ68: 615
AF69: DR | AG69: 1 | AH69: 2 | AJ69: 3
AF70: DWDM | AH70: 2 | AJ70: 2
AF71: Field Related issues | AG71: 2 | AH71: 22 | AJ71: 24
AF72: GPON | AG72: 1 | AH72: 3 | AJ72: 4
AF73: Helpdesk (Contact Center) | AG73: 3 | AH73: 80 | AJ73: 83
AF74: IPMPLS | AG74: 2 | AH74: 1 | AJ74: 3
AF75: Network | AG75: 169 | AH75: 103 | AJ75: 272
AF76: OEM Related Issues | AG76: 66 | AH76: 34 | AJ76: 100
AF77: Security | AG77: 19 | AH77: 139 | AJ77: 158
AF78: NOC | AG78: 254 | AH78: 424 | AJ78: 678
AF79: Applications/Tools | AG79: 254 | AH79: 424 | AJ79: 678
AF80: (blank)
AF81: (blank)
AF82: Grand Total | AG82: 947 | AH82: 1481 | AJ82: 2428
Z508: Status Switch
Z509: OPEN | AA509: OPEN
Z510: COMPLETED & APPROVED | AA510: CLOSED
Z511: WIP | AA511: OPEN
Z512: REOPENED | AA512: OPEN
Z513: CLOSURE REVIEW PENDING | AA513: OPEN
Z514: DEPENDENCY(Client/Ext) | AA514: OPEN
Z515: CLOSED | AA515: CLOSED
Z516: DEPENDENCY(Client/Ext.) | AA516: OPEN
Z517: Completed | AA517: CLOSED
Z518: NOT FEASIBLE | AA518: OPEN
AA519: OPEN
Z520: COMPLETED | AA520: CLOSED
Z521: BLANK | AA521: OPEN
Z527: Track-472 | AA527: Overall | AB527: OPEN | AC527: CLOSED
Z528: Security & Regulatory Compliance | AA528: =COUNTIFS('Master_Tracker(2428)'!$D:$D,"472",'Master_Tracker(2428)'!$I:$I,Z528) -> 46 | AB528: =COUNTIFS('Master_Tracker(2428)'!$D:$D,"472",'Master_Tracker(2428)'!$I:$I,$Z528,'Master_Tracker(2428)'!$AK:$AK,'Temp-PPT'!$AB$527) -> 33 | AC528: =COUNTIFS('Master_Tracker(2428)'!$D:$D,"472",'Master_Tracker(2428)'!$I:$I,$Z528,'Master_Tracker(2428)'!$AK:$AK,'Temp-PPT'!$AC$527) -> 13
Z529: DWDM | AA529: =COUNTIFS('Master_Tracker(2428)'!$D:$D,"472",'Master_Tracker(2428)'!$I:$I,Z529) -> 25 | AB529: =COUNTIFS('Master_Tracker(2428)'!$D:$D,"472",'Master_Tracker(2428)'!$I:$I,$Z529,'Master_Tracker(2428)'!$AK:$AK,'Temp-PPT'!$AB$527) -> 13 | AC529: =COUNTIFS('Master_Tracker(2428)'!$D:$D,"472",'Master_Tracker(2428)'!$I:$I,$Z529,'Master_Tracker(2428)'!$AK:$AK,'Temp-PPT'!$AC$527) -> 12
Z530: DWDM
Z531: Security & Regulatory Compliance
Z532: Security & Regulatory Compliance
Z533: BSS | AA533: =COUNTIFS('Master_Tracker(2428)'!$D:$D,"472",'Master_Tracker(2428)'!$I:$I,Z533) -> 26 | AB533: =COUNTIFS('Master_Tracker(2428)'!$D:$D,"472",'Master_Tracker(2428)'!$I:$I,$Z533,'Master_Tracker(2428)'!$AK:$AK,'Temp-PPT'!$AB$527) -> 24 | AC533: =COUNTIFS('Master_Tracker(2428)'!$D:$D,"472",'Master_Tracker(2428)'!$I:$I,$Z533,'Master_Tracker(2428)'!$AK:$AK,'Temp-PPT'!$AC$527) -> 2
Z534: BSS
Z535: BSS
Z536: BSS
Z537: BSS
Z538: BSS
Z539: BSS
Z540: BSS
Z541: BSS
Z542: BSS
Z543: BSS
Z544: BSS
Z545: BSS
... Z554: BSS
Z555: IP/MPLS | AA555: =COUNTIFS('Master_Tracker(2428)'!$D:$D,"472",'Master_Tracker(2428)'!$I:$I,Z555) -> 34 | AB555: =COUNTIFS('Master_Tracker(2428)'!$D:$D,"472",'Master_Tracker(2428)'!$I:$I,$Z555,'Master_Tracker(2428)'!$AK:$AK,'Temp-PPT'!$AB$527) -> 16 | AC555: =COUNTIFS('Master_Tracker(2428)'!$D:$D,"472",'Master_Tracker(2428)'!$I:$I,$Z555,'Master_Tracker(2428)'!$AK:$AK,'Temp-PPT'!$AC$527) -> 18
Z556: IP/MPLS
Z557: IP/MPLS
Z558: Security & Regulatory Compliance
Z559: Security & Regulatory Compliance
Z560: BSS
Z561: IP/MPLS
Z562: IP/MPLS
Z563: Security & Regulatory Compliance
Z564: Security & Regulatory Compliance
Z565: Security & Regulatory Compliance
Z566: Security & Regulatory Compliance
...

Sheet Temp-Convertors
A1: Cat | B1: Values
A2: MOM | B2: DR
A3: MOM | B3: AT
A4: MOM | B4: BBNL
A5: MOM | B5: Field Related issues
A6: MOM | B6: OEM Related Issues
A7: MOM | B7: Regulatory
A8: MOM | B8: WhatsApp
A9: MOM | B9: Test Lab
A10: MOM | B10: Network
A11: MOM | B11: Security
A12: MOM | B12: Applications/Tools
... A16: MOM | B16: GPON
A17: 472 | B17: Network
A18: 472 | B18: Security
A19: 472 | B19: Applications/Tools
A20: 472 | B20: DWDM
A21: 472 | B21: IPMPLS
A22: 472 | B22: GPON
A23: 472 | B23: DR
A24: NOC | B24: Applications/Tools
A40: Cat | B40: Type | C40: CONCAT | D40: Tfiber | E40: Column1
A41: 472 | B41: BSS | C41: =_xlfn.CONCAT(A41,B41) -> 472BSS | D41: Applications/Tools
A42: 472 | B42: BSS | C42: =_xlfn.CONCAT(A42,B42) -> 472BSS | D42: Applications/Tools
A43: 472 | B43: DC-IT | C43: =_xlfn.CONCAT(A43,B43) -> 472DC-IT | D43: Network
A44: 472 | B44: DR | C44: =_xlfn.CONCAT(A44,B44) -> 472DR | D44: DR
A45: 472 | B45: DWDM | C45: =_xlfn.CONCAT(A45,B45) -> 472DWDM | D45: DWDM
A46: 472 | B46: GIS | C46: =_xlfn.CONCAT(A46,B46) -> 472GIS | D46: Applications/Tools
A47: 472 | B47: GPON | C47: =_xlfn.CONCAT(A47,B47) -> 472GPON | D47: GPON
A48: 472 | B48: IP/MPLS | C48: =_xlfn.CONCAT(A48,B48) -> 472IP/MPLS | D48: IPMPLS
A49: 472 | B49: NSO | C49: =_xlfn.CONCAT(A49,B49) -> 472NSO | D49: Applications/Tools
A50: 472 | B50: OSS | C50: =_xlfn.CONCAT(A50,B50) -> 472OSS | D50: Applications/Tools
A51: 472 | B51: Security & Regulatory Compliance | C51: =_xlfn.CONCAT(A51,B51) -> 472Security & Regulatory Compliance | D51: Security
A52: 472 | B52: TNOC-Ops | C52: =_xlfn.CONCAT(A52,B52) -> 472TNOC-Ops | D52: Network
A53: MOM | B53: NOC Operationalization | C53: =_xlfn.CONCAT(A53,B53) -> MOMNOC Operationalization | D53: Network
A54: MOM | B54: IP/MPLS | C54: =_xlfn.CONCAT(A54,B54) -> MOMIP/MPLS | D54: IPMPLS
A55: MOM | B55: WFM | C55: =_xlfn.CONCAT(A55,B55) -> MOMWFM | D55: Applications/Tools
A56: MOM | B56: BSS | C56: =_xlfn.CONCAT(A56,B56) -> MOMBSS | D56: Applications/Tools
A57: MOM | B57: OSS | C57: =_xlfn.CONCAT(A57,B57) -> MOMOSS | D57: Applications/Tools
A58: MOM | B58: GIS | C58: =_xlfn.CONCAT(A58,B58) -> MOMGIS | D58: Applications/Tools
A59: MOM | B59: PM Tool Issue | C59: =_xlfn.CONCAT(A59,B59) -> MOMPM Tool Issue | D59: Applications
A60: MOM | B60: T&D Environment | C60: =_xlfn.CONCAT(A60,B60) -> MOMT&D Environment | D60: Applications
A61: MOM | B61: GPON | C61: =_xlfn.CONCAT(A61,B61) -> MOMGPON | D61: GPON
A62: MOM | B62: DR | C62: =_xlfn.CONCAT(A62,B62) -> MOMDR | D62: DR
A63: MOM | B63: Helpdesk | C63: =_xlfn.CONCAT(A63,B63) -> MOMHelpdesk | D63: Helpdesk (Contact Center)
A64: MOM | B64: Field Related | C64: =_xlfn.CONCAT(A64,B64) -> MOMField Related | D64: Field Related issues
... A83: NOC | B83: NSO | C83: =_xlfn.CONCAT(A83,B83) -> NOCNSO | D83: Applications/Tools

Sheet Sheet1
A1: Category | B1: MOM
A2: Owner(L&T) | B2: (All)
A4: Count of Owner(L&T) | B4: Column Labels
A5: Row Labels | C5: Closed | D5: CLOSURE REVIEW PENDING | E5: COMPLETED & APPROVED | F5: Dependancy on NSO, part of 472-points, Point No. 103 & 237 | G5: Dependancy on NSO, part of 472-points, Point No. 104 & 238 | H5: DEPENDENCY(Client/Ext.) | I5: OPEN | J5: WIP | K5: (blank) | L5: Completed | M5: COMPLETED | N5: NOT FEASIBLE | O5: DUPLICATE POINT (M688) | P5: DUPLICATE POINT (M739) | Q5: NOT_FEASIBLE | R5: Grand Total
A6: All Domain | B6: 1 | R6: 1
A7: BSS | I7: 344 | J7: 5 | L7: 12 | O7: 1 | P7: 1 | R7: 363
A8: DC-IT | I8: 1 | R8: 1
A9: DR | E9: 1 | I9: 2 | R9: 3
A10: DWDM | F10: 1 | G10: 1 | R10: 2
A11: Field Related | B11: 23 | I11: 1 | R11: 24
A12: GIS | I12: 1 | J12: 3 | L12: 35 | M12: 7 | N12: 8 | R12: 54
A13: GPON | E13: 1 | H13: 2 | J13: 1 | R13: 4
A14: Helpdesk | D14: 58 | E14: 3 | I14: 1 | J14: 21 | R14: 83
A15: IP/MPLS | B15: 1 | C15: 2 | R15: 3
A16: NOC Operationalization | B16: 163 | C16: 77 | E16: 1 | I16: 23 | K16: 6 | L16: 1 | R16: 271
A17: NSO | B17: 55 | R17: 55
A18: OEM Related | B18: 100 | R18: 100
A19: OSS | I19: 4 | J19: 10 | L19: 25 | M19: 3 | Q19: 2 | R19: 44
A20: PM Tool Issue | B20: 1 | L20: 1 | R20: 2
A21: WFM | B21: 23 | C21: 1 | I21: 6 | J21: 2 | L21: 55 | M21: 3 | N21: 7 | R21: 97
A22: Security & Regulatory Compliance | B22: 157 | I22: 1 | R22: 158
A23: T&D Environment | B23: 1 | D23: 4 | E23: 5 | I23: 2 | R23: 12
A24: IPDR | B24: 1 | R24: 1
A25: Grand Total | B25: 526 | C25: 80 | D25: 62 | E25: 11 | F25: 1 | G25: 1 | H25: 2 | I25: 386 | J25: 42 | K25: 6 | L25: 129 | M25: 13 | N25: 15 | O25: 1 | P25: 1 | Q25: 2 | R25: 1278

Sheet All Domain Summary
E3: =SUBTOTAL(9,E6:E22) -> 2429 | F3: =SUBTOTAL(9,F6:F22) -> 588 | G3: =SUBTOTAL(9,G6:G22) -> 469 | H3: =SUBTOTAL(9,H6:H22) -> 5 | I3: =SUBTOTAL(9,I6:I22) -> 1 | J3: =SUBTOTAL(9,J6:J22) -> 2 | K3: =SUBTOTAL(9,K6:K22) -> 6 | L3: =SUBTOTAL(9,L6:L22) -> 25 | ... P3: =SUBTOTAL(9,P6:P22) -> 3 | S3: =SUBTOTAL(9,S6:S22) -> 362 | T3: =SUBTOTAL(9,T6:T22) -> 1 | U3: =SUBTOTAL(9,U6:U22) -> 41 | V3: =SUBTOTAL(9,V6:V22) -> 3 | W3: =SUM(F3:V3) -> 1527
C4: Domain | D4: Owner | E4: Total Points | F4: Closed Points | G4: Artefacts to be updated | H4: Dependancy | S4: WIP | U4: Duplicate | V4: Not Feasible
H5: HPE | I5: Nokia | J5: Tejas | K5: Tejas & Nokia | L5: Nokia & NSO | M5: NSO | N5: T Fiber | O5: T Fiber, TPA,L&T | P5: All Packages | Q5: Project | R5: O&M | S5: L&T | T5: TPA
C6: DWDM | D6: Suresh Kumar | E6: 28 | F6: 14 | G6: 0 | H6: 1 | I6: 0 | J6: 0 | K6: 0 | L6: 0 | M6: 3 | N6: 5 | O6: 0 | P6: 1 | S6: 1 | T6: 1 | U6: 2
C7: GPON | D7: Sayed Pasha | E7: 156 | F7: 107 | G7: 0 | H7: 0 | I7: 1 | J7: 2 | K7: 6 | L7: 25 | M7: 2 | N7: 0 | O7: 0 | P7: 2 | S7: 1 | T7: 0 | U7: 12
C8: NOC Operations | D8: Ahmad Siddiqui | E8: 58 | F8: 45 | G8: 0 | H8: 0 | I8: 0 | J8: 0 | K8: 0 | L8: 0 | M8: 0 | N8: 0 | O8: 0 | P8: 0 | S8: 13 | T8: 0 | U8: 0
C9: NSO | D9: Jayanth | E9: 119 | F9: 1
C10: GIS | D10: Kaushalendra Kumar | E10: 106 | F10: 51 | G10: 38 | H10: 3 | I10: 0 | J10: 0 | K10: 0 | L10: 0 | M10: 0 | N10: 0 | O10: 0 | P10: 0 | S10: 6 | T10: 0 | U10: 6 | V10: 1
C11: WFM | D11: Kaushalendra Kumar | E11: 114 | F11: 0 | G11: 83 | H11: 1 | I11: 0 | J11: 0 | K11: 0 | L11: 0 | M11: 0 | N11: 0 | O11: 0 | P11: 0 | S11: 15 | T11: 0 | U11: 13 | V11: 2
C12: old BSS | D12: Sandeep Deshmukh | E12: 528
C13: New BSS | D13: Sandeep Deshmukh | E13: 20 | S13: 20
C14: DC Active Infra | D14: Ravi Kishore | E14: 51 | F14: 29 | G14: 0
C15: DC Network and IPMPLS | D15: R S Rao | E15: 35 | F15: 30 | G15: 0 | H15: 0 | I15: 0 | J15: 0 | K15: 0 | L15: 0 | M15: 0 | N15: 2 | O15: 1 | P15: 0 | S15: 2 | T15: 0 | U15: 0
C16: Project Execution | D16: Srinivas Kodali | E16: 30 | Q16: 23 | R16: 7 | S16: 0 | T16: 0 | U16: 0 | V16: 0
C17: Service Delivery Head | D17: Siva Prasad | E17: 308 | F17: 164 | G17: 25 | H17: 0 | I17: 0 | J17: 0 | K17: 0 | L17: 0 | M17: 0 | N17: 0 | O17: 0 | P17: 0 | S17: 119 | T17: 0 | U17: 0
C18: Security | D18: Bajiba Shaik | E18: 199 | F18: 51 | G18: 0
C19: Helpdesk | D19: Siva Kumar | E19: 136 | F19: 73 | G19: 0 | H19: 0 | I19: 0 | J19: 0 | K19: 0 | L19: 0 | M19: 0 | N19: 0 | O19: 0 | P19: 0 | S19: 63 | T19: 0 | U19: 0
C20: DC Passive Infra | D20: Srinivas Kommreddy | E20: 3
C21: OSS | D21: Venkatesh | E21: 536 | F21: 21 | G21: 323 | N21: 8 | S21: 122 | U21: 8
D22: T Fiber | E22: 2 | F22: 2 | G22: 0 | H22: 0 | I22: 0 | J22: 0 | K22: 0 | L22: 0 | M22: 0 | N22: 0 | O22: 0 | P22: 0 | S22: 0 | T22: 0 | U22: 0
F32: COMPLETED & APPROVED

Sheet Master_Tracker(2428)
Y1: =SUBTOTAL(3,Y3:Y2430) -> 274
B2: Slno | C2: UniqueID | D2: Category | E2: Meeting Date | F2: Priority | G2: Ramana | H2: Ramana-Domain | I2: Domain | J2: Sub-Domain | K2: Action Point | L2: Impact | M2: Priority | N2: Baseline Status | O2: xx | P2: Application | Q2: Module | R2: Remarks | S2: Remarks | T2: Organization | U2: Owner | V2: Owner(L&T) | W2: Target Date to Complete | X2: Open | Y2: Revised Status (L&T) As on 18-Sep-2025 | Z2: Approved BY (TF) | AA2: Approval Date(TF) | AB2: Link of evidences | AC2: R | AD2: S | AE2: T | AF2: U | AG2: V | AH2: W | AI2: X | AJ2: Tfiber-Cat | AK2: Derived Status (L&T) | AL2: OSS | AM2: OSS Remarks | AN2: Ramana Remarks as on 19-Sep-2025 | AO2: T Fiber Appoved Date | AP2: Artefacts | AQ2: Target Date | AR2: Qty
B3: 1 | C3: T1 | D3: 472 | E3: NA | I3: Security & Regulatory Compliance | J3: Configuration | K3: Integration testing of All supported devices is complete and adding all the devices is underway. | N3: Open | S3: what ever request has come all are integrated with ISE , any new device request comes same will be added . Also Aleppo PO get relaesed for ADintegration , it will also get integrated with AD. | V3: Sarmendra | X3: Open | Y3: DEPENDENCY(Client/Ext.) | AI3: =_xlfn.CONCAT(D3,I3) -> 472Security & Regulatory Compliance | AJ3: =VLOOKUP(AI3,Table1[[#All],[CONCAT]:[Tfiber]],2,FALSE) -> Security | AK3: OPEN | AR3: 1
B4: 2 | C4: T2 | D4: 472 | E4: NA | I4: DWDM | J4: Integration with Alepo | K4: RADIUS Configuration Testing on Ciena Node & EMS (MCP) | N4: Colosed | V4: Suresh Kumar | Y4: COMPLETED & APPROVED | Z4: AD-UT-Tfiber | AA4: 45783 | AB4: \\172.28.9.34\Artefacts_T-Fiber TNOC Tracker\DWDM\Artefact - T106 | AI4: =_xlfn.CONCAT(D4,I4) -> 472DWDM | AJ4: =VLOOKUP(AI4,Table1[[#All],[CONCAT]:[Tfiber]],2,FALSE) -> DWDM | AK4: CLOSED | AO4: 45783 | AP4: \\172.28.9.34\Artefacts_T-Fiber TNOC Tracker\DWDM\Artefact - T106 | AR4: 1
B5: 3 | C5: T3 | D5: 472 | E5: NA | I5: Security & Regulatory Compliance | J5: Integration | K5: Accouting data from Ciena MCP and field nodes to be captured in Alepo AAA | M5: Critical | N5: Open | S5: MCP upgradation is in pipeline . same will be completed by 25 Sep 2025 | V5: Sarmendra | X5: Open | Y5: WIP | AI5: =_xlfn.CONCAT(D5,I5) -> 472Security & Regulatory Compliance | AJ5: =VLOOKUP(AI5,Table1[[#All],[CONCAT]:[Tfiber]],2,FALSE) -> Security | AK5: OPEN | AR5: 1
B6: 4 | C6: T3 | D6: 472 | E6: NA | I6: DWDM | J6: Integration with Alepo | K6: TACACS+/Radius testing for AAA on ciena node | N6: Open | S6: 20-09-2025: 8.1 MCP software Patch upgradation will be completed by 27-Sep-25, After completetion of upgrdation AAA functionalities will be tested for ciena devices by using radius 13-09-25:MCP upgradation is in progress, will be able to check the logs by next week 28-08-2025: Activity is in progress, target to complete by 25th Sep'25 Authentication and Authorization tested and found OK for Node and MCP. 19-08-2025: Due to issue in disk partition and file type of storage, activity is not started 10-08-2025: OEM confirmation recieved and activity is planned from 18th August'25. 05-July-2025: DC OSS to DR MCP communication is through now, need to integrate and test before activity 12-July-2025: DC OSS to DR MCP integration testing done. Alarms and Autoticketing functioning as expected. Upgradation activity will be scheduled as per OEM confirmation, Target date - 30-07-25 26-July-2025: Schedule awaited from OEM 30-June-2025: DC OSS to DR MCP connectivity to be extended for PE approval, WIP. Target date - 30-07-25 15-06-25: Targeting to close the upgradation by month end, 30-06-25 30-05-2025: Accounting issue resolved in latest MCP version, verified in 8.2 Ver (Node logs are now capturing in MCP). Upgradation schedule awaited from Teleindia for our MCP from 7.1-P02 5/21/2025: Correlation to identified to find the user logged in at the specific time 28APR'25: As discussed with Sanjay sir, if user id not avaialble pls. try for correlation with IP. Some how Correlation to be done. In Accounting, Node and MCP logs are successfully reporting in Alepo with below limitation. Node Logs - Active profile name (ADMIN/RADIUS) is displayed against User ID (Ciena confirmed it is as per design no changes are possible) | T6: L&T | V6: Suresh Kumar | X6: Open | Y6: WIP | AI6: =_xlfn.CONCAT(D6,I6) -> 472DWDM | AJ6: =VLOOKUP(AI6,Table1[[#All],[CONCAT]:[Tfiber]],2,FALSE) -> DWDM | AK6: OPEN | AR6: 1
B7: 5 | C7: T4 | D7: 472 | E7: NA | I7: Security & Regulatory Compliance | J7: Security | K7: Alepo confirmed that Alepo AAA supports TACACS, Alepo to test Nokia and Ciena nodes integration on TACACS , with supporting artefacts of testing. 1.TACACS Testing with Tejas, Nokia, Ciena 2. Alepo Testing with Tejas, Nokia and Ciena | N7: Open | S7: 1.TACACS Testing with Tejas, Nokia, Ciena completed 2. Alepo Testing with Tejas, Nokia and Ciena | V7: Sarmendra | Y7: CLOSURE REVIEW PENDING | AI7: =_xlfn.CONCAT(D7,I7) -> 472Security & Regulatory Compliance | AJ7: =VLOOKUP(AI7,Table1[[#All],[CONCAT]:[Tfiber]],2,FALSE) -> Security | AK7: OPEN | AP7: Artefacts to be Submitted | AR7: 1
B8: 6 | C8: T5 | D8: 472 | E8: NA | I8: Security & Regulatory Compliance | J8: Functional AT | K8: Had a meeting with Ashwani from Alepo and sent him updated test cases. He is working on data gathering and will send us back by Tuesday. | N8: Open | S8: FAT were submitted to customer, Customer observation in being work out. Target to resubmission.- 23.07.25 | V8: Sarmendra | Y8: CLOSURE REVIEW PENDING | AI8: =_xlfn.CONCAT(D8,I8) -> 472Security & Regulatory Compliance | AJ8: =VLOOKUP(AI8,Table1[[#All],[CONCAT]:[Tfiber]],2,FALSE) -> Security | AK8: OPEN | AP8: Artefacts to be Submitted | AR8: 1
B9: 7 | C9: T6 | D9: 472 | E9: NA | I9: BSS | J9: Installation | K9: Installation of BSS Application | N9: Open | S9: 29-08-2025: Design and Solution document to be shared with GM NOC and Physical instllation of BSS need to validate according to solution from L&T Side before submitting for for review with T Fiber 26-06-2025: We have offered Installation AT. TFIBER has asked DC architecture review including license validity | V9: Manoj Nibrad | X9: Open | Y9: Open | AI9: =_xlfn.CONCAT(D9,I9) -> 472BSS | AJ9: =VLOOKUP(AI9,Table1[[#All],[CONCAT]:[Tfiber]],2,FALSE) -> Applications/Tools | AK9: OPEN | AR9: 1
B10: 8 | C10: T7 | D10: 472 | E10: NA | I10: BSS | J10: Integration | K10: Initial Integration with Third Party Applications (OSS & NSO) | N10: Open | S10: 26-06-2025: OSS Integration is done. NSO integration is pending. Awaiting NSO Team. | V10: Manoj Nibrad | X10: Open | Y10: Open | AI10: =_xlfn.CONCAT(D10,I10) -> 472BSS | AJ10: =VLOOKUP(AI10,Table1[[#All],[CONCAT]:[Tfiber]],2,FALSE) -> Applications/Tools | AK10: OPEN | AR10: 1
B11: 9 | C11: T8 | D11: 472 | E11: NA | I11: BSS | J11: Integration | K11: OSS interfaces | N11: Open | S11: 26-06-2025: Feasibility API & Ticket API integration is completed. | V11: Manoj Nibrad | X11: Open | Y11: Open | AI11: =_xlfn.CONCAT(D11,I11) -> 472BSS | AJ11: =VLOOKUP(AI11,Table1[[#All],[CONCAT]:[Tfiber]],2,FALSE) -> Applications/Tools | AK11: OPEN | AR11: 1
B12: 10 | C12: T9 | D12: 472 | E12: NA | I12: BSS | J12: Integration | K12: NSO interfaces | N12: Open | S12: 26-06-2025: Awaiting NSO Team | V12: Manoj Nibrad | X12: Open | Y12: Open | AI12: =_xlfn.CONCAT(D12,I12) -> 472BSS | AJ12: =VLOOKUP(AI12,Table1[[#All],[CONCAT]:[Tfiber]],2,FALSE) -> Applications/Tools | AK12: OPEN | AR12: 1
B13: 11 | C13: T10 | D13: 472 | E13: NA | I13: BSS | J13: Integration | K13: GeM Portal | N13: Open | V13: Manoj Nibrad | X13: Open | Y13: Open | Z13: On-Hold confirmation mail received from NOC Director | AA13: 45854 | AB13: \\172.28.9.34\share drive\Artefacts_T-Fiber TNOC Tracker\BSS\Artifact_T10 | AI13: =_xlfn.CONCAT(D13,I13) -> 472BSS | AJ13: =VLOOKUP(AI13,Table1[[#All],[CONCAT]:[Tfiber]],2,FALSE) -> Applications/Tools | AK13: CLOSED | AO13: 45854 | AP13: \\172.28.9.34\share drive\Artefacts_T-Fiber TNOC Tracker\BSS\Artifact_T10 | AR13: 1
B14: 12 | C14: T11 | D14: 472 | E14: NA | I14: BSS | J14: Development and unit testing | K14: Import Sub-Departments, Import Leads, Campaign Management, Opportunity/Quote/order Management, order booking and Service Order workflow for tested services | N14: Open | S14: 29-08-2025: All points are completed Import Sub-Departments, Import Leads, Opportunity/Quote/order Management, order booking and Service Order workflow for tested services Demo to be conducted to TFIBER. "Campaign Management" is Pending where inputs are required from TFIBER Business team 26-06-2025: Awaiting few inputs from TFIBER | V14: Manoj Nibrad | X14: Open | Y14: Open | AI14: =_xlfn.CONCAT(D14,I14) -> 472BSS | AJ14: =VLOOKUP(AI14,Table1[[#All],[CONCAT]:[Tfiber]],2,FALSE) -> Applications/Tools | AK14: OPEN | AR14: 1
B15: 13 | C15: T12 | D15: 472 | E15: NA | I15: BSS | J15: Development and unit testing | K15: Product/Service Catalogue integration | N15: Open | S15: 29-08-2025: Feature is available to admin User(Product Team) to configure new product based on requirement. BSS Team will provide Demo to the TFIBER (business team([Uday]/Solution Team[Sanjay]) for their acceptance. 26-06-2025: Artifacts submitted. Closure review is pending with TFIBER | V15: Manoj Nibrad | X15: Open | Y15: Open | AI15: =_xlfn.CONCAT(D15,I15) -> 472BSS | AJ15: =VLOOKUP(AI15,Table1[[#All],[CONCAT]:[Tfiber]],2,FALSE) -> Applications/Tools | AK15: OPEN | AR15: 1
B16: 14 | C16: T13 | D16: 472 | E16: NA | I16: BSS | J16: Development and unit testing | K16: Billing, Discounts & Adjustments, Invoice generation, Bill Formatting | N16: Open | S16: 29-08-2025: Feature is made available in the BSS application, BSS Team will provide demo to TFIBER Team (Business [Uday] & Finance[Bhaskar]) 26-06-2025: Artifacts submitted. Closure review is pending with TFIBER | V16: Manoj Nibrad | X16: Open | Y16: Open | AI16: =_xlfn.CONCAT(D16,I16) -> 472BSS | AJ16: =VLOOKUP(AI16,Table1[[#All],[CONCAT]:[Tfiber]],2,FALSE) -> Applications/Tools | AK16: OPEN | AR16: 1
B17: 15 | C17: T14 | D17: 472 | E17: NA | I17: BSS | J17: Development and unit testing | K17: Feasibility API response from OSS for service provisioning request | N17: Open | S17: 29-08-2025: Feaibility API is already integrated with BSS and demonstrated in GIBB demo and it is applicable for all products. 26-06-2025: Artifacts submitted. Closure review is pending with TFIBER | V17: Manoj Nibrad | X17: Open | Y17: Open | AI17: =_xlfn.CONCAT(D17,I17) -> 472BSS | AJ17: =VLOOKUP(AI17,Table1[[#All],[CONCAT]:[Tfiber]],2,FALSE) -> Applications/Tools | AK17: OPEN | AR17: 1
B18: 16 | C18: T15 | D18: 472 | E18: NA | I18: BSS | J18: Development and unit testing | K18: SMS notification, email gateway, Field engineer mobile app readiness | N18: Open | S18: 29-08-2025: Integration is already completed and applicable for all product same has demonstrated to TFIBER during GIBB demo session. 26-06-2025: Artifacts submitted. Closure review is pending with TFIBER | V18: Manoj Nibrad | X18: Open | Y18: Open | AI18: =_xlfn.CONCAT(D18,I18) -> 472BSS | AJ18: =VLOOKUP(AI18,Table1[[#All],[CONCAT]:[Tfiber]],2,FALSE) -> Applications/Tools | AK18: OPEN | AR18: 1
B19: 17 | C19: T16 | D19: 472 | E19: NA | I19: BSS | J19: Development and unit testing | K19: Service Assurance and trouble tickets | N19: Open | S19: 29-08-2025: Integration with Service Manager is done for technical ticket and BSS have functionality to handle the non-technical ticket in BSS itself. BSS team will demonstrate this functionality to TFIBER. Sanjay Sir needs to confirm demo date. 26-06-2025: Artifacts submitted. Closure review is pending with TFIBER | V19: Manoj Nibrad | X19: Open | Y19: Open | AI19: =_xlfn.CONCAT(D19,I19) -> 472BSS | AJ19: =VLOOKUP(AI19,Table1[[#All],[CONCAT]:[Tfiber]],2,FALSE) -> Applications/Tools | AK19: OPEN | AR19: 1
B20: 18 | C20: T17 | D20: 472 | E20: NA | I20: BSS | J20: Development and unit testing | K20: Customer Self care portal development for T-CELL, T-NET, L0 | N20: Open | S20: 29-08-2025: Webportal is available. BSS team needs to demonstrate to TFIBER team. Sanjay Sir needs to confirm demo date. 26-06-2025: Artifacts submitted. Closure review is pending with TFIBER | V20: Manoj Nibrad | X20: Open | Y20: Open | AI20: =_xlfn.CONCAT(D20,I20) -> 472BSS | AJ20: =VLOOKUP(AI20,Table1[[#All],[CONCAT]:[Tfiber]],2,FALSE) -> Applications/Tools | AK20: OPEN | AR20: 1
B21: 19 | C21: T18 | D21: 472 | E21: NA | I21: BSS | J21: Integration | K21: Integration modules Like on board Un-Assist & dependent module to be completed for all products from system to be initiated a workshop and to be closed in next 2 Weeks | N21: Open | S21: 29-08-2025: Seek input from Business team (Uday) and deploy post assisted completion. 26-06-2025: Input awaited from TFIBER | V21: Manoj Nibrad | X21: Open | Y21: Open | AI21: =_xlfn.CONCAT(D21,I21) -> 472BSS | AJ21: =VLOOKUP(AI21,Table1[[#All],[CONCAT]:[Tfiber]],2,FALSE) -> Applications/Tools | AK21: OPEN | AR21: 1
B22: 20 | C22: T19 | D22: 472 | E22: NA | I22: BSS | J22: MoM Action | K22: T-Cell service definition for workflow implementation in BSS for creating Spoke primary and secondary | N22: Open | S22: 29-08-2025:Update product concept note similar to GIBB and share with TFIBER for review 26-06-2025: We can deliver this post getting product concept note from TFIBER | V22: Manoj Nibrad | X22: Open | Y22: Open | AI22: =_xlfn.CONCAT(D22,I22) -> 472BSS | AJ22: =VLOOKUP(AI22,Table1[[#All],[CONCAT]:[Tfiber]],2,FALSE) -> Applications/Tools | AK22: OPEN | AR22: 1
B23: 21 | C23: T20 | D23: 472 | E23: NA | I23: BSS | J23: Development and unit testing | K23: Rules for primary and secondary spoke implementation in BSS- - GP with shortest distance will be primary - To display dropdown and concerned user group to select and confirm | N23: Open | S23: #N/A | V23: Manoj Nibrad | X23: Open | Y23: Open | AI23: =_xlfn.CONCAT(D23,I23) -> 472BSS | AJ23: =VLOOKUP(AI23,Table1[[#All],[CONCAT]:[Tfiber]],2,FALSE) -> Applications/Tools | AK23: OPEN | AP23: #N/A | AR23: 1
B24: 22 | C24: T21 | D24: 472 | E24: NA | I24: BSS | J24: MoM Action | K24: BSS firewall ports required for Security compliance | N24: Open | S24: BSS has to forward list of Port as per deiffrent modules of application | V24: Sarmendra | X24: Open | Y24: WIP | AI24: =_xlfn.CONCAT(D24,I24) -> 472BSS | AJ24: =VLOOKUP(AI24,Table1[[#All],[CONCAT]:[Tfiber]],2,FALSE) -> Applications/Tools | AK24: OPEN | AR24: 1
B25: 23 | C25: T22 | D25: 472 | E25: NA | I25: BSS | J25: Security | K25: Roadmap for password policy implementation in CSP | N25: Open | S25: Ciriteria for Paswword policy hase been Shared wioth BSS team . BSS team has to implement and submit report for verifications. | V25: Sarmendra | X25: Open | Y25: WIP | AI25: =_xlfn.CONCAT(D25,I25) -> 472BSS | AJ25: =VLOOKUP(AI25,Table1[[#All],[CONCAT]:[Tfiber]],2,FALSE) -> Applications/Tools | AK25: OPEN | AR25: 1
B26: 24 | C26: T23 | D26: 472 | E26: NA | I26: BSS | J26: Security | K26: DMZ requirements for CSP | N26: Open | S26: IP amd URL required by BSS foir NAT through DMZ has been Completed | V26: Sarmendra | X26: Open | Y26: WIP | AI26: =_xlfn.CONCAT(D26,I26) -> 472BSS | AJ26: =VLOOKUP(AI26,Table1[[#All],[CONCAT]:[Tfiber]],2,FALSE) -> Applications/Tools | AK26: OPEN | AR26: 1
B27: 25 | C27: T24 | D27: 472 | E27: NA | I27: BSS | J27: MoM Action | K27: PoP location confirmation usergroup for connectivity to O&M | N27: Open | S27: 29-08-2025: Seek input from O&M team (Umesh) 26-06-2025: Input awaited from TFIBER | V27: Manoj Nibrad | X27: Open | Y27: Open | AI27: =_xlfn.CONCAT(D27,I27) -> 472BSS | AJ27: =VLOOKUP(AI27,Table1[[#All],[CONCAT]:[Tfiber]],2,FALSE) -> Applications/Tools | AK27: OPEN | AR27: 1
B28: 26 | C28: T25 | D28: 472 | E28: NA | I28: BSS | J28: MoM Action | K28: Product concept note configuration in BSS queries to be shared | N28: Open | S28: 29-08-2025: Queries to be prepared and share with TFIBER for discussion. 17-07-2025: Business Team of TFIBER needs to finalize and confirm all product. 26-06-2025: Need Product concept note from TFIBER | V28: Manoj Nibrad | X28: Open | Y28: Open | AI28: =_xlfn.CONCAT(D28,I28) -> 472BSS | AJ28: =VLOOKUP(AI28,Table1[[#All],[CONCAT]:[Tfiber]],2,FALSE) -> Applications/Tools | AK28: OPEN | AR28: 1
B29: 27 | C29: T26 | D29: 472 | E29: NA | I29: BSS | J29: MoM Action | K29: Location id logic for NSO provisioning | N29: Open | S29: 29-08-2025: Ciruit ID logic PPT shared by Sivakumar, needs to use and implement in BSS. 26-06-2025: Timeline 30th July is considering NSO support is available in 2-3 days | V29: Manoj Nibrad | X29: Open | Y29: Open | AI29: =_xlfn.CONCAT(D29,I29) -> 472BSS | AJ29: =VLOOKUP(AI29,Table1[[#All],[CONCAT]:[Tfiber]],2,FALSE) -> Applications/Tools | AK29: OPEN | AR29: 1
B30: 28 | C30: T27 | D30: 472 | E30: NA | I30: BSS | J30: Integration | K30: Tariff plan parameters viz. 5G, 4G finalisation. (BSS should capture QOS parameter & Requirements) | N30: Open | S30: 29-08-2025: Product Can be configured in BSS product catalogue Demo to be given to TFIBER 26-06-2025: Input awaited from TFIBER | V30: Manoj Nibrad | X30: Open | Y30: Open | AI30: =_xlfn.CONCAT(D30,I30) -> 472BSS | AJ30: =VLOOKUP(AI30,Table1[[#All],[CONCAT]:[Tfiber]],2,FALSE) -> Applications/Tools | AK30: OPEN | AR30: 1
B31: 29 | C31: T28 | D31: 472 | E31: NA | I31: IP/MPLS | J31: Functional AT | K31: Internal AT 83% complete. Waiting Cisco to update data sent by Vikram and then we will submit to TPA ( for pending cases, we just need a maintanence window to test as it is impacting activity) This is for ISE | N31: Open | S31: FAT documents were submitted to TPA , However it has some common observation which will be discussed with TPA team by Mr Sharma. Subsequently , correction will be made in FAT doc | V31: Sarmendra | X31: Open | Y31: WIP | AI31: =_xlfn.CONCAT(D31,I31) -> 472IP/MPLS | AJ31: =VLOOKUP(AI31,Table1[[#All],[CONCAT]:[Tfiber]],2,FALSE) -> IPMPLS | AK31: OPEN | AR31: 1
B32: 30 | C32: T29 | D32: 472 | E32: NA | I32: IP/MPLS | J32: Functional AT | K32: CSM is having memory issues. Need to sort it out before we do AT. Working on settling that with Cisco. Memory will be allocated and tested in the first week of July | N32: Open | S32: CSM has been replaced by ASDM | V32: Sarmendra | X32: Open | Y32: WIP | AI32: =_xlfn.CONCAT(D32,I32) -> 472IP/MPLS | AJ32: =VLOOKUP(AI32,Table1[[#All],[CONCAT]:[Tfiber]],2,FALSE) -> IPMPLS | AK32: OPEN | AR32: 1
B33: 31 | C33: T30 | D33: 472 | E33: NA | I33: IP/MPLS | J33: Functional AT | K33: Internal AT 72% complete. Waiting on Cisco to update data sent by Vikram and then we will submit to TPA. ( for pending cases, we just need a maintanence window to test as it is impacting activity) | N33: Open | S33: FAT documents were submitted to TPA , However it has some common observation which will be discussed with TPA team by Mr Sharma. Subsequently , correction will be made in FAT doc | V33: Sarmendra | X33: Open | Y33: WIP | AI33: =_xlfn.CONCAT(D33,I33) -> 472IP/MPLS | AJ33: =VLOOKUP(AI33,Table1[[#All],[CONCAT]:[Tfiber]],2,FALSE) -> IPMPLS | AK33: OPEN | AR33: 1
B34: 32 | C34: T31 | D34: 472 | E34: NA | I34: Security & Regulatory Compliance | J34: Security | K34: Internal Audit for all applications | N34: Open | S34: Application audited partally , howver PT audit couldnot be done due to lack of necessary tools. Same has been requested with LTTS team , but it could not be materialised. | V34: Sarmendra | X34: Open | Y34: WIP | AI34: =_xlfn.CONCAT(D34,I34) -> 472Security & Regulatory Compliance | AJ34: =VLOOKUP(AI34,Table1[[#All],[CONCAT]:[Tfiber]],2,FALSE) -> Security | AK34: OPEN | AR34: 1
B35: 33 | C35: T32 | D35: 472 | E35: NA | I35: Security & Regulatory Compliance | J35: Security | K35: Internal audit for network elements | N35: Open | S35: Network elemants auditted including NOC end points , However PT for same is pending. | V35: Sarmendra | X35: Open | Y35: WIP | AI35: =_xlfn.CONCAT(D35,I35) -> 472Security & Regulatory Compliance | AJ35: =VLOOKUP(AI35,Table1[[#All],[CONCAT]:[Tfiber]],2,FALSE) -> Security | AK35: OPEN | AR35: 1
... B38: 36 | C38: T35 | D38: 472 | E38: NA | I38: IP/MPLS | J38: Security | K38: external audit for network elements(Tfiber will be arranging a partner for third party audit) | N38: Open | S38: Awaited TSTG Audit party to engage | V38: Sarmendra | X38: Open | Y38: DEPENDENCY(Client/Ext.) | AI38: =_xlfn.CONCAT(D38,I38) -> 472IP/MPLS | AJ38: =VLOOKUP(AI38,Table1[[#All],[CONCAT]:[Tfiber]],2,FALSE) -> IPMPLS | AK38: OPEN | AR38: 1
B39: 37 | C39: T36 | D39: 472 | E39: NA | I39: Security & Regulatory Compliance | J39: Security | K39: Physical user access | N39: Open | S39: Has completed , Artefacts will be resubmitted. | V39: Sarmendra | X39: Open | Y39: REOPENED | AB39: \\172.28.9.34\Artefacts_T-Fiber TNOC Tracker\NW-Security\T36 | AI39: =_xlfn.CONCAT(D39,I39) -> 472Security & Regulatory Compliance | AJ39: =VLOOKUP(AI39,Table1[[#All],[CONCAT]:[Tfiber]],2,FALSE) -> Security | AK39: OPEN | AP39: \\172.28.9.34\Artefacts_T-Fiber TNOC Tracker\NW-Security\T36 | AR39: 1
B40: 38 | C40: T37 | D40: 472 | E40: NA | I40: Security & Regulatory Compliance | J40: Security | K40: Virtual user access-VPN | N40: Open | S40: Has completed , Artefacts will be resubmitted. | V40: Sarmendra | X40: Open | Y40: REOPENED | AI40: =_xlfn.CONCAT(D40,I40) -> 472Security & Regulatory Compliance | AJ40: =VLOOKUP(AI40,Table1[[#All],[CONCAT]:[Tfiber]],2,FALSE) -> Security | AK40: OPEN | AR40: 1
B41: 39 | C41: T38 | D41: 472 | E41: NA | I41: Security & Regulatory Compliance | J41: Security | K41: Role based severity access | N41: Open | S41: Completed and Review pending. Artfacts submitted | V41: Sarmendra | X41: Open | Y41: WIP | AI41: =_xlfn.CONCAT(D41,I41) -> 472Security & Regulatory Compliance | AJ41: =VLOOKUP(AI41,Table1[[#All],[CONCAT]:[Tfiber]],2,FALSE) -> Security | AK41: OPEN | AR41: 1
B42: 40 | C42: T39 | D42: 472 | E42: NA | I42: Security & Regulatory Compliance | J42: Security | K42: ISE integration with Cisco elements | N42: Open | S42: Artefacts will be submitted. | V42: Sarmendra | Y42: CLOSURE REVIEW PENDING | AI42: =_xlfn.CONCAT(D42,I42) -> 472Security & Regulatory Compliance | AJ42: =VLOOKUP(AI42,Table1[[#All],[CONCAT]:[Tfiber]],2,FALSE) -> Security | AK42: OPEN | AP42: Artefacts to be Submitted | AR42: 1
B43: 41 | C43: T40 | D43: 472 | E43: NA | I43: Security & Regulatory Compliance | J43: Regulatory | K43: Regulatory Compliance with respect DoT policies 1. Security Policy-Complied 2. Security Architecture of Telecom Network-Complied 3. Information Security Risk Assessment and Risk Treatment processes and their implementation plan-WIP, Target: Dec 2024 reviewed with customer. 4. Recruitment processes and employee's record-WIP, Target:12-10-2025 5. Controls for effectiveness of security management-WIP, Target: 28 -02-2025 6. Evidence of monitoring, measurement results and management reviews of security management-WIP, Target: 28-02-2025 7. Security Audit programs and audit results-Complied 8. Inventory management and classification of information assets and their handling Completed 9. Procedure for responding to information and network security incidents-WIP, Target: 28-02-2025 - SIRT reviewed 10. Main S/W updation and changes-WIP, Target: 28-02-2025 11. Supply chain of products (HW/SW). To be taken from manufacturer/supplier-Communicated to Sekhar. WIP, Target: 14-02-2025 12. SW details and documentation obtained from manufacturers/supplier-Communicated to Sekhar WIP, Target: 14-02-2025 13. O&M procedures in the form of manual-O&M manual and OEM wise manuals WIP, Target: 14-02-2025 14. Processes for internal and external communication relevant to the security management-WIP, Target: 07-3-2025 | N43: Open | S43: Confirmation of purchase of ISE. License needed to upgrade for HA | V43: Sarmendra | X43: Open | Y43: DEPENDENCY(Client/Ext.) | AI43: =_xlfn.CONCAT(D43,I43) -> 472Security & Regulatory Compliance | AJ43: =VLOOKUP(AI43,Table1[[#All],[CONCAT]:[Tfiber]],2,FALSE) -> Security | AK43: OPEN | AP43: #VALUE! | AR43: 1
B44: 42 | C44: T41 | D44: 472 | E44: NA | I44: DC-IT | J44: Servers and Strorage (Deployment and Installations) | K44: 1. Compute & Storage | N44: Open | S44: 11-Oct-25: As per the OEM's/SME's request, storage is allocated as per requirements. Artifacts are Captured. OEM Confirmation Emails to be captured as a Reference. | V44: Ravi Kishore | X44: Open | Y44: REOPENED | AB44: \\172.28.9.34\share drive\Artefacts_T-Fiber TNOC Tracker\DC IT-Infra\Artifact for - T41 | AI44: =_xlfn.CONCAT(D44,I44) -> 472DC-IT | AJ44: =VLOOKUP(AI44,Table1[[#All],[CONCAT]:[Tfiber]],2,FALSE) -> Network | AK44: OPEN | AR44: 1
B45: 43 | C45: T42 | D45: 472 | E45: NA | I45: DC-IT | J45: Servers and Strorage (Deployment and Installations) | K45: 2. Virtulization | N45: Colosed | V45: Ravi Kishore | Y45: COMPLETED & APPROVED | Z45: AD-UT-Tfiber | AA45: 45791 | AB45: \\172.28.9.34\share drive\Artefacts_T-Fiber TNOC Tracker\DC IT-Infra\Artifact for -T42 | AI45: =_xlfn.CONCAT(D45,I45) -> 472DC-IT | AJ45: =VLOOKUP(AI45,Table1[[#All],[CONCAT]:[Tfiber]],2,FALSE) -> Network | AK45: CLOSED | AO45: 45791 | AP45: \\172.28.9.34\share drive\Artefacts_T-Fiber TNOC Tracker\DC IT-Infra\Artifact for -T42 | AR45: 1
B46: 44 | C46: T43 | D46: 472 | E46: NA | I46: DC-IT | J46: Servers and Strorage (Deployment and Installations) | K46: 3. Anti-virus | N46: Colosed | V46: Ravi Kishore | Y46: COMPLETED & APPROVED | Z46: AD-UT-Tfiber | AA46: 45791 | AB46: \\172.28.9.34\share drive\Artefacts_T-Fiber TNOC Tracker\DC IT-Infra\Artifact for -T43 | AI46: =_xlfn.CONCAT(D46,I46) -> 472DC-IT | AJ46: =VLOOKUP(AI46,Table1[[#All],[CONCAT]:[Tfiber]],2,FALSE) -> Network | AK46: CLOSED | AO46: 45791 | AP46: \\172.28.9.34\share drive\Artefacts_T-Fiber TNOC Tracker\DC IT-Infra\Artifact for -T43 | AR46: 1
B47: 45 | C47: T44 | D47: 472 | E47: NA | I47: DC-IT | J47: Servers and Strorage (Deployment and Installations) | K47: 4. VM's Deployment Application Installations | N47: Colosed | V47: Ravi Kishore | Y47: COMPLETED & APPROVED | Z47: AD-UT-Tfiber | AA47: 45791 | AB47: \\172.28.9.34\share drive\Artefacts_T-Fiber TNOC Tracker\DC IT-Infra\Artifact for -T44 | AI47: =_xlfn.CONCAT(D47,I47) -> 472DC-IT | AJ47: =VLOOKUP(AI47,Table1[[#All],[CONCAT]:[Tfiber]],2,FALSE) -> Network | AK47: CLOSED | AO47: 45791 | AP47: \\172.28.9.34\share drive\Artefacts_T-Fiber TNOC Tracker\DC IT-Infra\Artifact for -T44 | AR47: 1
B48: 46 | C48: T45 | D48: 472 | E48: NA | I48: DC-IT | J48: Commvault Backup | K48: Application Installation | N48: Colosed | V48: Ravi Kishore | Y48: COMPLETED & APPROVED | Z48: AD-UT-Tfiber | AA48: 45791 | AB48: \\172.28.9.34\Artefacts_T-Fiber TNOC Tracker\DC IT-Infra\Artifact for - T45 | AI48: =_xlfn.CONCAT(D48,I48) -> 472DC-IT | AJ48: =VLOOKUP(AI48,Table1[[#All],[CONCAT]:[Tfiber]],2,FALSE) -> Network | AK48: CLOSED | AO48: 45791 | AP48: \\172.28.9.34\Artefacts_T-Fiber TNOC Tracker\DC IT-Infra\Artifact for - T45 | AR48: 1
B49: 47 | C49: T46 | D49: 472 | E49: NA | I49: DC-IT | J49: Commvault Backup | K49: Application Configuration | N49: Colosed | V49: Ravi Kishore | Y49: COMPLETED & APPROVED | Z49: AD-UT-Tfiber | AA49: 45791 | AB49: \\172.28.9.34\Artefacts_T-Fiber TNOC Tracker\DC IT-Infra\Artifact for - T46 | AI49: =_xlfn.CONCAT(D49,I49) -> 472DC-IT | AJ49: =VLOOKUP(AI49,Table1[[#All],[CONCAT]:[Tfiber]],2,FALSE) -> Network | AK49: CLOSED | AO49: 45791 | AP49: \\172.28.9.34\Artefacts_T-Fiber TNOC Tracker\DC IT-Infra\Artifact for - T46 | AR49: 1
B50: 48 | C50: T47 | D50: 472 | E50: NA | I50: DC-IT | J50: Commvault Backup | K50: Application Installation AT | N50: Colosed | V50: Ravi Kishore | Y50: COMPLETED & APPROVED | Z50: AD-UT-Tfiber | AA50: 45791 | AB50: \\172.28.9.34\Artefacts_T-Fiber TNOC Tracker\DC IT-Infra\Artifact for - T47 | AI50: =_xlfn.CONCAT(D50,I50) -> 472DC-IT | AJ50: =VLOOKUP(AI50,Table1[[#All],[CONCAT]:[Tfiber]],2,FALSE) -> Network | AK50: CLOSED | AO50: 45791 | AP50: \\172.28.9.34\Artefacts_T-Fiber TNOC Tracker\DC IT-Infra\Artifact for - T47 | AR50: 1
B51: 49 | C51: T48 | D51: 472 | E51: NA | I51: DC-IT | J51: Commvault Backup | K51: Application Functional AT | N51: Open | S51: Working on the Extra Test cases which are received from the TPA & T-Fiber. | V51: Ravi Kishore | X51: Open | Y51: WIP | AB51: \\172.28.9.34\Artefacts_T-Fiber TNOC Tracker\DC IT-Infra\Artifact for - T48 | AI51: =_xlfn.CONCAT(D51,I51) -> 472DC-IT | AJ51: =VLOOKUP(AI51,Table1[[#All],[CONCAT]:[Tfiber]],2,FALSE) -> Network | AK51: OPEN | AR51: 1
B52: 50 | C52: T49 | D52: 472 | E52: NA | I52: DC-IT | J52: LLD | K52: LLD Approved conditionally with few punch points. Updated LLD to be submitted | N52: Open | S52: Working on DC IT-Infra Server and storage-MoM Points received from the T-Fiber. | V52: Ravi Kishore | X52: Open | Y52: WIP | AB52: \\172.28.9.34\Artefacts_T-Fiber TNOC Tracker\DC IT-Infra\Artifact for - T49 | AI52: =_xlfn.CONCAT(D52,I52) -> 472DC-IT | AJ52: =VLOOKUP(AI52,Table1[[#All],[CONCAT]:[Tfiber]],2,FALSE) -> Network | AK52: OPEN | AR52: 1
B53: 51 | C53: T50 | D53: 472 | E53: NA | I53: DC-IT | J53: MoM Action | K53: Radware , A10 Configuration file needed to be shared to RaviKishore | N53: Open | S53: Artfacts submitted . point Closure on 10 Jul 25 | V53: Sarmendra | Y53: COMPLETED & APPROVED | AB53: \\172.28.9.34\Artefacts_T-Fiber TNOC Tracker\NW-Security\T50 | AI53: =_xlfn.CONCAT(D53,I53) -> 472DC-IT | AJ53: =VLOOKUP(AI53,Table1[[#All],[CONCAT]:[Tfiber]],2,FALSE) -> Network | AK53: CLOSED | AP53: \\172.28.9.34\Artefacts_T-Fiber TNOC Tracker\NW-Security\T50 | AR53: 1
B54: 52 | C54: T51 | D54: 472 | E54: NA | I54: DC-IT | J54: Commvault Backup | K54: Backup retention and Backup activity (such as when incremental backup,full backup are scheduled and time duration required to complete such backup). Application Wise Backup Retention should be as per DOT Guidelines | N54: Colosed | V54: Ravi Kishore | Y54: COMPLETED & APPROVED | Z54: AD-UT-Tfiber | AA54: 45791 | AB54: \\172.28.9.34\Artefacts_T-Fiber TNOC Tracker\DC IT-Infra\Artifact for - T51 | AI54: =_xlfn.CONCAT(D54,I54) -> 472DC-IT | AJ54: =VLOOKUP(AI54,Table1[[#All],[CONCAT]:[Tfiber]],2,FALSE) -> Network | AK54: CLOSED | AO54: 45791 | AP54: \\172.28.9.34\Artefacts_T-Fiber TNOC Tracker\DC IT-Infra\Artifact for - T51 | AR54: 1
B55: 53 | C55: T52 | D55: 472 | E55: NA | I55: DC-IT | J55: Commvault Backup | K55: Backup solution should have hot , cold and archieve storage inorder to decrease the backup size/capacity in long run. | N55: Colosed | V55: Ravi Kishore | Y55: COMPLETED & APPROVED | Z55: AD-UT-Tfiber | AA55: 45791 | AB55: \\172.28.9.34\share drive\Artefacts_T-Fiber TNOC Tracker\DC IT-Infra\Artifact for - T52 | AI55: =_xlfn.CONCAT(D55,I55) -> 472DC-IT | AJ55: =VLOOKUP(AI55,Table1[[#All],[CONCAT]:[Tfiber]],2,FALSE) -> Network | AK55: CLOSED | AO55: 45791 | AP55: \\172.28.9.34\share drive\Artefacts_T-Fiber TNOC Tracker\DC IT-Infra\Artifact for - T52 | AR55: 1
B56: 54 | C56: T53 | D56: 472 | E56: NA | I56: DC-IT | J56: SSD storage migration – EPNM/PI | K56: EPNM/PI VMs migration to SSD Storage | N56: Colosed | V56: Ravi Kishore | Y56: COMPLETED & APPROVED | Z56: AD-UT-Tfiber | AA56: 45791 | AB56: \\172.28.9.34\share drive\Artefacts_T-Fiber TNOC Tracker\DC IT-Infra\Artifact for - T53 | AI56: =_xlfn.CONCAT(D56,I56) -> 472DC-IT | AJ56: =VLOOKUP(AI56,Table1[[#All],[CONCAT]:[Tfiber]],2,FALSE) -> Network | AK56: CLOSED | AO56: 45791 | AP56: \\172.28.9.34\share drive\Artefacts_T-Fiber TNOC Tracker\DC IT-Infra\Artifact for - T53 | AR56: 1
B57: 55 | C57: T54 | D57: 472 | E57: NA | I57: DC-IT | J57: SSD storage migration – ISE/FMC | K57: ISE & FMC VMs migration to SSD Storage | N57: Colosed | V57: Ravi Kishore | Y57: COMPLETED & APPROVED | Z57: AD-UT-Tfiber | AA57: 45791 | AB57: \\172.28.9.34\share drive\Artefacts_T-Fiber TNOC Tracker\DC IT-Infra\Artifact for - T54 | AI57: =_xlfn.CONCAT(D57,I57) -> 472DC-IT | AJ57: =VLOOKUP(AI57,Table1[[#All],[CONCAT]:[Tfiber]],2,FALSE) -> Network | AK57: CLOSED | AO57: 45791 | AP57: \\172.28.9.34\share drive\Artefacts_T-Fiber TNOC Tracker\DC IT-Infra\Artifact for - T54 | AR57: 1
B58: 56 | C58: T55 | D58: 472 | E58: NA | I58: DC-IT | J58: MoM Action | K58: VM Placing should be verified & rectified, Same service VM needs to be placed in different Physical Server/host. | N58: Colosed | V58: Ravi Kishore | Y58: COMPLETED & APPROVED | Z58: AD-UT-Tfiber | AA58: 45791 | AB58: \\172.28.9.34\share drive\Artefacts_T-Fiber TNOC Tracker\DC IT-Infra\Artifact for - T55 | AI58: =_xlfn.CONCAT(D58,I58) -> 472DC-IT | AJ58: =VLOOKUP(AI58,Table1[[#All],[CONCAT]:[Tfiber]],2,FALSE) -> Network | AK58: CLOSED | AO58: 45791 | AP58: \\172.28.9.34\share drive\Artefacts_T-Fiber TNOC Tracker\DC IT-Infra\Artifact for - T55 | AR58: 1
B59: 57 | C59: T56 | D59: 472 | E59: NA | I59: DC-IT | J59: MoM Action | K59: SOP documents needs to be provided | N59: Open | S59: SOP documents submitted to Operations team. Remaining pending documents to be prepared periodically. | V59: Ravi Kishore | X59: Open | Y59: REOPENED | AB59: \\172.28.9.34\share drive\Artefacts_T-Fiber TNOC Tracker\DC IT-Infra\Artifact for - T56 | AI59: =_xlfn.CONCAT(D59,I59) -> 472DC-IT | AJ59: =VLOOKUP(AI59,Table1[[#All],[CONCAT]:[Tfiber]],2,FALSE) -> Network | AK59: OPEN | AR59: 1
B60: 58 | C60: T57 | D60: 472 | E60: NA | I60: DC-IT | J60: LLD | K60: Approved conditionally with few punch points. Updated LLD to be submitted | N60: Open | S60: 14-Aug-25 : Discussion was done with TPA and Tfiber and submitted updated LLD document. 18-Jun-25 : Updated DC Network LLD submitted on 18-Jun-25 for TFiber review | T60: L&T | V60: RS Rao | Y60: COMPLETED & APPROVED | AI60: =_xlfn.CONCAT(D60,I60) -> 472DC-IT | AJ60: =VLOOKUP(AI60,Table1[[#All],[CONCAT]:[Tfiber]],2,FALSE) -> Network | AK60: CLOSED | AO60: 45883 | AP60: \\172.28.9.34\Artefacts_T-Fiber TNOC Tracker\IPMPLS\DC Network LLD V1.7 14-Aug-2025.pdf | AR60: 1
B61: 59 | C61: T58 | D61: 472 | E61: NA | I61: DC-IT | J61: Cisco EPNM | K61: Cisco EPNM infrastructure AT | N61: Open | S61: 22-Sep-25: IPMPLS Domain team to submit detailed remarks on raised queries. 08-Jul-2025 - Sandeep will come back by EoD today on extension of Cisco support renewal 01-Jul-25 : Revised FAT documents submission pending (TPA observations to be included) OEM(Cisco) suport is required to show the new test cases, Inputs provided to OEM on 14th May & 30th Jun. OEM onboarding is in progress & LnT Contracts team coordinating | T61: L&T | U61: RS Rao | V61: RS Rao | X61: Open | Y61: Open | AI61: =_xlfn.CONCAT(D61,I61) -> 472DC-IT | AJ61: =VLOOKUP(AI61,Table1[[#All],[CONCAT]:[Tfiber]],2,FALSE) -> Network | AK61: OPEN | AR61: 1
B62: 60 | C62: T59 | D62: 472 | E62: NA | I62: DC-IT | J62: Cisco PI | K62: Cisco prime infrastructure AT | N62: Open | S62: 22-Sep-25: IPMPLS Domain team to submit detailed remarks on raised queries. 08-Jul-2025 - Sandeep will come back by EoD today on extension of Cisco support renewal 01-Jul-25 : Revised FAT documents submission pending (TPA observations to be included) OEM(Cisco) suport is required to show the new test cases, Inputs provided to OEM on 14th May & 30th Jun. OEM onboarding is in progress & LnT Contracts team is coordinating | T62: L&T | U62: RS Rao | V62: RS Rao | X62: Open | Y62: Open | AI62: =_xlfn.CONCAT(D62,I62) -> 472DC-IT | AJ62: =VLOOKUP(AI62,Table1[[#All],[CONCAT]:[Tfiber]],2,FALSE) -> Network | AK62: OPEN | AR62: 1
B63: 61 | C63: T60 | D63: 472 | E63: NA | I63: DC-IT | J63: NTP | K63: Installation | N63: Colosed | V63: RS Rao | Y63: COMPLETED & APPROVED | Z63: AD-UT-Tfiber | AA63: 45782 | AB63: \\172.28.9.34\Artefacts_T-Fiber TNOC Tracker\IPMPLS\Primary NTP - T60,T61,T62.pdf \\172.28.9.34\Artefacts_T-Fiber TNOC Tracker\IPMPLS\Secondary NTP - T60,T61,T62.pdf | AI63: =_xlfn.CONCAT(D63,I63) -> 472DC-IT | AJ63: =VLOOKUP(AI63,Table1[[#All],[CONCAT]:[Tfiber]],2,FALSE) -> Network | AK63: CLOSED | AO63: 45782 | AP63: \\172.28.9.34\Artefacts_T-Fiber TNOC Tracker\IPMPLS\Primary NTP - T60,T61,T62.pdf \\172.28.9.34\Artefacts_T-Fiber TNOC Tracker\IPMPLS\Secondary NTP - T60,T61,T62.pdf | AR63: 1
B64: 62 | C64: T61 | D64: 472 | E64: NA | I64: DC-IT | J64: NTP | K64: Configuration | N64: Colosed | V64: RS Rao | Y64: COMPLETED & APPROVED | Z64: AD-UT-Tfiber | AA64: 45782 | AB64: \\172.28.9.34\Artefacts_T-Fiber TNOC Tracker\IPMPLS\Primary NTP - T60,T61,T62.pdf \\172.28.9.34\Artefacts_T-Fiber TNOC Tracker\IPMPLS\Secondary NTP - T60,T61,T62.pdf | AI64: =_xlfn.CONCAT(D64,I64) -> 472DC-IT | AJ64: =VLOOKUP(AI64,Table1[[#All],[CONCAT]:[Tfiber]],2,FALSE) -> Network | AK64: CLOSED | AO64: 45782 | AP64: \\172.28.9.34\Artefacts_T-Fiber TNOC Tracker\IPMPLS\Primary NTP - T60,T61,T62.pdf \\172.28.9.34\Artefacts_T-Fiber TNOC Tracker\IPMPLS\Secondary NTP - T60,T61,T62.pdf | AR64: 1
B65: 63 | C65: T62 | D65: 472 | E65: NA | I65: DC-IT | J65: NTP | K65: NTP Installation AT | N65: Colosed | V65: RS Rao | Y65: COMPLETED & APPROVED | Z65: AD-UT-Tfiber | AA65: 45782 | AB65: \\172.28.9.34\Artefacts_T-Fiber TNOC Tracker\IPMPLS\Primary NTP - T60,T61,T62.pdf \\172.28.9.34\Artefacts_T-Fiber TNOC Tracker\IPMPLS\Secondary NTP - T60,T61,T62.pdf | AI65: =_xlfn.CONCAT(D65,I65) -> 472DC-IT | AJ65: =VLOOKUP(AI65,Table1[[#All],[CONCAT]:[Tfiber]],2,FALSE) -> Network | AK65: CLOSED | AO65: 45782 | AP65: \\172.28.9.34\Artefacts_T-Fiber TNOC Tracker\IPMPLS\Primary NTP - T60,T61,T62.pdf \\172.28.9.34\Artefacts_T-Fiber TNOC Tracker\IPMPLS\Secondary NTP - T60,T61,T62.pdf | AR65: 1
B66: 64 | C66: T63 | D66: 472 | E66: NA | I66: DC-IT | J66: NTP | K66: NTP Functional AT | N66: Open | V66: RS Rao | Y66: COMPLETED & APPROVED | Z66: AD-UT-Tfiber | AA66: 45841 | AB66: \\172.28.9.34\Artefacts_T-Fiber TNOC Tracker\IPMPLS\NTP FAT & Acceptance - T63.pdf | AI66: =_xlfn.CONCAT(D66,I66) -> 472DC-IT | AJ66: =VLOOKUP(AI66,Table1[[#All],[CONCAT]:[Tfiber]],2,FALSE) -> Network | AK66: CLOSED | AO66: 45841 | AP66: \\172.28.9.34\Artefacts_T-Fiber TNOC Tracker\IPMPLS\NTP FAT & Acceptance - T63.pdf | AR66: 1
B67: 65 | C67: T64 | D67: 472 | E67: NA | I67: DC-IT | J67: Functional AT | K67: DC Network Infra AT | N67: Open | S67: 22-Sep-25: IPMPLS Domain team to submit detailed remarks on raised queries. 08-Jul-2025 - Sandeep will come back by EoD today on extension of Cisco support renewal 01-Jul-25 : Revised FAT documents submission pending (TPA observations to be included) OEM(Cisco) suport is required to show the new test cases, Inputs provided to OEM on 14th May & 30th Jun. OEM onboarding is in progress & LnT Contracts team is coordinating | T67: L&T | U67: RS Rao | V67: RS Rao | X67: Open | Y67: Open | AI67: =_xlfn.CONCAT(D67,I67) -> 472DC-IT | AJ67: =VLOOKUP(AI67,Table1[[#All],[CONCAT]:[Tfiber]],2,FALSE) -> Network | AK67: OPEN | AR67: 1
B68: 66 | C68: T65 | D68: 472 | E68: NA | I68: DR | J68: Servers and Strorage (Deployment and Installations) | K68: Virtulization | N68: Colosed | V68: Ravi Kishore | Y68: COMPLETED & APPROVED | Z68: AD-UT-Tfiber | AA68: 45791 | AB68: \\172.28.9.34\share drive\Artefacts_T-Fiber TNOC Tracker\DR\Artifact for - T65 | AI68: =_xlfn.CONCAT(D68,I68) -> 472DR | AJ68: =VLOOKUP(AI68,Table1[[#All],[CONCAT]:[Tfiber]],2,FALSE) -> DR | AK68: CLOSED | AO68: 45791 | AP68: \\172.28.9.34\share drive\Artefacts_T-Fiber TNOC Tracker\DR\Artifact for - T65 | AR68: 1
B69: 67 | C69: T66 | D69: 472 | E69: NA | I69: DR | J69: DC (TNOC-DR) | K69: Network Readiness | N69: Colosed | V69: Ravi Kishore | Y69: COMPLETED & APPROVED | Z69: AD-UT-Tfiber | AA69: 45791 | AB69: \\172.28.9.34\Artefacts_T-Fiber TNOC Tracker\DR\Artifact for - T66 | AI69: =_xlfn.CONCAT(D69,I69) -> 472DR | AJ69: =VLOOKUP(AI69,Table1[[#All],[CONCAT]:[Tfiber]],2,FALSE) -> DR | AK69: CLOSED | AO69: 45791 | AP69: \\172.28.9.34\Artefacts_T-Fiber TNOC Tracker\DR\Artifact for - T66 | AR69: 1
B70: 68 | C70: T67 | D70: 472 | E70: NA | I70: DR | J70: Mahbubnagar-DR | K70: Network Readiness | N70: Colosed | V70: Ravi Kishore | Y70: COMPLETED & APPROVED | Z70: AD-UT-Tfiber | AA70: 45791 | AB70: \\172.28.9.34\share drive\Artefacts_T-Fiber TNOC Tracker\DR\Artifact for -T67 | AI70: =_xlfn.CONCAT(D70,I70) -> 472DR | AJ70: =VLOOKUP(AI70,Table1[[#All],[CONCAT]:[Tfiber]],2,FALSE) -> DR | AK70: CLOSED | AO70: 45791 | AP70: \\172.28.9.34\Artefacts_T-Fiber TNOC Tracker\DR\Artifact for - T66 | AR70: 1
B71: 69 | C71: T68 | D71: 472 | E71: NA | I71: DR | J71: Design & Documentation | K71: LLD: Approved conditionally with few punch points. Updated LLD to be submitted | N71: Open | S71: Working on additional points shared by Tfiber. | V71: Ravi Kishore | X71: Open | Y71: WIP | AB71: \\172.28.9.34\Artefacts_T-Fiber TNOC Tracker\DR\Artifact for -T68 | AI71: =_xlfn.CONCAT(D71,I71) -> 472DR | AJ71: =VLOOKUP(AI71,Table1[[#All],[CONCAT]:[Tfiber]],2,FALSE) -> DR | AK71: OPEN | AR71: 1
B72: 70 | C72: T69 | D72: 472 | E72: NA | I72: DR | J72: Design & Documentation | K72: HLD: Revised solution to submitted | N72: Open | S72: Working on additional points shared by Tfiber. | V72: Ravi Kishore | X72: Open | Y72: WIP | AB72: \\172.28.9.34\Artefacts_T-Fiber TNOC Tracker\DR\Artifact for -T69 | AI72: =_xlfn.CONCAT(D72,I72) -> 472DR | AJ72: =VLOOKUP(AI72,Table1[[#All],[CONCAT]:[Tfiber]],2,FALSE) -> DR | AK72: OPEN | AR72: 1
B73: 71 | C73: T70 | D73: 472 | E73: NA | I73: DR | J73: Design & Documentation | K73: DC-DR redunancy Test | N73: Colosed | V73: Ravi Kishore | Y73: COMPLETED & APPROVED | Z73: AD-UT-Tfiber | AA73: 45791 | AB73: \\172.28.9.34\share drive\Artefacts_T-Fiber TNOC Tracker\DR\Artifact for - T70 | AI73: =_xlfn.CONCAT(D73,I73) -> 472DR | AJ73: =VLOOKUP(AI73,Table1[[#All],[CONCAT]:[Tfiber]],2,FALSE) -> DR | AK73: CLOSED | AO73: 45791 | AP73: \\172.28.9.34\share drive\Artefacts_T-Fiber TNOC Tracker\DR\Artifact for - T70 | AR73: 1
B74: 72 | C74: T71 | D74: 472 | E74: NA | I74: DR | J74: MoM Action | K74: UTM Features (DR FW) | N74: Open | S74: Meeting scheduled with CTRL S to verify the UTM features | V74: Sarmendra | X74: Open | Y74: WIP | AI74: =_xlfn.CONCAT(D74,I74) -> 472DR | AJ74: =VLOOKUP(AI74,Table1[[#All],[CONCAT]:[Tfiber]],2,FALSE) -> DR | AK74: OPEN | AR74: 1
B75: 73 | C75: T72 | D75: 472 | E75: NA | I75: DR | J75: MoM Action | K75: To configure LACP between L3 Switch and Core Router | N75: Open | S75: 11-Oct-25: CtrlS has to give proposal for procurement for addtional BoQ. IT infra SME need to Re-intiate a mail to get BoQ 22-Sep-25: The existing switch which was placed at DR by CtrlS doesnt have feature on LACP Bundling. CtrlS is planning to relplace the exising switch with LACP supported switch. DC Infra admin need to provide tentative timelines for replacement. 08-Jul-2025 Sandeep will ensure on CTRL-S support and update by EoD 01-Jul-25 : Ticket (SR01301726) raised with CtrlS on 27-Jun, Config & testing to be carried out. This is additional task as per CtrlS and commercials may be involved. LnT Contracts team also talking to CtrlS account team to complete the task. 24-Dec-25 : SR01036770 opened with CtrlS for LACP configuration and it is not O&M activity as per CtrlS ops. team. escalated to LnT Contracts team for supoort. | T75: CtrlS | U75: Venkat | V75: Ravi Kishore | X75: Open | Y75: WIP | AI75: =_xlfn.CONCAT(D75,I75) -> 472DR | AJ75: =VLOOKUP(AI75,Table1[[#All],[CONCAT]:[Tfiber]],2,FALSE) -> DR | AK75: OPEN | AR75: 1
B76: 74 | C76: T73 | D76: 472 | E76: NA | I76: DR | J76: MoM Action | K76: To configure LACP between Core Router and Firewall | N76: Open | S76: 11-Oct-25: CtrlS has to give proposal for procurement for addtional BoQ. IT infra SME need to Re-intiate a mail to get BoQ 22-Sep-25: The existing switch which was placed at DR by CtrlS doesnt have feature on LACP Bundling. CtrlS is planning to relplace the exising switch with LACP supported switch. DC Infra admin need to provide tentative timelines for replacement. 01-Jul-25 : Ticket (SR01301726) raised with CtrlS on 27-Jun, Config & testing to be carried out. This is additional task as per CtrlS and commercials may be involved. LnT Contracts team also talking to CtrlS account team to complete the task. 24-Dec-25 : SR01036770 opened with CtrlS for LACP configuration and it is not O&M activity as per CtrlS ops. team. escalated to LnT Contracts team for supoort. | T76: CtrlS | U76: Venkat | V76: Ravi Kishore | X76: Open | Y76: WIP | AI76: =_xlfn.CONCAT(D76,I76) -> 472DR | AJ76: =VLOOKUP(AI76,Table1[[#All],[CONCAT]:[Tfiber]],2,FALSE) -> DR | AK76: OPEN | AR76: 1
B77: 75 | C77: T74 | D77: 472 | E77: NA | I77: DR | J77: MoM Action | K77: To configure LACP between Firewall and L2 Switch | N77: Open | S77: 11-Oct-25: CtrlS has to give proposal for procurement for addtional BoQ. IT infra SME need to Re-intiate a mail to get BoQ 22-Sep-25: The existing switch which was placed at DR by CtrlS doesnt have feature on LACP Bundling. CtrlS is planning to relplace the exising switch with LACP supported switch. DC Infra admin need to provide tentative timelines for replacement. 01-Jul-25 : Ticket (SR01301726) raised with CtrlS on 27-Jun, Config & testing to be carried out. This is additional task as per CtrlS and commercials may be involved. LnT Contracts team also talking to CtrlS account team to complete the task. 24-Dec-25 : SR01036770 opened with CtrlS for LACP configuration and it is not O&M activity as per CtrlS ops. team. escalated to LnT Contracts team for supoort. | T77: CtrlS | U77: Venkat | V77: Ravi Kishore | X77: Open | Y77: WIP | AI77: =_xlfn.CONCAT(D77,I77) -> 472DR | AJ77: =VLOOKUP(AI77,Table1[[#All],[CONCAT]:[Tfiber]],2,FALSE) -> DR | AK77: OPEN | AR77: 1
B78: 76 | C78: T75 | D78: 472 | E78: NA | I78: DR | J78: MoM Action | K78: To confirm on backups for DR Virtual machines | N78: Colosed | V78: Ravi Kishore | Y78: COMPLETED & APPROVED | Z78: AD-UT-Tfiber | AA78: 45791 | AB78: \\172.28.9.34\share drive\Artefacts_T-Fiber TNOC Tracker\DR\Artifact for - T75 | AI78: =_xlfn.CONCAT(D78,I78) -> 472DR | AJ78: =VLOOKUP(AI78,Table1[[#All],[CONCAT]:[Tfiber]],2,FALSE) -> DR | AK78: CLOSED | AO78: 45791 | AP78: \\172.28.9.34\share drive\Artefacts_T-Fiber TNOC Tracker\DR\Artifact for - T75 | AR78: 1
B79: 77 | C79: T76 | D79: 472 | E79: NA | I79: DR | J79: MoM Action | K79: Backup storage to 25 TB | N79: Colosed | V79: Ravi Kishore | Y79: COMPLETED & APPROVED | Z79: AD-UT-Tfiber | AA79: 45791 | AB79: \\172.28.9.34\share drive\Artefacts_T-Fiber TNOC Tracker\DR\Artifact for - T76 | AI79: =_xlfn.CONCAT(D79,I79) -> 472DR | AJ79: =VLOOKUP(AI79,Table1[[#All],[CONCAT]:[Tfiber]],2,FALSE) -> DR | AK79: CLOSED | AO79: 45791 | AP79: \\172.28.9.34\share drive\Artefacts_T-Fiber TNOC Tracker\DR\Artifact for - T76 | AR79: 1
B80: 78 | C80: T77 | D80: 472 | E80: NA | I80: DR | J80: MoM Action | K80: To submit the SOPs for DC-DR switchover, DC-DR failover and failback | N80: Open | S80: Tejas, Nokia, GIS & Ciena MCP documnets are received. Remaining all Applications domains SOP's to be updated. | V80: Ravi Kishore | X80: Open | Y80: REOPENED | AB80: \\172.28.9.34\share drive\Artefacts_T-Fiber TNOC Tracker\DR\Artifact for - T77 | AI80: =_xlfn.CONCAT(D80,I80) -> 472DR | AJ80: =VLOOKUP(AI80,Table1[[#All],[CONCAT]:[Tfiber]],2,FALSE) -> DR | AK80: OPEN | AR80: 1
B81: 79 | C81: T78 | D81: 472 | E81: NA | I81: DR | J81: MoM Action | K81: to monitor the DR Servers | N81: Open | S81: DR servers monitoring through DR vCentre happening. DR is maintained by CtrlS team as per contract. Feasibility to be checked to integrated through OSS OBM. | V81: Ravi Kishore | X81: Open | Y81: WIP | AB81: \\172.28.9.34\share drive\Artefacts_T-Fiber TNOC Tracker\DR\Artifact for - T78 | AI81: =_xlfn.CONCAT(D81,I81) -> 472DR | AJ81: =VLOOKUP(AI81,Table1[[#All],[CONCAT]:[Tfiber]],2,FALSE) -> DR | AK81: OPEN | AR81: 1
B82: 80 | C82: T79 | D82: 472 | E82: NA | I82: DR | J82: MoM Action | K82: To confirm that DNS switchover between DC and DR locations should be automatic | N82: Colosed | V82: Ravi Kishore | Y82: COMPLETED & APPROVED | Z82: AD-UT-Tfiber | AA82: 45791 | AB82: \\172.28.9.34\Artefacts_T-Fiber TNOC Tracker\DR\Artifact for - T79 | AI82: =_xlfn.CONCAT(D82,I82) -> 472DR | AJ82: =VLOOKUP(AI82,Table1[[#All],[CONCAT]:[Tfiber]],2,FALSE) -> DR | AK82: CLOSED | AO82: 45791 | AP82: \\172.28.9.34\Artefacts_T-Fiber TNOC Tracker\DR\Artifact for - T79 | AR82: 1
B83: 81 | C83: T80 | D83: 472 | E83: NA | I83: DR | J83: MoM Action | K83: Mahubnagar as NTP | N83: Colosed | V83: RS Rao | Y83: COMPLETED & APPROVED | Z83: AD-UT-Tfiber | AA83: 45782 | AB83: \\172.28.9.34\Artefacts_T-Fiber TNOC Tracker\IPMPLS\Primary NTP - T60,T61,T62.pdf \\172.28.9.34\Artefacts_T-Fiber TNOC Tracker\IPMPLS\Secondary NTP - T60,T61,T62.pdf | AI83: =_xlfn.CONCAT(D83,I83) -> 472DR | AJ83: =VLOOKUP(AI83,Table1[[#All],[CONCAT]:[Tfiber]],2,FALSE) -> DR | AK83: CLOSED | AO83: 45782 | AP83: \\172.28.9.34\Artefacts_T-Fiber TNOC Tracker\IPMPLS\Primary NTP - T60,T61,T62.pdf \\172.28.9.34\Artefacts_T-Fiber TNOC Tracker\IPMPLS\Secondary NTP - T60,T61,T62.pdf | AR83: 1
B84: 82 | C84: T81 | D84: 472 | E84: NA | I84: DR | J84: Configuration | K84: All application to be migrated to implement DR LB configuration | N84: Open | S84: 11-Oct-25: Approved DR HLD document to be shared with T Fiber for further discussion. Noikia app is integrated with DR LB . Balance application migration on DR LB is in Pipeline | V84: Ravi Kishore | X84: Open | Y84: WIP | AI84: =_xlfn.CONCAT(D84,I84) -> 472DR | AJ84: =VLOOKUP(AI84,Table1[[#All],[CONCAT]:[Tfiber]],2,FALSE) -> DR | AK84: OPEN | AR84: 1
B85: 83 | C85: T82 | D85: 472 | E85: NA | I85: DR | J85: MoM Action | K85: To confirm the applications which support Veem Replication for Reconfiguration | N85: Colosed | V85: Ravi Kishore | Y85: COMPLETED & APPROVED | Z85: AD-UT-Tfiber | AA85: 45791 | AB85: \\172.28.9.34\share drive\Artefacts_T-Fiber TNOC Tracker\DR\Artifact for - T82 | AI85: =_xlfn.CONCAT(D85,I85) -> 472DR | AJ85: =VLOOKUP(AI85,Table1[[#All],[CONCAT]:[Tfiber]],2,FALSE) -> DR | AK85: CLOSED | AO85: 45791 | AP85: \\172.28.9.34\share drive\Artefacts_T-Fiber TNOC Tracker\DR\Artifact for - T82 | AR85: 1
B86: 84 | C86: T83 | D86: 472 | E86: NA | I86: DWDM | J86: Network Deployment & integration | K86: Zonal Links Integration (12/15) | N86: Open | S86: 20-Sep-25: Nirmal, Jainoor, Gudihatnoor & Bhimni RFE pending due to forest permission 31-July-2025:As per discussion with Ramanaiah sir, need to discuss these points with T Fiber Project team for further action, till that time this point kept on hold Depend on 04 Facilities RFE in Pkg-C Asifabad - Warangal & Karimnagar - Asifabad - Links integrated as per interim plan, actual integration pending Nizamabad - Asifabad - E2E link integration pending 28th-Apr'25: As per Sandeep Sanmani - Forest permission still pending 6/25/2025: Status is same no visibility on forest permission, Target date would be D+21 05-July-25: No progress on the forest permission | T86: T Fiber | U86: Srinivas Jukuri(Project) | V86: Suresh Kumar | X86: Open | Y86: DEPENDENCY(Client/Ext.) | AI86: =_xlfn.CONCAT(D86,I86) -> 472DWDM | AJ86: =VLOOKUP(AI86,Table1[[#All],[CONCAT]:[Tfiber]],2,FALSE) -> DWDM | AK86: OPEN | AR86: 1
B87: 85 | C87: T84 | D87: 472 | E87: NA | I87: DWDM | J87: Network Deployment & integration | K87: Nodes Live & Operational (67/71) | N87: Open | S87: 31-July-2025:As per discussion with Ramanaiah sir, need to discuss these points with T Fiber Project team for further action, till that time this point kept on hold Nirmal, Jainoor, Gudihatnoor & Bhimni RFE pending due to forest permission 28th-Apr'25: As per Sandeep Sanmani - Forest permission still pending 15-06-25: No progress on the permission, target - D+15 05-July-25: No progress on the forest permission | T87: T Fiber | U87: Srinivas Jukuri(Project) | V87: Suresh Kumar | X87: Open | Y87: DEPENDENCY(Client/Ext.) | AI87: =_xlfn.CONCAT(D87,I87) -> 472DWDM | AJ87: =VLOOKUP(AI87,Table1[[#All],[CONCAT]:[Tfiber]],2,FALSE) -> DWDM | AK87: OPEN | AR87: 1
B88: 86 | C88: T85 | D88: 472 | E88: NA | I88: DWDM | J88: Network Deployment & integration | K88: Zonal Rings readiness with 1+R protection (5/7) | N88: Open | S88: 31-July-2025:As per discussion with Ramanaiah sir, need to discuss these points with T Fiber Project team for further action, till that time this point kept on hold 02 rings depend on 04 Facilities RFE readiness in Pkg-C, which is pending due to forest permission 28th-Apr'25: As per Sandeep Sanmani - Forest permission still pending 6/25/2025: No visibility on forest permission, target date would be D+30 05-July-25: No progress on the forest permission | T88: T Fiber | U88: Srinivas Jukuri(Project) | V88: Suresh Kumar | X88: Open | Y88: DEPENDENCY(Client/Ext.) | AI88: =_xlfn.CONCAT(D88,I88) -> 472DWDM | AJ88: =VLOOKUP(AI88,Table1[[#All],[CONCAT]:[Tfiber]],2,FALSE) -> DWDM | AK88: OPEN | AR88: 1
B89: 87 | C89: T86 | D89: 472 | E89: NA | I89: DWDM | J89: Network Deployment & AT Status | K89: Nodal AT (67/71) | N89: Open | S89: 31-July-2025:As per discussion with Ramanaiah sir, need to discuss these points with T Fiber Project team for further action, till that time this point kept on hold Nirmal, Jainoor, Gudihatnoor & Bhimni RFE pending due to forest permission 28th-Apr'25: As per Sandeep Sanmani - Forest permission still pending 15-06-25: No progress on the permission, target - D+15 05-July-25: No progress on the forest permission | T89: T Fiber | U89: Srinivas Jukuri(Project) | V89: Suresh Kumar | X89: Open | Y89: DEPENDENCY(Client/Ext.) | AI89: =_xlfn.CONCAT(D89,I89) -> 472DWDM | AJ89: =VLOOKUP(AI89,Table1[[#All],[CONCAT]:[Tfiber]],2,FALSE) -> DWDM | AK89: OPEN | AR89: 1
B90: 88 | C90: T87 | D90: 472 | E90: NA | I90: DWDM | J90: Network Deployment & integration | K90: Mandal Ring Integration through OADM | N90: Open | S90: 31-July-2025:As per discussion with Ramanaiah sir, need to discuss these points with T Fiber Project team for further action, till that time this point kept on hold Mandal services are provisioned (10G) as per integration plan by all packages 6/25/2025: 203 services provisioned out of 270 planned. Remaining can be provisioned as per the requirement | T90: T Fiber | U90: Srinivas Jukuri(Project) | V90: Suresh Kumar | X90: Open | Y90: DEPENDENCY(Client/Ext.) | AI90: =_xlfn.CONCAT(D90,I90) -> 472DWDM | AJ90: =VLOOKUP(AI90,Table1[[#All],[CONCAT]:[Tfiber]],2,FALSE) -> DWDM | AK90: OPEN | AR90: 1
B91: 89 | C91: T88 | D91: 472 | E91: NA | I91: DWDM | J91: Network Deployment & AT Status | K91: Zonal Link AT (7/15) | N91: Open | S91: 31-July-2025:As per discussion with Ramanaiah sir, need to discuss these points with T Fiber Project team for further action, till that time this point kept on hold 04 Link AT's approved by T Fiber and 03 Link AT's pending due to letter from Ciena awaited (No impact due to ILA to OADM upgradation) 05 Link AT pending due to high losses in the spans, depend on all packages 02 Links integrated as per interim plan, so not considered for Link AT 20May'25: Declaration letter submitted to T Fiber for 03 links AT approval 25-06-2025: Dependancy on field, no progress. 30-June-2025: As discussed in the meeting, need to arrange meeting with all stakeholders | T91: All Packages | V91: Suresh Kumar | X91: Open | Y91: DEPENDENCY(Client/Ext.) | AI91: =_xlfn.CONCAT(D91,I91) -> 472DWDM | AJ91: =VLOOKUP(AI91,Table1[[#All],[CONCAT]:[Tfiber]],2,FALSE) -> DWDM | AK91: OPEN | AN91: 20-Sep-25: Mr.Suresh will update the status | AR91: 1
B92: 90 | C92: T89 | D92: 472 | E92: NA | I92: DWDM | J92: Design & Documentation | K92: HLD (Revised) with OADM Solution | N92: Colosed | V92: Suresh Kumar | Y92: COMPLETED & APPROVED | Z92: AD-UT-Tfiber | AA92: 45783 | AB92: \\172.28.9.34\Artefacts_T-Fiber TNOC Tracker\DWDM\Artefact - T89 | AI92: =_xlfn.CONCAT(D92,I92) -> 472DWDM | AJ92: =VLOOKUP(AI92,Table1[[#All],[CONCAT]:[Tfiber]],2,FALSE) -> DWDM | AK92: CLOSED | AO92: 45783 | AP92: \\172.28.9.34\Artefacts_T-Fiber TNOC Tracker\DWDM\Artefact - T89 | AR92: 1
B93: 91 | C93: T90 | D93: 472 | E93: NA | I93: DWDM | J93: Design & Documentation | K93: LLD (Revised) with OADM Solution (Ciena) | N93: Colosed | V93: Suresh Kumar | Y93: COMPLETED & APPROVED | Z93: AD-UT-Tfiber | AA93: 45783 | AB93: \\172.28.9.34\Artefacts_T-Fiber TNOC Tracker\DWDM\Artefact - T90 | AI93: =_xlfn.CONCAT(D93,I93) -> 472DWDM | AJ93: =VLOOKUP(AI93,Table1[[#All],[CONCAT]:[Tfiber]],2,FALSE) -> DWDM | AK93: CLOSED | AO93: 45783 | AP93: \\172.28.9.34\Artefacts_T-Fiber TNOC Tracker\DWDM\Artefact - T90 | AR93: 1
B94: 92 | C94: T91 | D94: 472 | E94: NA | I94: DWDM | J94: Design & Documentation | K94: Nodal ATP | N94: Colosed | V94: Suresh Kumar | Y94: COMPLETED & APPROVED | Z94: AD-UT-Tfiber | AA94: 45783 | AB94: \\172.28.9.34\Artefacts_T-Fiber TNOC Tracker\DWDM\Artefact - T91 & T92 | AI94: =_xlfn.CONCAT(D94,I94) -> 472DWDM | AJ94: =VLOOKUP(AI94,Table1[[#All],[CONCAT]:[Tfiber]],2,FALSE) -> DWDM | AK94: CLOSED | AO94: 45783 | AP94: \\172.28.9.34\Artefacts_T-Fiber TNOC Tracker\DWDM\Artefact - T91 & T92 | AR94: 1
B95: 93 | C95: T92 | D95: 472 | E95: NA | I95: DWDM | J95: Design & Documentation | K95: Link ATP | N95: Colosed | V95: Suresh Kumar | Y95: COMPLETED & APPROVED | Z95: AD-UT-Tfiber | AA95: 45783 | AB95: \\172.28.9.34\Artefacts_T-Fiber TNOC Tracker\DWDM\Artefact - T91 & T92 | AI95: =_xlfn.CONCAT(D95,I95) -> 472DWDM | AJ95: =VLOOKUP(AI95,Table1[[#All],[CONCAT]:[Tfiber]],2,FALSE) -> DWDM | AK95: CLOSED | AO95: 45783 | AP95: \\172.28.9.34\Artefacts_T-Fiber TNOC Tracker\DWDM\Artefact - T91 & T92 | AR95: 1
B96: 94 | C96: T93 | D96: 472 | E96: NA | I96: DWDM | J96: Design & Documentation | K96: Ring ATP | N96: Colosed | V96: Suresh Kumar | Y96: COMPLETED & APPROVED | Z96: AD-UT-Tfiber | AA96: 45783 | AB96: \\172.28.9.34\Artefacts_T-Fiber TNOC Tracker\DWDM\Artefact - T93 | AI96: =_xlfn.CONCAT(D96,I96) -> 472DWDM | AJ96: =VLOOKUP(AI96,Table1[[#All],[CONCAT]:[Tfiber]],2,FALSE) -> DWDM | AK96: CLOSED | AO96: 45783 | AP96: \\172.28.9.34\Artefacts_T-Fiber TNOC Tracker\DWDM\Artefact - T93 | AR96: 1
B97: 95 | C97: T94 | D97: 472 | E97: NA | I97: DWDM | J97: Design & Documentation | K97: DWDM EMS (MCP) Functional ATP | N97: Open | S97: 20-Sep-25: MCP FAT document submitted to TPA on XX-XX-XXXX. Meeting need to be scheduled on 22-Sep-25 with TPA to get the clarifications on delay. 13-Sep-25: Response awaited from TPA team 29-August-2025: Spoken with Mr. Bijju, response awaited 26-July-25: FAT document approval pending 08-July-2025: 1. MCP FAT document prepared as per RFP requirements and TPA remarks 2. 100G traffic throughput will be shown during Ring ATP 07-July-2025: 1. SME not aware of MCP FAT Check list, but prepared FAT document and sent to TPA for validation 05-July-2025: Submitted AT document to T Fiber TPA 30-June-2025: target to submit by 2nd July'25, based on OEM reply Revised version to be submitted as per T Fiber remarks on 29th Apr'25 | T97: TPA | U97: Biju | V97: Suresh Kumar | X97: Open | Y97: WIP | AI97: =_xlfn.CONCAT(D97,I97) -> 472DWDM | AJ97: =VLOOKUP(AI97,Table1[[#All],[CONCAT]:[Tfiber]],2,FALSE) -> DWDM | AK97: OPEN | AN97: Pending from TPA | AR97: 1
B98: 96 | C98: T95 | D98: 472 | E98: NA | I98: DWDM | J98: Integration with OSS | K98: DWDM Network Alarms Integration | N98: Colosed | V98: Suresh Kumar | Y98: COMPLETED & APPROVED | Z98: AD-UT-Tfiber | AA98: 45783 | AB98: \\172.28.9.34\Artefacts_T-Fiber TNOC Tracker\DWDM\Artefact - T95 | AI98: =_xlfn.CONCAT(D98,I98) -> 472DWDM | AJ98: =VLOOKUP(AI98,Table1[[#All],[CONCAT]:[Tfiber]],2,FALSE) -> DWDM | AK98: CLOSED | AO98: 45783 | AP98: \\172.28.9.34\Artefacts_T-Fiber TNOC Tracker\DWDM\Artefact - T95 | AR98: 1
B99: 97 | C99: T96 | D99: 472 | E99: NA | I99: DWDM | J99: Integration with OSS | K99: Hardware Inventory Integration in HPE OSS | N99: Colosed | V99: Suresh Kumar | Y99: COMPLETED & APPROVED | Z99: AD-UT-Tfiber | AA99: 45783 | AB99: \\172.28.9.34\Artefacts_T-Fiber TNOC Tracker\DWDM\Artefact - T96 | AI99: =_xlfn.CONCAT(D99,I99) -> 472DWDM | AJ99: =VLOOKUP(AI99,Table1[[#All],[CONCAT]:[Tfiber]],2,FALSE) -> DWDM | AK99: CLOSED | AO99: 45783 | AP99: \\172.28.9.34\Artefacts_T-Fiber TNOC Tracker\DWDM\Artefact - T96 | AR99: 1
B100: 98 | C100: T97 | D100: 472 | E100: NA | I100: DWDM | J100: Integration with OSS | K100: DWDM Network Topology | N100: Open | S100: 26-July-2025: HPE conveyed that Topology border unable to make bold or hilight 12-July-2025: Update awaited from HPE 07-July-2025: Topology is visible but border is not highlighted. HP checking for the possibility to impose of border map on topology. Required 02 weeks post confirmation 05-July-2025: In discussion with HPE, required 02 weeks post confirmation, 21st July 30-June-2025: As discussed with Suresh P checking with HPE. Tentative date: 16th July. As discussed in the meeting, call to be arranged along with OSS SME and HP team | T100: HPE | U100: Anand | V100: Suresh Kumar | X100: Open | Y100: DEPENDENCY(Client/Ext.) | AI100: =_xlfn.CONCAT(D100,I100) -> 472DWDM | AJ100: =VLOOKUP(AI100,Table1[[#All],[CONCAT]:[Tfiber]],2,FALSE) -> DWDM | AK100: OPEN | AR100: 1
B101: 99 | C101: T98 | D101: 472 | E101: NA | I101: DWDM | J101: Integration with OSS | K101: Auto Ticket & RCA for Fiber Cuts | N101: Colosed | V101: Suresh Kumar | Y101: COMPLETED & APPROVED | Z101: AD-UT-Tfiber | AA101: 45783 | AB101: \\172.28.9.34\Artefacts_T-Fiber TNOC Tracker\DWDM\Artefact - T98 | AI101: =_xlfn.CONCAT(D101,I101) -> 472DWDM | AJ101: =VLOOKUP(AI101,Table1[[#All],[CONCAT]:[Tfiber]],2,FALSE) -> DWDM | AK101: CLOSED | AO101: 45783 | AP101: \\172.28.9.34\Artefacts_T-Fiber TNOC Tracker\DWDM\Artefact - T98 | AR101: 1
B102: 100 | C102: T99 | D102: 472 | E102: NA | I102: DWDM | J102: Integration with OSS | K102: Auto Ticket & RCA for Hardware Failures | N102: Open | V102: Suresh Kumar | Y102: COMPLETED & APPROVED | AI102: =_xlfn.CONCAT(D102,I102) -> 472DWDM | AJ102: =VLOOKUP(AI102,Table1[[#All],[CONCAT]:[Tfiber]],2,FALSE) -> DWDM | AK102: Open | AP102: \\172.28.9.34\Artefacts_T-Fiber TNOC Tracker\DWDM\Artefact - T99 | AR102: 1
...

Sheet Sheet7
A3: Sum of Qty | B3: Column Labels
A4: Row Labels | B4: 472 | C4: MOM | D4: NOC | E4: Grand Total
A5: Completed & Approved | B5: 255 | C5: 271 | D5: 15 | E5: 541
A6: Completed but Verification undrer Process | B6: 45 | C6: 174 | D6: 269 | E6: 488
A7: Open | B7: 172 | C7: 833 | D7: 394 | E7: 1399
A8: Grand Total | B8: 472 | C8: 1278 | D8: 678 | E8: 2428

Sheet Summary-1
A3: Sum of Qty | B3: Column Labels
A4: Row Labels | B4: 472 | C4: MOM | D4: NOC | E4: Grand Total
A5: Closed after June | B5: 54 | C5: 227 | D5: 15 | E5: 296
A6: Closed before june-2025 | B6: 201 | C6: 44 | E6: 245
A7: Completed but Verification undrer Process | B7: 45 | C7: 174 | D7: 269 | E7: 488
A8: Open | B8: 172 | C8: 833 | D8: 394 | E8: 1399
A9: Grand Total | B9: 472 | C9: 1278 | D9: 678 | E9: 2428

Sheet Ramana-Master Tracker 2428
A2: Slno | B2: UniqueID | C2: Category | D2: Meeting Date | E2: Priority | F2: Ramana | G2: Ramana-Domain | H2: Domain | I2: Sub-Domain | J2: Action Point | K2: Impact | L2: Priority | M2: Baseline Status | N2: Application | O2: Module | P2: Remarks | T2: LTTS REMARKS | U2: NSO SD | V2: NSO ED | W2: Created By | X2: NSO Status | Y2: Owner | Z2: Final Approval Status | AC2: Tfiber-Cat | AD2: Derived Status (L&T) | AE2: OSS | AF2: OSS DetailedRemarks | AG2: T/F | AH2: Ramana Remarks as on 19-Sep-2025 | AI2: NSO Comments | AJ2: Review Status | AK2: Review Comments dated on | AL2: Tentative Completion Date | AM2: T Fiber Appoved Date | AN2: Artifacts | AO2: Ramana-Remarks | AP2: Updated on 01-Dec-2025 | AQ2: 45943 | AR2: Remarks(1399)
A3: 1 | B3: T1 | C3: 472 | D3: NA | H3: Security & Regulatory Compliance | I3: Configuration | J3: Integration testing of All supported devices is complete and adding all the devices is underway. | M3: Open | P3: what ever request has come all are integrated with ISE , any new device request comes same will be added . Also Aleppo PO get relaesed for ADintegration , it will also get integrated with AD. | AC3: Security | AD3: Closed | AI3: Organization structure | AM3: 45973 | AN3: \\172.28.9.34\Artefacts_T-Fiber TNOC Tracker\NW-Security\T1_01-Nov-25.pdf | AO3: Completed & Approved | AP3: Closed after 07-Nov-25 | AQ3: Open
A4: 2 | B4: T2 | C4: 472 | D4: NA | H4: DWDM | I4: Integration with Alepo | J4: RADIUS Configuration Testing on Ciena Node & EMS (MCP) | M4: Colosed | AC4: DWDM | AD4: Closed | AI4: Received sample doc from Manoj | AM4: 45783 | AN4: \\172.28.9.34\Artefacts_T-Fiber TNOC Tracker\DWDM\Artefact - T106 | AO4: Completed & Approved | AP4: Closed before june-2025 | AQ4: Closed before june-2025
A5: 3 | B5: T3 | C5: 472 | D5: NA | H5: Security & Regulatory Compliance | I5: Integration | J5: Accouting data from Ciena MCP and field nodes to be captured in Alepo AAA | L5: Critical | M5: Open | P5: 28-Nov-25: The Alepo team is integrating AD Once done these points will be closed. MCP upgradation is in pipeline . same will be completed by 25 Sep 2025 | AC5: Security | AD5: OPEN | AI5: Is this IPv4 and IPv6 | AO5: Open | AP5: Open | AQ5: Open
A6: 4 | B6: T3 | C6: 472 | D6: NA | H6: DWDM | I6: Integration with Alepo | J6: TACACS+/Radius testing for AAA on ciena node | M6: Open | P6: 28-Nov-25: The Alepo team is integrating AD Once done these points will be closed. 20-09-2025: 8.1 MCP software Patch upgradation will be completed by 27-Sep-25, After completetion of upgrdation AAA functi | Q6: ona | R6: litie | S6: s wi | T6: ll be tes | U6: for ciena d | W6: evi | X6: ces | AA6: by | AB6: using radius 13-09-25:MCP upgradation is in progress, will be able to check the logs by next week 28-08-2025: Activity is in progress, target to complete by 25th Sep'25 Authentication and Authorization tested and found OK for Node and MCP. 19-08-2025: Due to issue in disk partition and file type of storage, activity is not started 10-08-2025: OEM confirmation recieved and activity is planned from 18th August'25. 05-July-2025: DC OSS to DR MCP communication is through now, need to integrate and test before activity 12-July-2025: DC OSS to DR MCP integration testing done. Alarms and Autoticketing functioning as expected. Upgradation activity will be scheduled as per OEM confirmation, Target date - 30-07-25 26-July-2025: Schedule awaited from OEM 30-June-2025: DC OSS to DR MCP connectivity to be extended for PE approval, WIP. Target date - 30-07-25 15-06-25: Targeting to close the upgradation by month end, 30-06-25 30-05-2025: Accounting issue resolved in latest MCP version, verified in 8.2 Ver (Node logs are now capturing in MCP). Upgradation schedule awaited from Teleindia for our MCP from 7.1-P02 5/21/2025: Correlation to identified to find the user logged in at the specific time 28APR'25: As discussed with Sanjay sir, if user id not avaialble pls. try for correlation with IP. Some how Correlation to be done. In Accounting, Node and MCP logs are successfully reporting in Alepo with below limitation. Node Logs - Active profile name (ADMIN/RADIUS) is displayed against User ID (Ciena confirmed it is as per design no changes are possible) | AC6: DWDM | AD6: OPEN | AI6: what are these services | AO6: Completed but Verification undrer Process | AP6: Completed but Verification undrer Process | AQ6: Completed but Verification undrer Process
A7: 5 | B7: T4 | C7: 472 | D7: NA | H7: Security & Regulatory Compliance | I7: Security | J7: Alepo confirmed that Alepo AAA supports TACACS, Alepo to test Nokia and Ciena nodes integration on TACACS , with supporting artefacts of testing. 1.TACACS Testing with Tejas, Nokia, Ciena 2. Alepo Testing with Tejas, Nokia and Ciena | M7: Open | P7: 28-Nov-25: The Alepo team is integrating AD Once done these points will be closed. 1.TACACS Testing with Tejas, Nokia, Ciena completed 2. Alepo Testing with Tejas, Nokia and Ciena | AC7: Security | AD7: OPEN | AI7: We have development VM's but not testing kindly clarity | AO7: Completed but Verification undrer Process | AP7: Completed but Verification undrer Process | AQ7: Completed but Verification undrer Process
A8: 6 | B8: T5 | C8: 472 | D8: NA | H8: Security & Regulatory Compliance | I8: Functional AT | J8: Had a meeting with Ashwani from Alepo and sent him updated test cases. He is working on data gathering and will send us back by Tuesday. | M8: Open | P8: FAT were submitted to customer, Customer observation in being work out. Target to resubmission.- 23.07.25 | AC8: Security | AD8: Closed | AM8: 45960 | AN8: \\172.28.9.34\Artefacts_T-Fiber TNOC Tracker\NW-Security\T5_29-Oct-25.pdf | AO8: Closed | AP8: Closed After 14-Oct | AQ8: Completed but Verification undrer Process
A9: 7 | B9: T6 | C9: 472 | D9: NA | H9: BSS | I9: Installation | J9: Installation of BSS Application | M9: Open | P9: 29-08-2025: Design and Solution document to be shared with GM NOC and Physical instllation of BSS need to validate according to solution from L&T Side before submitting for for review with T Fiber 26-06- | Q9: 202 | R9: 5: We | S9: hav | T9: e offered | U9: stallation A | W9: T. | X9: TFI | AA9: BER | AB9: has asked DC architecture review including license validity | AC9: Applications/Tools | AD9: OPEN | AO9: Completed but Verification undrer Process | AP9: Completed but Verification undrer Process | AQ9: Completed but Verification undrer Process
A10: 8 | B10: T7 | C10: 472 | D10: NA | H10: BSS | I10: Integration | J10: Initial Integration with Third Party Applications (OSS & NSO) | M10: Open | P10: 26-06-2025: OSS Integration is done. NSO integration is pending. Awaiting NSO Team. | AC10: Applications/Tools | AD10: OPEN | AO10: Open | AP10: Open | AQ10: Open
A11: 9 | B11: T8 | C11: 472 | D11: NA | H11: BSS | I11: Integration | J11: OSS interfaces | M11: Open | P11: 26-06-2025: Feasibility API & Ticket API integration is completed. | AC11: Applications/Tools | AD11: OPEN | AI11: Ask Ritik | AO11: Open | AP11: Open | AQ11: Open
A12: 10 | B12: T9 | C12: 472 | D12: NA | H12: BSS | I12: Integration | J12: NSO interfaces | M12: Open | P12: 26-06-2025: Awaiting NSO Team | AC12: Applications/Tools | AD12: OPEN | AO12: Open | AP12: Open | AQ12: Open
A13: 11 | B13: T10 | C13: 472 | D13: NA | H13: BSS | I13: Integration | J13: GeM Portal | M13: Open | AC13: Applications/Tools | AD13: CLOSED | AM13: 45854 | AN13: \\172.28.9.34\share drive\Artefacts_T-Fiber TNOC Tracker\BSS\Artifact_T10 | AO13: Open | AP13: Open | AQ13: Open
A14: 12 | B14: T11 | C14: 472 | D14: NA | H14: BSS | I14: Development and unit testing | J14: Import Sub-Departments, Import Leads, Campaign Management, Opportunity/Quote/order Management, order booking and Service Order workflow for tested services | M14: Open | P14: 29-08-2025: All points are completed Import Sub-Departments, Import Leads, Opportunity/Quote/order Management, order booking and Service Order workflow for tested services Demo to be conducted to TFIBER. | Q14: "Ca | R14: mpaig | S14: n Ma | T14: nagement" | U14: Pending whe | W14: re | X14: inp | AA14: uts | AB14: are required from TFIBER Business team 26-06-2025: Awaiting few inputs from TFIBER | AC14: Applications/Tools | AD14: OPEN | AO14: Open | AP14: Open | AQ14: Open
A15: 13 | B15: T12 | C15: 472 | D15: NA | H15: BSS | I15: Development and unit testing | J15: Product/Service Catalogue integration | M15: Open | P15: 29-08-2025: Feature is available to admin User(Product Team) to configure new product based on requirement. BSS Team will provide Demo to the TFIBER (business team([Uday]/Solution Team[Sanjay]) for their | Q15: acc | R15: eptan | S15: ce. | T15: 26-06-202 | U15: Artifacts su | W15: bmi | X15: tte | AA15: d. C | AB15: losure review is pending with TFIBER | AC15: Applications/Tools | AD15: OPEN | AI15: Jayant Sir | AO15: Completed but Verification undrer Process | AP15: Completed but Verification undrer Process | AQ15: Completed but Verification undrer Process
A16: 14 | B16: T13 | C16: 472 | D16: NA | H16: BSS | I16: Development and unit testing | J16: Billing, Discounts & Adjustments, Invoice generation, Bill Formatting | M16: Open | P16: 29-08-2025: Feature is made available in the BSS application, BSS Team will provide demo to TFIBER Team (Business [Uday] & Finance[Bhaskar]) 26-06-2025: Artifacts submitted. Closure review is pending with | Q16: TFI | R16: BER | AC16: Applications/Tools | AD16: OPEN | AO16: Completed but Verification undrer Process | AP16: Completed but Verification undrer Process | AQ16: Completed but Verification undrer Process
A17: 15 | B17: T14 | C17: 472 | D17: NA | H17: BSS | I17: Development and unit testing | J17: Feasibility API response from OSS for service provisioning request | M17: Open | P17: 29-08-2025: Feaibility API is already integrated with BSS and demonstrated in GIBB demo and it is applicable for all products. 26-06-2025: Artifacts submitted. Closure review is pending with TFIBER | AC17: Applications/Tools | AD17: OPEN | AO17: Completed but Verification undrer Process | AP17: Completed but Verification undrer Process | AQ17: Completed but Verification undrer Process
A18: 16 | B18: T15 | C18: 472 | D18: NA | H18: BSS | I18: Development and unit testing | J18: SMS notification, email gateway, Field engineer mobile app readiness | M18: Open | P18: 29-08-2025: Integration is already completed and applicable for all product same has demonstrated to TFIBER during GIBB demo session. 26-06-2025: Artifacts submitted. Closure review is pending with TFIBER | AC18: Applications/Tools | AD18: OPEN | AO18: Open | AP18: Open | AQ18: Open
A19: 17 | B19: T16 | C19: 472 | D19: NA | H19: BSS | I19: Development and unit testing | J19: Service Assurance and trouble tickets | M19: Open | P19: 29-08-2025: Integration with Service Manager is done for technical ticket and BSS have functionality to handle the non-technical ticket in BSS itself. BSS team will demonstrate this functionality to TFIBER | Q19: . S | R19: anjay | S19: Sir | T19: needs to | U19: nfirm demo d | W19: ate | X19: . 2 | AA19: 45814 | AB19: -2025: Artifacts submitted. Closure review is pending with TFIBER | AC19: Applications/Tools | AD19: OPEN | AO19: Completed but Verification undrer Process | AP19: Completed but Verification undrer Process | AQ19: Completed but Verification undrer Process
A20: 18 | B20: T17 | C20: 472 | D20: NA | H20: BSS | I20: Development and unit testing | J20: Customer Self care portal development for T-CELL, T-NET, L0 | M20: Open | P20: 29-08-2025: Webportal is available. BSS team needs to demonstrate to TFIBER team. Sanjay Sir needs to confirm demo date. 26-06-2025: Artifacts submitted. Closure review is pending with TFIBER | AC20: Applications/Tools | AD20: OPEN | AO20: Open | AP20: Open | AQ20: Open
A21: 19 | B21: T18 | C21: 472 | D21: NA | H21: BSS | I21: Integration | J21: Integration modules Like on board Un-Assist & dependent module to be completed for all products from system to be initiated a workshop and to be closed in next 2 Weeks | M21: Open | P21: 29-08-2025: Seek input from Business team (Uday) and deploy post assisted completion. 26-06-2025: Input awaited from TFIBER | AC21: Applications/Tools | AD21: OPEN | AO21: Open | AP21: Open | AQ21: Open
A22: 20 | B22: T19 | C22: 472 | D22: NA | H22: BSS | I22: MoM Action | J22: T-Cell service definition for workflow implementation in BSS for creating Spoke primary and secondary | M22: Open | P22: 29-08-2025:Update product concept note similar to GIBB and share with TFIBER for review 26-06-2025: We can deliver this post getting product concept note from TFIBER | AC22: Applications/Tools | AD22: OPEN | AO22: Open | AP22: Open | AQ22: Open
A23: 21 | B23: T20 | C23: 472 | D23: NA | H23: BSS | I23: Development and unit testing | J23: Rules for primary and secondary spoke implementation in BSS- - GP with shortest distance will be primary - To display dropdown and concerned user group to select and confirm | M23: Open | P23: #N/A | AC23: Applications/Tools | AD23: OPEN | AO23: Open | AP23: Open | AQ23: Open
A24: 22 | B24: T21 | C24: 472 | D24: NA | H24: BSS | I24: MoM Action | J24: BSS firewall ports required for Security compliance | M24: Open | P24: BSS has to forward list of Port as per deiffrent modules of application | AC24: Applications/Tools | AD24: Closed | AM24: 45962 | AN24: \\172.28.9.34\Artefacts_T-Fiber TNOC Tracker\NW-Security\T21_31-Oct-25.pdf | AO24: Closed | AP24: Closed After 14-Oct | AQ24: Open
A25: 23 | B25: T22 | C25: 472 | D25: NA | H25: BSS | I25: Security | J25: Roadmap for password policy implementation in CSP | M25: Open | P25: Ciriteria for Paswword policy hase been Shared wioth BSS team . BSS team has to implement and submit report for verifications. 30-Oct-25: Ciriteria for Paswword policy hase been Shared wioth BSS team . BSS | Q25: te | R25: am ha | S25: s to | T25: implemen | U25: nd submit re | W25: por | X25: t f | AA25: or v | AB25: erifications. Point to be moved to BSS | AC25: Applications/Tools | AD25: OPEN | AO25: Open | AP25: Open | AQ25: Open
A26: 24 | B26: T23 | C26: 472 | D26: NA | H26: BSS | I26: Security | J26: DMZ requirements for CSP | M26: Open | P26: IP amd URL required by BSS foir NAT through DMZ has been Completed | AC26: Applications/Tools | AD26: Closed | AM26: 45962 | AN26: \\172.28.9.34\Artefacts_T-Fiber TNOC Tracker\NW-Security\T23_31-Oct-25.pdf | AO26: Closed | AP26: Closed After 14-Oct | AQ26: Open
A27: 25 | B27: T24 | C27: 472 | D27: NA | H27: BSS | I27: MoM Action | J27: PoP location confirmation usergroup for connectivity to O&M | M27: Open | P27: 29-08-2025: Seek input from O&M team (Umesh) 26-06-2025: Input awaited from TFIBER | AC27: Applications/Tools | AD27: OPEN | AO27: Open | AP27: Open | AQ27: Open
A28: 26 | B28: T25 | C28: 472 | D28: NA | H28: BSS | I28: MoM Action | J28: Product concept note configuration in BSS queries to be shared | M28: Open | P28: 29-08-2025: Queries to be prepared and share with TFIBER for discussion. 17-07-2025: Business Team of TFIBER needs to finalize and confirm all product. 26-06-2025: Need Product concept note from TFIBER | AC28: Applications/Tools | AD28: OPEN | AI28: BSS | AO28: Open | AP28: Open | AQ28: Open
A29: 27 | B29: T26 | C29: 472 | D29: NA | H29: BSS | I29: MoM Action | J29: Location id logic for NSO provisioning | M29: Open | P29: 29-08-2025: Ciruit ID logic PPT shared by Sivakumar, needs to use and implement in BSS. 26-06-2025: Timeline 30th July is considering NSO support is available in 2-3 days | AC29: Applications/Tools | AD29: OPEN | AO29: Open | AP29: Open | AQ29: Open
A30: 28 | B30: T27 | C30: 472 | D30: NA | H30: BSS | I30: Integration | J30: Tariff plan parameters viz. 5G, 4G finalisation. (BSS should capture QOS parameter & Requirements) | M30: Open | P30: 29-08-2025: Product Can be configured in BSS product catalogue Demo to be given to TFIBER 26-06-2025: Input awaited from TFIBER | AC30: Applications/Tools | AD30: OPEN | AO30: Open | AP30: Open | AQ30: Open
A31: 29 | B31: T28 | C31: 472 | D31: NA | H31: IP/MPLS | I31: Functional AT | J31: Internal AT 83% complete. Waiting Cisco to update data sent by Vikram and then we will submit to TPA ( for pending cases, we just need a maintanence window to test as it is impacting activity) This is for ISE | M31: Open | P31: 28-Nov-25: Document preparation in progress once done points will be closed. FAT documents were submitted to TPA , However it has some common observation which will be discussed with TPA team by Mr Sharma. | Q31: Su | R31: bsequ | S31: entl | T31: y , corre | U31: on will be m | W31: ade | X31: in | AA31: FAT | AB31: doc | AC31: IPMPLS | AD31: OPEN | AO31: Open | AP31: Open | AQ31: Open
A32: 30 | B32: T29 | C32: 472 | D32: NA | H32: IP/MPLS | I32: Functional AT | J32: CSM is having memory issues. Need to sort it out before we do AT. Working on settling that with Cisco. Memory will be allocated and tested in the first week of July | M32: Open | P32: CSM has been replaced by ASDM | AC32: IPMPLS | AD32: Closed | AI32: Jayant Sir | AM32: 45960 | AN32: \\172.28.9.34\Artefacts_T-Fiber TNOC Tracker\NW-Security\M1145_29-Oct-25.pdf | AO32: Closed | AP32: Closed After 14-Oct | AQ32: Open
A33: 31 | B33: T30 | C33: 472 | D33: NA | H33: IP/MPLS | I33: Functional AT | J33: Internal AT 72% complete. Waiting on Cisco to update data sent by Vikram and then we will submit to TPA. ( for pending cases, we just need a maintanence window to test as it is impacting activity) | M33: Open | P33: 28-Nov-25: Document preparation in progress once done points will be closed. FAT documents were submitted to TPA , However it has some common observation which will be discussed with TPA team by Mr Sharma. | Q33: Su | R33: bsequ | S33: entl | T33: y , corre | U33: on will be m | W33: ade | X33: in | AA33: FAT | AB33: doc | AC33: IPMPLS | AD33: OPEN | AO33: Open | AP33: Open | AQ33: Open
A34: 32 | B34: T31 | C34: 472 | D34: NA | H34: Security & Regulatory Compliance | I34: Security | J34: Internal Audit for all applications | M34: Open | P34: 28-Nov-25: VAPT is going on, once VAPT is done points will be closed. Application audited partally , howver PT audit couldnot be done due to lack of necessary tools. Same has been requested with LTTS team | Q34: , b | R34: ut it | S34: cou | T34: ld not be | U34: terialised. | AC34: Security | AD34: OPEN | AO34: Open | AP34: Open | AQ34: Open
A35: 33 | B35: T32 | C35: 472 | D35: NA | H35: Security & Regulatory Compliance | I35: Security | J35: Internal audit for network elements | M35: Open | P35: 28-Nov-25: VAPT is going on, once VAPT is done points will be closed. Network elemants auditted including NOC end points , However PT for same is pending. | AC35: Security | AD35: OPEN | AI35: Venkatesh | AO35: Open | AP35: Open | AQ35: Open
A36: 34 | B36: T33 | C36: 472 | D36: NA | H36: BSS | I36: Security | J36: Security policies to evolve related to DOT/CDOT etc | M36: Open | P36: 29-08-2025: Collect data from Sivakumar and read user to access the data by DOT. 26-06-2025: Waiting for inputs for multiple deliverables | AC36: Applications/Tools | AD36: OPEN | AO36: Open | AP36: Open | AQ36: Open
A37: 35 | B37: T34 | C37: 472 | D37: NA | H37: IP/MPLS | I37: Security | J37: external Audit for all applications (Tfiber will be arranging a partner for third party audit) | M37: Open | P37: 28-Nov-25: VAPT is going on, once VAPT is done points will be closed. Awaited TSTG Audit party to engage. | AC37: IPMPLS | AD37: OPEN | AM37: 46010 | AO37: Completed &Approved | AP37: Closed after 14-Dec-25 | AQ37: Completed &Approved
A38: 36 | B38: T35 | C38: 472 | D38: NA | H38: IP/MPLS | I38: Security | J38: external audit for network elements(Tfiber will be arranging a partner for third party audit) | M38: Open | P38: 28-Nov-25: VAPT is going on, once VAPT is done points will be closed. Awaited TSTG Audit party to engage | AC38: IPMPLS | AD38: OPEN | AM38: 46010 | AO38: Completed &Approved | AP38: Closed after 14-Dec-25 | AQ38: Completed &Approved
A39: 37 | B39: T36 | C39: 472 | D39: NA | H39: Security & Regulatory Compliance | I39: Security | J39: Physical user access | M39: Open | P39: Has completed , Artefacts will be resubmitted. | AC39: Security | AD39: Closed | AM39: 45960 | AN39: \\172.28.9.34\Artefacts_T-Fiber TNOC Tracker\NW-Security\T36_28-Oct-25.pdf | AO39: Closed | AP39: Closed After 14-Oct | AQ39: Open
A40: 38 | B40: T37 | C40: 472 | D40: NA | H40: Security & Regulatory Compliance | I40: Security | J40: Virtual user access-VPN | M40: Open | P40: Has completed , Artefacts will be resubmitted. | AC40: Security | AD40: Closed | AI40: Jyothi | AM40: 45960 | AN40: \\172.28.9.34\Artefacts_T-Fiber TNOC Tracker\NW-Security\T37_28-Oct-25.pdf | AO40: Closed | AP40: Closed After 14-Oct | AQ40: Open
A41: 39 | B41: T38 | C41: 472 | D41: NA | H41: Security & Regulatory Compliance | I41: Security | J41: Role based severity access | M41: Open | P41: 28-Nov-25: Work in Progress. Completed and Review pending. Artfacts submitted | AC41: Security | AD41: OPEN | AI41: Jayant Sir | AO41: Open | AP41: Open | AQ41: Open
A42: 40 | B42: T39 | C42: 472 | D42: NA | H42: Security & Regulatory Compliance | I42: Security | J42: ISE integration with Cisco elements | M42: Open | P42: 28-Nov-25: Work in Progress. Artefacts will be submitted. | AC42: Security | AD42: OPEN | AO42: Completed but Verification undrer Process | AP42: Completed but Verification undrer Process | AQ42: Completed but Verification undrer Process
A43: 41 | B43: T40 | C43: 472 | D43: NA | H43: Security & Regulatory Compliance | I43: Regulatory | J43: Regulatory Compliance with respect DoT policies 1. Security Policy-Complied 2. Security Architecture of Telecom Network-Complied 3. Information Security Risk Assessment and Risk Treatment processes and their implementation plan-WIP, Target: Dec 2024 reviewed with customer. 4. Recruitment processes and employee's record-WIP, Target:12-10-2025 5. Controls for effectiveness of security management-WIP, Target: 28 -02-2025 6. Evidence of monitoring, measurement results and management reviews of security management-WIP, Target: 28-02-2025 7. Security Audit programs and audit results-Complied 8. Inventory management and classification of information assets and their handling Completed 9. Procedure for responding to information and network security incidents-WIP, Target: 28-02-2025 - SIRT reviewed 10. Main S/W updation and changes-WIP, Target: 28-02-2025 11. Supply chain of products (HW/SW). To be taken from manufacturer/supplier-Communicated to Sekhar. WIP, Target: 14-02-2025 12. SW details and documentation obtained from manufacturers/supplier-Communicated to Sekhar WIP, Target: 14-02-2025 13. O&M procedures in the form of manual-O&M manual and OEM wise manuals WIP, Target: 14-02-2025 14. Processes for internal and external communication relevant to the security management-WIP, Target: 07-3-2025 | M43: Open | P43: 28-Nov-25: Document preparation in progress once done points will be closed. Confirmation of purchase of ISE. License needed to upgrade for HA | AC43: Security | AD43: OPEN | AO43: Open | AP43: Open | AQ43: Open
A44: 42 | B44: T41 | C44: 472 | D44: NA | H44: DC-IT | I44: Servers and Strorage (Deployment and Installations) | J44: 1. Compute & Storage | M44: Open | P44: 11-Oct-25: As per the OEM's/SME's request, storage is allocated as per requirements. Artifacts are Captured. OEM Confirmation Emails to be captured as a Reference. | AC44: Network | AD44: OPEN | AO44: Open | AP44: Open | AQ44: Open
A45: 43 | B45: T42 | C45: 472 | D45: NA | H45: DC-IT | I45: Servers and Strorage (Deployment and Installations) | J45: 2. Virtulization | M45: Colosed | AC45: Network | AD45: Closed | AM45: 45791 | AN45: \\172.28.9.34\share drive\Artefacts_T-Fiber TNOC Tracker\DC IT-Infra\Artifact for -T42 | AO45: Completed & Approved | AP45: Closed before june-2025 | AQ45: Closed before june-2025
A46: 44 | B46: T43 | C46: 472 | D46: NA | H46: DC-IT | I46: Servers and Strorage (Deployment and Installations) | J46: 3. Anti-virus | M46: Colosed | AC46: Network | AD46: Closed | AM46: 45791 | AN46: \\172.28.9.34\share drive\Artefacts_T-Fiber TNOC Tracker\DC IT-Infra\Artifact for -T43 | AO46: Completed & Approved | AP46: Closed before june-2025 | AQ46: Closed before june-2025
A47: 45 | B47: T44 | C47: 472 | D47: NA | H47: DC-IT | I47: Servers and Strorage (Deployment and Installations) | J47: 4. VM's Deployment Application Installations | M47: Colosed | AC47: Network | AD47: Closed | AM47: 45791 | AN47: \\172.28.9.34\share drive\Artefacts_T-Fiber TNOC Tracker\DC IT-Infra\Artifact for -T44 | AO47: Completed & Approved | AP47: Closed before june-2025 | AQ47: Closed before june-2025
A48: 46 | B48: T45 | C48: 472 | D48: NA | H48: DC-IT | I48: Commvault Backup | J48: Application Installation | M48: Colosed | AC48: Network | AD48: Closed | AM48: 45791 | AN48: \\172.28.9.34\Artefacts_T-Fiber TNOC Tracker\DC IT-Infra\Artifact for - T45 | AO48: Completed & Approved | AP48: Closed before june-2025 | AQ48: Closed before june-2025
A49: 47 | B49: T46 | C49: 472 | D49: NA | H49: DC-IT | I49: Commvault Backup | J49: Application Configuration | M49: Colosed | AC49: Network | AD49: Closed | AM49: 45791 | AN49: \\172.28.9.34\Artefacts_T-Fiber TNOC Tracker\DC IT-Infra\Artifact for - T46 | AO49: Completed & Approved | AP49: Closed before june-2025 | AQ49: Closed before june-2025
A50: 48 | B50: T47 | C50: 472 | D50: NA | H50: DC-IT | I50: Commvault Backup | J50: Application Installation AT | M50: Colosed | AC50: Network | AD50: Closed | AM50: 45791 | AN50: \\172.28.9.34\Artefacts_T-Fiber TNOC Tracker\DC IT-Infra\Artifact for - T47 | AO50: Completed & Approved | AP50: Closed before june-2025 | AQ50: Closed before june-2025
A51: 49 | B51: T48 | C51: 472 | D51: NA | H51: DC-IT | I51: Commvault Backup | J51: Application Functional AT | M51: Open | P51: Working on the Extra Test cases which are received from the TPA & T-Fiber. | AC51: Network | AD51: OPEN | AI51: Jyothi | AO51: Open | AP51: Open | AQ51: Open
A52: 50 | B52: T49 | C52: 472 | D52: NA | H52: DC-IT | I52: LLD | J52: LLD Approved conditionally with few punch points. Updated LLD to be submitted | M52: Open | P52: Working on DC IT-Infra Server and storage-MoM Points received from the T-Fiber. | AC52: Network | AD52: OPEN | AI52: Jyothi | AO52: Completed but Verification undrer Process | AP52: Completed but Verification undrer Process | AQ52: Completed but Verification undrer Process
A53: 51 | B53: T50 | C53: 472 | D53: NA | H53: DC-IT | I53: MoM Action | J53: Radware , A10 Configuration file needed to be shared to RaviKishore | M53: Open | P53: Artfacts submitted . point Closure on 10 Jul 25 | AC53: Network | AD53: Closed | AN53: \\172.28.9.34\Artefacts_T-Fiber TNOC Tracker\NW-Security\T50 | AO53: Completed & Approved | AP53: Closed before june-2025 | AQ53: Closed after June
A54: 52 | B54: T51 | C54: 472 | D54: NA | H54: DC-IT | I54: Commvault Backup | J54: Backup retention and Backup activity (such as when incremental backup,full backup are scheduled and time duration required to complete such backup). Application Wise Backup Retention should be as per DOT Guidelines | M54: Colosed | AC54: Network | AD54: Closed | AM54: 45791 | AN54: \\172.28.9.34\Artefacts_T-Fiber TNOC Tracker\DC IT-Infra\Artifact for - T51 | AO54: Completed & Approved | AP54: Closed before june-2025 | AQ54: Closed before june-2025
A55: 53 | B55: T52 | C55: 472 | D55: NA | H55: DC-IT | I55: Commvault Backup | J55: Backup solution should have hot , cold and archieve storage inorder to decrease the backup size/capacity in long run. | M55: Colosed | AC55: Network | AD55: Closed | AM55: 45791 | AN55: \\172.28.9.34\share drive\Artefacts_T-Fiber TNOC Tracker\DC IT-Infra\Artifact for - T52 | AO55: Completed & Approved | AP55: Closed before june-2025 | AQ55: Closed before june-2025
A56: 54 | B56: T53 | C56: 472 | D56: NA | H56: DC-IT | I56: SSD storage migration – EPNM/PI | J56: EPNM/PI VMs migration to SSD Storage | M56: Colosed | AC56: Network | AD56: Closed | AM56: 45791 | AN56: \\172.28.9.34\share drive\Artefacts_T-Fiber TNOC Tracker\DC IT-Infra\Artifact for - T53 | AO56: Completed & Approved | AP56: Closed before june-2025 | AQ56: Closed before june-2025
A57: 55 | B57: T54 | C57: 472 | D57: NA | H57: DC-IT | I57: SSD storage migration – ISE/FMC | J57: ISE & FMC VMs migration to SSD Storage | M57: Colosed | AC57: Network | AD57: Closed | AI57: kartheek | AM57: 45791 | AN57: \\172.28.9.34\share drive\Artefacts_T-Fiber TNOC Tracker\DC IT-Infra\Artifact for - T54 | AO57: Completed & Approved | AP57: Closed before june-2025 | AQ57: Closed before june-2025
A58: 56 | B58: T55 | C58: 472 | D58: NA | H58: DC-IT | I58: MoM Action | J58: VM Placing should be verified & rectified, Same service VM needs to be placed in different Physical Server/host. | M58: Colosed | AC58: Network | AD58: Closed | AM58: 45791 | AN58: \\172.28.9.34\share drive\Artefacts_T-Fiber TNOC Tracker\DC IT-Infra\Artifact for - T55 | AO58: Completed & Approved | AP58: Closed before june-2025 | AQ58: Closed before june-2025
A59: 57 | B59: T56 | C59: 472 | D59: NA | H59: DC-IT | I59: MoM Action | J59: SOP documents needs to be provided | M59: Open | P59: SOP documents submitted to Operations team. Remaining pending documents to be prepared periodically. | AC59: Network | AD59: OPEN | AO59: Open | AP59: Open | AQ59: Open
A60: 58 | B60: T57 | C60: 472 | D60: NA | H60: DC-IT | I60: LLD | J60: Approved conditionally with few punch points. Updated LLD to be submitted | M60: Open | P60: 14-Aug-25 : Discussion was done with TPA and Tfiber and submitted updated LLD document. 18-Jun-25 : Updated DC Network LLD submitted on 18-Jun-25 for TFiber review | AC60: Network | AD60: Closed | AM60: 45883 | AN60: \\172.28.9.34\Artefacts_T-Fiber TNOC Tracker\IPMPLS\DC Network LLD V1.7 14-Aug-2025.pdf | AO60: Completed & Approved | AP60: Closed before june-2025 | AQ60: Closed after June
A61: 59 | B61: T58 | C61: 472 | D61: NA | H61: DC-IT | I61: Cisco EPNM | J61: Cisco EPNM infrastructure AT | M61: Open | P61: 22-Sep-25: IPMPLS Domain team to submit detailed remarks on raised queries. 08-Jul-2025 - Sandeep will come back by EoD today on extension of Cisco support renewal 01-Jul-25 : Revised FAT documents submiss | Q61: ion | R61: pend | S61: ing | T61: (TPA obs | U61: ations to be | W61: in | X61: clu | AA61: ded) | AB61: OEM(Cisco) suport is required to show the new test cases, Inputs provided to OEM on 14th May & 30th Jun. OEM onboarding is in progress & LnT Contracts team coordinating | AC61: Network | AD61: OPEN | AI61: erv | AO61: Completed but Verification undrer Process | AP61: Completed but Verification undrer Process | AQ61: Completed but Verification undrer Process
A62: 60 | B62: T59 | C62: 472 | D62: NA | H62: DC-IT | I62: Cisco PI | J62: Cisco prime infrastructure AT | M62: Open | P62: 22-Sep-25: IPMPLS Domain team to submit detailed remarks on raised queries. 08-Jul-2025 - Sandeep will come back by EoD today on extension of Cisco support renewal 01-Jul-25 : Revised FAT documents submiss | Q62: ion | R62: pend | S62: ing | T62: (TPA obs | U62: ations to be | W62: in | X62: clu | AA62: ded) | AB62: OEM(Cisco) suport is required to show the new test cases, Inputs provided to OEM on 14th May & 30th Jun. OEM onboarding is in progress & LnT Contracts team is coordinating | AC62: Network | AD62: OPEN | AI62: erv | AO62: Completed but Verification undrer Process | AP62: Completed but Verification undrer Process | AQ62: Completed but Verification undrer Process
A63: 61 | B63: T60 | C63: 472 | D63: NA | H63: DC-IT | I63: NTP | J63: Installation | M63: Colosed | AC63: Network | AD63: Closed | AM63: 45782 | AN63: \\172.28.9.34\Artefacts_T-Fiber TNOC Tracker\IPMPLS\Primary NTP - T60,T61,T62.pdf \\172.28.9.34\Artefacts_T-Fiber TNOC Tracker\IPMPLS\Secondary NTP - T60,T61,T62.pdf | AO63: Completed & Approved | AP63: Closed before june-2025 | AQ63: Closed before june-2025
A64: 62 | B64: T61 | C64: 472 | D64: NA | H64: DC-IT | I64: NTP | J64: Configuration | M64: Colosed | AC64: Network | AD64: Closed | AM64: 45782 | AN64: \\172.28.9.34\Artefacts_T-Fiber TNOC Tracker\IPMPLS\Primary NTP - T60,T61,T62.pdf \\172.28.9.34\Artefacts_T-Fiber TNOC Tracker\IPMPLS\Secondary NTP - T60,T61,T62.pdf | AO64: Completed & Approved | AP64: Closed before june-2025 | AQ64: Closed before june-2025
A65: 63 | B65: T62 | C65: 472 | D65: NA | H65: DC-IT | I65: NTP | J65: NTP Installation AT | M65: Colosed | AC65: Network | AD65: Closed | AM65: 45782 | AN65: \\172.28.9.34\Artefacts_T-Fiber TNOC Tracker\IPMPLS\Primary NTP - T60,T61,T62.pdf \\172.28.9.34\Artefacts_T-Fiber TNOC Tracker\IPMPLS\Secondary NTP - T60,T61,T62.pdf | AO65: Completed & Approved | AP65: Closed before june-2025 | AQ65: Closed before june-2025
A66: 64 | B66: T63 | C66: 472 | D66: NA | H66: DC-IT | I66: NTP | J66: NTP Functional AT | M66: Open | AC66: Network | AD66: Closed | AM66: 45841 | AN66: \\172.28.9.34\Artefacts_T-Fiber TNOC Tracker\IPMPLS\NTP FAT & Acceptance - T63.pdf | AO66: Completed & Approved | AP66: Closed before june-2025 | AQ66: Closed after June
A67: 65 | B67: T64 | C67: 472 | D67: NA | H67: DC-IT | I67: Functional AT | J67: DC Network Infra AT | M67: Open | P67: 22-Sep-25: IPMPLS Domain team to submit detailed remarks on raised queries. 08-Jul-2025 - Sandeep will come back by EoD today on extension of Cisco support renewal 01-Jul-25 : Revised FAT documents submiss | Q67: ion | R67: pend | S67: ing | T67: (TPA obs | U67: ations to be | W67: in | X67: clu | AA67: ded) | AB67: OEM(Cisco) suport is required to show the new test cases, Inputs provided to OEM on 14th May & 30th Jun. OEM onboarding is in progress & LnT Contracts team is coordinating | AC67: Network | AD67: OPEN | AI67: erv | AO67: Completed but Verification undrer Process | AP67: Completed but Verification undrer Process | AQ67: Completed but Verification undrer Process
A68: 66 | B68: T65 | C68: 472 | D68: NA | H68: DR | I68: Servers and Strorage (Deployment and Installations) | J68: Virtulization | M68: Colosed | AC68: DR | AD68: Closed | AM68: 45791 | AN68: \\172.28.9.34\share drive\Artefacts_T-Fiber TNOC Tracker\DR\Artifact for - T65 | AO68: Completed & Approved | AP68: Closed before june-2025 | AQ68: Closed before june-2025
A69: 67 | B69: T66 | C69: 472 | D69: NA | H69: DR | I69: DC (TNOC-DR) | J69: Network Readiness | M69: Colosed | AC69: DR | AD69: Closed | AM69: 45791 | AN69: \\172.28.9.34\Artefacts_T-Fiber TNOC Tracker\DR\Artifact for - T66 | AO69: Completed & Approved | AP69: Closed before june-2025 | AQ69: Closed before june-2025
A70: 68 | B70: T67 | C70: 472 | D70: NA | H70: DR | I70: Mahbubnagar-DR | J70: Network Readiness | M70: Colosed | AC70: DR | AD70: Closed | AM70: 45791 | AN70: \\172.28.9.34\Artefacts_T-Fiber TNOC Tracker\DR\Artifact for - T66 | AO70: Completed & Approved | AP70: Closed before june-2025 | AQ70: Closed before june-2025
A71: 69 | B71: T68 | C71: 472 | D71: NA | H71: DR | I71: Design & Documentation | J71: LLD: Approved conditionally with few punch points. Updated LLD to be submitted | M71: Open | P71: Working on additional points shared by Tfiber. | AC71: DR | AD71: OPEN | AO71: Open | AP71: Open | AQ71: Open
A72: 70 | B72: T69 | C72: 472 | D72: NA | H72: DR | I72: Design & Documentation | J72: HLD: Revised solution to submitted | M72: Open | P72: Working on additional points shared by Tfiber. | AC72: DR | AD72: OPEN | AO72: Open | AP72: Open | AQ72: Open
A73: 71 | B73: T70 | C73: 472 | D73: NA | H73: DR | I73: Design & Documentation | J73: DC-DR redunancy Test | M73: Colosed | AC73: DR | AD73: Closed | AM73: 45791 | AN73: \\172.28.9.34\share drive\Artefacts_T-Fiber TNOC Tracker\DR\Artifact for - T70 | AO73: Completed & Approved | AP73: Closed before june-2025 | AQ73: Closed before june-2025
A74: 72 | B74: T71 | C74: 472 | D74: NA | H74: DR | I74: MoM Action | J74: UTM Features (DR FW) | M74: Open | P74: Meeting scheduled with CTRL S to verify the UTM features 30-Oct-25: Duplicate to Point T71. DR does not have a public-facing application, and DR and DC firewalls are different | AC74: DR | AD74: Closed | AM74: 45962 | AN74: \\172.28.9.34\Artefacts_T-Fiber TNOC Tracker\NW-Security\T71_31-Oct-25.pdf | AO74: Completed & Approved | AP74: Closed After 14-Oct | AQ74: Open
A75: 73 | B75: T72 | C75: 472 | D75: NA | H75: DR | I75: MoM Action | J75: To configure LACP between L3 Switch and Core Router | M75: Open | P75: 11-Oct-25: CtrlS has to give proposal for procurement for addtional BoQ. IT infra SME need to Re-intiate a mail to get BoQ 22-Sep-25: The existing switch which was placed at DR by CtrlS doesnt have feature | Q75: on | R75: LACP | S75: Bun | T75: dling. Ct | U75: is planning | W75: to | X75: re | AA75: lpla | AB75: ce the exising switch with LACP supported switch. DC Infra admin need to provide tentative timelines for replacement. 08-Jul-2025 Sandeep will ensure on CTRL-S support and update by EoD 01-Jul-25 : Ticket (SR01301726) raised with CtrlS on 27-Jun, Config & testing to be carried out. This is additional task as per CtrlS and commercials may be involved. LnT Contracts team also talking to CtrlS account team to complete the task. 24-Dec-25 : SR01036770 opened with CtrlS for LACP configuration and it is not O&M activity as per CtrlS ops. team. escalated to LnT Contracts team for supoort. | AC75: DR | AD75: OPEN | AI75: rlS | AO75: Open | AP75: Open | AQ75: Open
A76: 74 | B76: T73 | C76: 472 | D76: NA | H76: DR | I76: MoM Action | J76: To configure LACP between Core Router and Firewall | M76: Open | P76: 11-Oct-25: CtrlS has to give proposal for procurement for addtional BoQ. IT infra SME need to Re-intiate a mail to get BoQ 22-Sep-25: The existing switch which was placed at DR by CtrlS doesnt have feature | Q76: on | R76: LACP | S76: Bun | T76: dling. Ct | U76: is planning | W76: to | X76: re | AA76: lpla | AB76: ce the exising switch with LACP supported switch. DC Infra admin need to provide tentative timelines for replacement. 01-Jul-25 : Ticket (SR01301726) raised with CtrlS on 27-Jun, Config & testing to be carried out. This is additional task as per CtrlS and commercials may be involved. LnT Contracts team also talking to CtrlS account team to complete the task. 24-Dec-25 : SR01036770 opened with CtrlS for LACP configuration and it is not O&M activity as per CtrlS ops. team. escalated to LnT Contracts team for supoort. | AC76: DR | AD76: OPEN | AI76: rlS | AO76: Open | AP76: Open | AQ76: Open
A77: 75 | B77: T74 | C77: 472 | D77: NA | H77: DR | I77: MoM Action | J77: To configure LACP between Firewall and L2 Switch | M77: Open | P77: 11-Oct-25: CtrlS has to give proposal for procurement for addtional BoQ. IT infra SME need to Re-intiate a mail to get BoQ 22-Sep-25: The existing switch which was placed at DR by CtrlS doesnt have feature | Q77: on | R77: LACP | S77: Bun | T77: dling. Ct | U77: is planning | W77: to | X77: re | AA77: lpla | AB77: ce the exising switch with LACP supported switch. DC Infra admin need to provide tentative timelines for replacement. 01-Jul-25 : Ticket (SR01301726) raised with CtrlS on 27-Jun, Config & testing to be carried out. This is additional task as per CtrlS and commercials may be involved. LnT Contracts team also talking to CtrlS account team to complete the task. 24-Dec-25 : SR01036770 opened with CtrlS for LACP configuration and it is not O&M activity as per CtrlS ops. team. escalated to LnT Contracts team for supoort. | AC77: DR | AD77: OPEN | AI77: rlS | AO77: Open | AP77: Open | AQ77: Open
A78: 76 | B78: T75 | C78: 472 | D78: NA | H78: DR | I78: MoM Action | J78: To confirm on backups for DR Virtual machines | M78: Colosed | AC78: DR | AD78: Closed | AM78: 45791 | AN78: \\172.28.9.34\share drive\Artefacts_T-Fiber TNOC Tracker\DR\Artifact for - T75 | AO78: Completed & Approved | AP78: Closed before june-2025 | AQ78: Closed before june-2025
A79: 77 | B79: T76 | C79: 472 | D79: NA | H79: DR | I79: MoM Action | J79: Backup storage to 25 TB | M79: Colosed | AC79: DR | AD79: Closed | AM79: 45791 | AN79: \\172.28.9.34\share drive\Artefacts_T-Fiber TNOC Tracker\DR\Artifact for - T76 | AO79: Completed & Approved | AP79: Closed before june-2025 | AQ79: Closed before june-2025
A80: 78 | B80: T77 | C80: 472 | D80: NA | H80: DR | I80: MoM Action | J80: To submit the SOPs for DC-DR switchover, DC-DR failover and failback | M80: Open | P80: Tejas, Nokia, GIS & Ciena MCP documnets are received. Remaining all Applications domains SOP's to be updated. | AC80: DR | AD80: OPEN | AO80: Open | AP80: Open | AQ80: Open
A81: 79 | B81: T78 | C81: 472 | D81: NA | H81: DR | I81: MoM Action | J81: to monitor the DR Servers | M81: Open | P81: DR servers monitoring through DR vCentre happening. DR is maintained by CtrlS team as per contract. Feasibility to be checked to integrated through OSS OBM. | AC81: DR | AD81: OPEN | AO81: Open | AP81: Open | AQ81: Open
A82: 80 | B82: T79 | C82: 472 | D82: NA | H82: DR | I82: MoM Action | J82: To confirm that DNS switchover between DC and DR locations should be automatic | M82: Colosed | AC82: DR | AD82: Closed | AM82: 45791 | AN82: \\172.28.9.34\Artefacts_T-Fiber TNOC Tracker\DR\Artifact for - T79 | AO82: Completed & Approved | AP82: Closed before june-2025 | AQ82: Closed before june-2025
A83: 81 | B83: T80 | C83: 472 | D83: NA | H83: DR | I83: MoM Action | J83: Mahubnagar as NTP | M83: Colosed | AC83: DR | AD83: Closed | AM83: 45782 | AN83: \\172.28.9.34\Artefacts_T-Fiber TNOC Tracker\IPMPLS\Primary NTP - T60,T61,T62.pdf \\172.28.9.34\Artefacts_T-Fiber TNOC Tracker\IPMPLS\Secondary NTP - T60,T61,T62.pdf | AO83: Completed & Approved | AP83: Closed before june-2025 | AQ83: Closed before june-2025
A84: 82 | B84: T81 | C84: 472 | D84: NA | H84: DR | I84: Configuration | J84: All application to be migrated to implement DR LB configuration | M84: Open | P84: 11-Oct-25: Approved DR HLD document to be shared with T Fiber for further discussion. Noikia app is integrated with DR LB . Balance application migration on DR LB is in Pipeline | AC84: DR | AD84: OPEN | AO84: Open | AP84: Open | AQ84: Open
A85: 83 | B85: T82 | C85: 472 | D85: NA | H85: DR | I85: MoM Action | J85: To confirm the applications which support Veem Replication for Reconfiguration | M85: Colosed | AC85: DR | AD85: Closed | AM85: 45791 | AN85: \\172.28.9.34\share drive\Artefacts_T-Fiber TNOC Tracker\DR\Artifact for - T82 | AO85: Completed & Approved | AP85: Closed before june-2025 | AQ85: Closed before june-2025
A86: 84 | B86: T83 | C86: 472 | D86: NA | H86: DWDM | I86: Network Deployment & integration | J86: Zonal Links Integration (12/15) | M86: Open | P86: 20-Sep-25: Nirmal, Jainoor, Gudihatnoor & Bhimni RFE pending due to forest permission 31-July-2025:As per discussion with Ramanaiah sir, need to discuss these points with T Fiber Project team for furthe | Q86: r a | R86: ction | S86: , ti | T86: ll that t | U86: this point | W86: kep | X86: t o | AA86: n ho | AB86: ld Depend on 04 Facilities RFE in Pkg-C Asifabad - Warangal & Karimnagar - Asifabad - Links integrated as per interim plan, actual integration pending Nizamabad - Asifabad - E2E link integration pending 28th-Apr'25: As per Sandeep Sanmani - Forest permission still pending 6/25/2025: Status is same no visibility on forest permission, Target date would be D+21 05-July-25: No progress on the forest permission | AC86: DWDM | AD86: OPEN | AI86: ime | AO86: Completed but Verification undrer Process | AP86: Completed but Verification undrer Process | AQ86: Completed but Verification undrer Process
A87: 85 | B87: T84 | C87: 472 | D87: NA | H87: DWDM | I87: Network Deployment & integration | J87: Nodes Live & Operational (67/71) | M87: Open | P87: 31-July-2025:As per discussion with Ramanaiah sir, need to discuss these points with T Fiber Project team for further action, till that time this point kept on hold Nirmal, Jainoor, Gudihatnoor & Bhimni RF | Q87: E p | R87: endin | S87: g du | T87: e to fore | U87: permission | W87: 28 | X87: th- | AA87: Apr' | AB87: 25: As per Sandeep Sanmani - Forest permission still pending 15-06-25: No progress on the permission, target - D+15 05-July-25: No progress on the forest permission | AC87: DWDM | AD87: OPEN | AI87: st | AO87: Completed but Verification undrer Process | AP87: Completed but Verification undrer Process | AQ87: Completed but Verification undrer Process
A88: 86 | B88: T85 | C88: 472 | D88: NA | H88: DWDM | I88: Network Deployment & integration | J88: Zonal Rings readiness with 1+R protection (5/7) | M88: Open | P88: 31-July-2025:As per discussion with Ramanaiah sir, need to discuss these points with T Fiber Project team for further action, till that time this point kept on hold 02 rings depend on 04 Facilities RFE re | Q88: adi | R88: ness | S88: in P | T88: kg-C, whi | U88: is pending d | W88: ue | X88: to | AA88: fore | AB88: st permission 28th-Apr'25: As per Sandeep Sanmani - Forest permission still pending 6/25/2025: No visibility on forest permission, target date would be D+30 05-July-25: No progress on the forest permission | AC88: DWDM | AD88: OPEN | AI88: ch | AO88: Completed but Verification undrer Process | AP88: Completed but Verification undrer Process | AQ88: Completed but Verification undrer Process
A89: 87 | B89: T86 | C89: 472 | D89: NA | H89: DWDM | I89: Network Deployment & AT Status | J89: Nodal AT (67/71) | M89: Open | P89: 31-July-2025:As per discussion with Ramanaiah sir, need to discuss these points with T Fiber Project team for further action, till that time this point kept on hold Nirmal, Jainoor, Gudihatnoor & Bhimni RF | Q89: E p | R89: endin | S89: g du | T89: e to fore | U89: permission | W89: 28 | X89: th- | AA89: Apr' | AB89: 25: As per Sandeep Sanmani - Forest permission still pending 15-06-25: No progress on the permission, target - D+15 05-July-25: No progress on the forest permission | AC89: DWDM | AD89: OPEN | AI89: st | AO89: Completed but Verification undrer Process | AP89: Completed but Verification undrer Process | AQ89: Completed but Verification undrer Process
A90: 88 | B90: T87 | C90: 472 | D90: NA | H90: DWDM | I90: Network Deployment & integration | J90: Mandal Ring Integration through OADM | M90: Open | P90: 31-July-2025:As per discussion with Ramanaiah sir, need to discuss these points with T Fiber Project team for further action, till that time this point kept on hold Mandal services are provisioned (10G) as | Q90: pe | R90: r int | S90: egra | T90: tion plan | U90: all package | W90: s 6 | X90: /25 | AA90: /202 | AB90: 5: 203 services provisioned out of 270 planned. Remaining can be provisioned as per the requirement | AC90: DWDM | AD90: OPEN | AI90: by | AO90: Completed but Verification undrer Process | AP90: Completed but Verification undrer Process | AQ90: Completed but Verification undrer Process
A91: 89 | B91: T88 | C91: 472 | D91: NA | H91: DWDM | I91: Network Deployment & AT Status | J91: Zonal Link AT (7/15) | M91: Open | P91: 31-July-2025:As per discussion with Ramanaiah sir, need to discuss these points with T Fiber Project team for further action, till that time this point kept on hold 04 Link AT's approved by T Fiber and 03 | Q91: Lin | R91: k AT' | S91: s pe | T91: nding due | U91: letter from | W91: Ci | X91: ena | AA91: awa | AB91: ited (No impact due to ILA to OADM upgradation) 05 Link AT pending due to high losses in the spans, depend on all packages 02 Links integrated as per interim plan, so not considered for Link AT 20May'25: Declaration letter submitted to T Fiber for 03 links AT approval 25-06-2025: Dependancy on field, no progress. 30-June-2025: As discussed in the meeting, need to arrange meeting with all stakeholders | AC91: DWDM | AD91: OPEN | AH91: 20-Sep-25: Mr.Suresh will update the status | AI91: to | AO91: Completed but Verification undrer Process | AP91: Completed but Verification undrer Process | AQ91: Completed but Verification undrer Process
A92: 90 | B92: T89 | C92: 472 | D92: NA | H92: DWDM | I92: Design & Documentation | J92: HLD (Revised) with OADM Solution | M92: Colosed | AC92: DWDM | AD92: Closed | AM92: 45783 | AN92: \\172.28.9.34\Artefacts_T-Fiber TNOC Tracker\DWDM\Artefact - T89 | AO92: Completed & Approved | AP92: Closed before june-2025 | AQ92: Closed before june-2025
A93: 91 | B93: T90 | C93: 472 | D93: NA | H93: DWDM | I93: Design & Documentation | J93: LLD (Revised) with OADM Solution (Ciena) | M93: Colosed | AC93: DWDM | AD93: Closed | AM93: 45783 | AN93: \\172.28.9.34\Artefacts_T-Fiber TNOC Tracker\DWDM\Artefact - T90 | AO93: Completed & Approved | AP93: Closed before june-2025 | AQ93: Closed before june-2025
A94: 92 | B94: T91 | C94: 472 | D94: NA | H94: DWDM | I94: Design & Documentation | J94: Nodal ATP | M94: Colosed | AC94: DWDM | AD94: Closed | AM94: 45783 | AN94: \\172.28.9.34\Artefacts_T-Fiber TNOC Tracker\DWDM\Artefact - T91 & T92 | AO94: Completed & Approved | AP94: Closed before june-2025 | AQ94: Closed before june-2025
A95: 93 | B95: T92 | C95: 472 | D95: NA | H95: DWDM | I95: Design & Documentation | J95: Link ATP | M95: Colosed | AC95: DWDM | AD95: Closed | AM95: 45783 | AN95: \\172.28.9.34\Artefacts_T-Fiber TNOC Tracker\DWDM\Artefact - T91 & T92 | AO95: Completed & Approved | AP95: Closed before june-2025 | AQ95: Closed before june-2025
A96: 94 | B96: T93 | C96: 472 | D96: NA | H96: DWDM | I96: Design & Documentation | J96: Ring ATP | M96: Colosed | AC96: DWDM | AD96: Closed | AM96: 45783 | AN96: \\172.28.9.34\Artefacts_T-Fiber TNOC Tracker\DWDM\Artefact - T93 | AO96: Completed & Approved | AP96: Closed before june-2025 | AQ96: Closed before june-2025
A97: 95 | B97: T94 | C97: 472 | D97: NA | H97: DWDM | I97: Design & Documentation | J97: DWDM EMS (MCP) Functional ATP | M97: Open | P97: 20-Sep-25: MCP FAT document submitted to TPA on XX-XX-XXXX. Meeting need to be scheduled on 22-Sep-25 with TPA to get the clarifications on delay. 13-Sep-25: Response awaited from TPA team 29-August-2025: | Q97: Sp | R97: oken | S97: with | T97: Mr. Bijj | U97: response awa | W97: ite | X97: d 2 | AA97: 6-Ju | AB97: ly-25: FAT document approval pending 08-July-2025: 1. MCP FAT document prepared as per RFP requirements and TPA remarks 2. 100G traffic throughput will be shown during Ring ATP 07-July-2025: 1. SME not aware of MCP FAT Check list, but prepared FAT document and sent to TPA for validation 05-July-2025: Submitted AT document to T Fiber TPA 30-June-2025: target to submit by 2nd July'25, based on OEM reply Revised version to be submitted as per T Fiber remarks on 29th Apr'25 | AC97: DWDM | AD97: OPEN | AH97: Pending from TPA | AI97: u, | AO97: Completed but Verification undrer Process | AP97: Completed but Verification undrer Process | AQ97: Completed but Verification undrer Process
A98: 96 | B98: T95 | C98: 472 | D98: NA | H98: DWDM | I98: Integration with OSS | J98: DWDM Network Alarms Integration | M98: Colosed | AC98: DWDM | AD98: Closed | AM98: 45783 | AN98: \\172.28.9.34\Artefacts_T-Fiber TNOC Tracker\DWDM\Artefact - T95 | AO98: Completed & Approved | AP98: Closed before june-2025 | AQ98: Closed before june-2025
A99: 97 | B99: T96 | C99: 472 | D99: NA | H99: DWDM | I99: Integration with OSS | J99: Hardware Inventory Integration in HPE OSS | M99: Colosed | AC99: DWDM | AD99: Closed | AM99: 45783 | AN99: \\172.28.9.34\Artefacts_T-Fiber TNOC Tracker\DWDM\Artefact - T96 | AO99: Completed & Approved | AP99: Closed before june-2025 | AQ99: Closed before june-2025
A100: 98 | B100: T97 | C100: 472 | D100: NA | H100: DWDM | I100: Integration with OSS | J100: DWDM Network Topology | M100: Open | P100: 11-Nov-25: 26-July-2025: HPE conveyed that Topology border unable to make bold or hilight 12-July-2025: Update awaited from HPE 07-July-2025: Topology is visible but border is not highlighted. HP checking | Q100: fo | R100: r the | S100: pos | T100: sibility | U100: impose of bo | W100: rde | X100: r m | AA100: ap o | AB100: n topology. Required 02 weeks post confirmation 05-July-2025: In discussion with HPE, required 02 weeks post confirmation, 21st July 30-June-2025: As discussed with Suresh P checking with HPE. Tentative date: 16th July. As discussed in the meeting, call to be arranged along with OSS SME and HP team | AC100: DWDM | AD100: OPEN | AI100: to | AO100: Completed but Verification undrer Process | AP100: Completed but Verification undrer Process | AQ100: Completed but Verification undrer Process
A101: 99 | B101: T98 | C101: 472 | D101: NA | H101: DWDM | I101: Integration with OSS | J101: Auto Ticket & RCA for Fiber Cuts | M101: Colosed | AC101: DWDM | AD101: Closed | AM101: 45783 | AN101: \\172.28.9.34\Artefacts_T-Fiber TNOC Tracker\DWDM\Artefact - T98 | AO101: Completed & Approved | AP101: Closed before june-2025 | AQ101: Closed before june-2025
...

Sheet LLD
A1: LLD Action Points | B1: NSO Status | C1: NSO Comments(10/03/2026) | D1: Review TNOC (09/03/2026) Comments | E1: Owner | F1: Status
A2: 1. TCell P2p (P2Mp covered TCELL p2p product to be included). | B2: Completed | C2: Configuration can be added if available | D2: Use test lab for configuration on 2 routers (MAG,GAC) | E2: Mahesh & Jyothi | F2: Done
A3: 2. GI ILL (configuration concept available but not covered as product Automation list). | B3: Completed | E3: Mahesh & Jyothi | F3: Done
A4: ` | B4: Inprogress | D4: Sayyad:Alternate solution work is in progress suggested by Tfiber(In 3 days will complete this) | E4: Mahesh & Jyothi | F4: Hold From Sayyad
A5: 4. ONT Bridge Mode (DHCP to check). | B5: Inprogress | D5: Sayyad:when ONT in bridge mode DHCP will not be released by ONT, | E5: Mahesh & Jyothi | F5: Hold From Sayyad
A6: 5. DWDM/OTN product not covered (Low level to Include). | B6: Completed | C6: Refer document sent by ritik | D6: CIENA testing not possible only information can be provided because we dont have ciena on test lab for OADM and OTN | E6: Mahesh & Jyothi | F6: Done
A7: 6. Re-Try and provision mechanism parameter to check , number of retries. | B7: How many times can we re-provision | C7: NSO Team | D7: NSO Team 8/5/2026 : read nso document | E7: Mahesh & Jyothi | F7: Hold NSO
A8: 7. RFS to be discussed ( Node reachability vs TFiber OWN Connectivity). | B8: Need Clarity | C8: NSO Team | D8: NSO 8/5/2026 : read nso document Initially Tfiber has given the matrics for RFS however it will be taken care in the feasibility. | E8: Mahesh & Jyothi | F8: Hold NSO
A9: 8. Zone also can be included for service delivery. | B9: Need Clarity | C9: As of now No Service Delivery in Zone | D9: As of now No at present no service has been provided from zonal(ZCR) however POC can be performed and demonstrated. | E9: Mahesh & Jyothi
A10: 9. Additionally Second configuration of PON port not working to be resolved while already existing customer is in use, We cant go live without this option. This was working when Cisco has done the Demo now its not working. | B10: Completed | D10: already done each olt port has 64 connectivities, with splitter given access to customers. | E10: Mahesh & Jyothi | F10: Jayant sir
A11: 10. ONT LAN Ports unshut while configuration done based on number of services & requirement. | B11: Completed | C11: Refer document sent by Sayyad | D11: Sayyad:It is a part of existing service provision api's | E11: Mahesh & Jyothi | F11: Done
A12: 11. NSO Vlan asignment models. | B12: Completed | C12: Ok | D12: Ok | E12: Mahesh & Jyothi | F12: Done
A13: 12. IP Pool asignment models. | B13: Completed | C13: Check GI-BB & TDIA | D13: GI-BB & TDIA | E13: Mahesh & Jyothi | F13: Done
A14: 13. IPv6 provisioning for GI delivery to include. | B14: Completed | C14: Provide service delivery IP not the network.Once IPV6 is tested come and discuss with govind sir | D14: Provide service delivery IP not the network.Once IPV6 is tested come and discuss with govind sir | E14: Mahesh & Jyothi | F14: Done
A15: 14. Traffic priority for Qos in GPON not covered. | B15: Completed | C15: QoS Profile OLT OR ONT DONE | E15: Mahesh & Jyothi | F15: Done
D21: NOTE: Configuration for all Points : Either NSO or Network
D22: In Entire documentation there is no configuration.

Sheet Sheet3
C5: Total Open Points | D5: Closure Review Pending | E5: Duplicate | F5: Not Feasible | G5: WIP
C6: 63 | D6: 23 | E6: 6 | F6: 4 | G6: 30

Sheet 472 Deailed Sheet
B2: Slno | C2: UniqueID | D2: Category | E2: Meeting Date | F2: Priority | G2: Ramana | H2: Ramana-Domain | I2: Domain | J2: Sub-Domain | K2: Action Point | L2: Impact | M2: Priority | N2: Baseline Status | O2: xx | P2: Application | Q2: Module | R2: Remarks | S2: Remarks | T2: Organization | U2: Owner | V2: Owner(L&T) | W2: Target Date to Complete | X2: Open | Y2: Revised Status (L&T) As on 18-Sep-2025 | Z2: Approved BY (TF) | AA2: Approval Date(TF) | AB2: Link of evidences | AC2: R | AD2: S | AE2: T | AF2: U | AG2: V | AH2: W | AI2: X | AJ2: Tfiber-Cat | AK2: Derived Status (L&T) | AL2: OSS | AM2: OSS Remarks | AN2: Ramana Remarks as on 19-Sep-2025 | AO2: T Fiber Appoved Date | AP2: Artefacts | AQ2: Target Date | AR2: Qty | AS2: Ramana-Remarks | AT2: Updated on 13-Oct-2025
B3: 1 | C3: T1 | D3: 472 | E3: NA | I3: Security & Regulatory Compliance | J3: Configuration | K3: Integration testing of All supported devices is complete and adding all the devices is underway. | N3: Open | S3: what ever request has come all are integrated with ISE , any new device request comes same will be added . Also Aleppo PO get relaesed for ADintegration , it will also get integrated with AD. | V3: Sarmendra | X3: Open | Y3: DEPENDENCY(Client/Ext.) | AI3: 472Security & Regulatory Compliance | AJ3: Security | AK3: OPEN | AR3: 1 | AS3: Open | AT3: Open
B4: 2 | C4: T2 | D4: 472 | E4: NA | I4: DWDM | J4: Integration with Alepo | K4: RADIUS Configuration Testing on Ciena Node & EMS (MCP) | N4: Colosed | V4: Suresh Kumar | Y4: COMPLETED & APPROVED | Z4: AD-UT-Tfiber | AA4: 45783 | AB4: \\172.28.9.34\Artefacts_T-Fiber TNOC Tracker\DWDM\Artefact - T106 | AI4: 472DWDM | AJ4: DWDM | AK4: CLOSED | AO4: 45783 | AP4: \\172.28.9.34\Artefacts_T-Fiber TNOC Tracker\DWDM\Artefact - T106 | AR4: 1 | AS4: Completed & Approved | AT4: Closed before june-2025
B5: 3 | C5: T3 | D5: 472 | E5: NA | I5: Security & Regulatory Compliance | J5: Integration | K5: Accouting data from Ciena MCP and field nodes to be captured in Alepo AAA | M5: Critical | N5: Open | S5: MCP upgradation is in pipeline . same will be completed by 25 Sep 2025 | V5: Sarmendra | X5: Open | Y5: WIP | AI5: 472Security & Regulatory Compliance | AJ5: Security | AK5: OPEN | AR5: 1 | AS5: Open | AT5: Open
B6: 4 | C6: T3 | D6: 472 | E6: NA | I6: DWDM | J6: Integration with Alepo | K6: TACACS+/Radius testing for AAA on ciena node | N6: Open | S6: 20-09-2025: 8.1 MCP software Patch upgradation will be completed by 27-Sep-25, After completetion of upgrdation AAA functionalities will be tested for ciena devices by using radius 13-09-25:MCP upgradation is in progress, will be able to check the logs by next week 28-08-2025: Activity is in progress, target to complete by 25th Sep'25 Authentication and Authorization tested and found OK for Node and MCP. 19-08-2025: Due to issue in disk partition and file type of storage, activity is not started 10-08-2025: OEM confirmation recieved and activity is planned from 18th August'25. 05-July-2025: DC OSS to DR MCP communication is through now, need to integrate and test before activity 12-July-2025: DC OSS to DR MCP integration testing done. Alarms and Autoticketing functioning as expected. Upgradation activity will be scheduled as per OEM confirmation, Target date - 30-07-25 26-July-2025: Schedule awaited from OEM 30-June-2025: DC OSS to DR MCP connectivity to be extended for PE approval, WIP. Target date - 30-07-25 15-06-25: Targeting to close the upgradation by month end, 30-06-25 30-05-2025: Accounting issue resolved in latest MCP version, verified in 8.2 Ver (Node logs are now capturing in MCP). Upgradation schedule awaited from Teleindia for our MCP from 7.1-P02 5/21/2025: Correlation to identified to find the user logged in at the specific time 28APR'25: As discussed with Sanjay sir, if user id not avaialble pls. try for correlation with IP. Some how Correlation to be done. In Accounting, Node and MCP logs are successfully reporting in Alepo with below limitation. Node Logs - Active profile name (ADMIN/RADIUS) is displayed against User ID (Ciena confirmed it is as per design no changes are possible) | T6: L&T | V6: Suresh Kumar | X6: Open | Y6: WIP | AI6: 472DWDM | AJ6: DWDM | AK6: OPEN | AR6: 1 | AS6: Open | AT6: Open
B7: 5 | C7: T4 | D7: 472 | E7: NA | I7: Security & Regulatory Compliance | J7: Security | K7: Alepo confirmed that Alepo AAA supports TACACS, Alepo to test Nokia and Ciena nodes integration on TACACS , with supporting artefacts of testing. 1.TACACS Testing with Tejas, Nokia, Ciena 2. Alepo Testing with Tejas, Nokia and Ciena | N7: Open | S7: 1.TACACS Testing with Tejas, Nokia, Ciena completed 2. Alepo Testing with Tejas, Nokia and Ciena | V7: Sarmendra | Y7: CLOSURE REVIEW PENDING | AI7: 472Security & Regulatory Compliance | AJ7: Security | AK7: OPEN | AP7: Artefacts to be Submitted | AR7: 1 | AS7: Completed but Verification undrer Process | AT7: Completed but Verification undrer Process
B8: 6 | C8: T5 | D8: 472 | E8: NA | I8: Security & Regulatory Compliance | J8: Functional AT | K8: Had a meeting with Ashwani from Alepo and sent him updated test cases. He is working on data gathering and will send us back by Tuesday. | N8: Open | S8: FAT were submitted to customer, Customer observation in being work out. Target to resubmission.- 23.07.25 | V8: Sarmendra | Y8: CLOSURE REVIEW PENDING | AI8: 472Security & Regulatory Compliance | AJ8: Security | AK8: OPEN | AP8: Artefacts to be Submitted | AR8: 1 | AS8: Completed but Verification undrer Process | AT8: Completed but Verification undrer Process
B9: 7 | C9: T6 | D9: 472 | E9: NA | I9: BSS | J9: Installation | K9: Installation of BSS Application | N9: Open | S9: 29-08-2025: Design and Solution document to be shared with GM NOC and Physical instllation of BSS need to validate according to solution from L&T Side before submitting for for review with T Fiber 26-06-2025: We have offered Installation AT. TFIBER has asked DC architecture review including license validity | V9: Manoj Nibrad | X9: Open | Y9: Open | AI9: 472BSS | AJ9: Applications/Tools | AK9: OPEN | AR9: 1 | AS9: Open | AT9: Open
B10: 8 | C10: T7 | D10: 472 | E10: NA | I10: BSS | J10: Integration | K10: Initial Integration with Third Party Applications (OSS & NSO) | N10: Open | S10: 26-06-2025: OSS Integration is done. NSO integration is pending. Awaiting NSO Team. | V10: Manoj Nibrad | X10: Open | Y10: Open | AI10: 472BSS | AJ10: Applications/Tools | AK10: OPEN | AR10: 1 | AS10: Open | AT10: Open
B11: 9 | C11: T8 | D11: 472 | E11: NA | I11: BSS | J11: Integration | K11: OSS interfaces | N11: Open | S11: 26-06-2025: Feasibility API & Ticket API integration is completed. | V11: Manoj Nibrad | X11: Open | Y11: Open | AI11: 472BSS | AJ11: Applications/Tools | AK11: OPEN | AR11: 1 | AS11: Open | AT11: Open
B12: 10 | C12: T9 | D12: 472 | E12: NA | I12: BSS | J12: Integration | K12: NSO interfaces | N12: Open | S12: 26-06-2025: Awaiting NSO Team | V12: Manoj Nibrad | X12: Open | Y12: Open | AI12: 472BSS | AJ12: Applications/Tools | AK12: OPEN | AR12: 1 | AS12: Open | AT12: Open
B13: 11 | C13: T10 | D13: 472 | E13: NA | I13: BSS | J13: Integration | K13: GeM Portal | N13: Open | V13: Manoj Nibrad | X13: Open | Y13: Open | Z13: On-Hold confirmation mail received from NOC Director | AA13: 45854 | AB13: \\172.28.9.34\share drive\Artefacts_T-Fiber TNOC Tracker\BSS\Artifact_T10 | AI13: 472BSS | AJ13: Applications/Tools | AK13: CLOSED | AO13: 45854 | AP13: \\172.28.9.34\share drive\Artefacts_T-Fiber TNOC Tracker\BSS\Artifact_T10 | AR13: 1 | AS13: Open | AT13: Open
B14: 12 | C14: T11 | D14: 472 | E14: NA | I14: BSS | J14: Development and unit testing | K14: Import Sub-Departments, Import Leads, Campaign Management, Opportunity/Quote/order Management, order booking and Service Order workflow for tested services | N14: Open | S14: 29-08-2025: All points are completed Import Sub-Departments, Import Leads, Opportunity/Quote/order Management, order booking and Service Order workflow for tested services Demo to be conducted to TFIBER. "Campaign Management" is Pending where inputs are required from TFIBER Business team 26-06-2025: Awaiting few inputs from TFIBER | V14: Manoj Nibrad | X14: Open | Y14: Open | AI14: 472BSS | AJ14: Applications/Tools | AK14: OPEN | AR14: 1 | AS14: Open | AT14: Open
B15: 13 | C15: T12 | D15: 472 | E15: NA | I15: BSS | J15: Development and unit testing | K15: Product/Service Catalogue integration | N15: Open | S15: 29-08-2025: Feature is available to admin User(Product Team) to configure new product based on requirement. BSS Team will provide Demo to the TFIBER (business team([Uday]/Solution Team[Sanjay]) for their acceptance. 26-06-2025: Artifacts submitted. Closure review is pending with TFIBER | V15: Manoj Nibrad | X15: Open | Y15: Open | AI15: 472BSS | AJ15: Applications/Tools | AK15: OPEN | AR15: 1 | AS15: Open | AT15: Open
B16: 14 | C16: T13 | D16: 472 | E16: NA | I16: BSS | J16: Development and unit testing | K16: Billing, Discounts & Adjustments, Invoice generation, Bill Formatting | N16: Open | S16: 29-08-2025: Feature is made available in the BSS application, BSS Team will provide demo to TFIBER Team (Business [Uday] & Finance[Bhaskar]) 26-06-2025: Artifacts submitted. Closure review is pending with TFIBER | V16: Manoj Nibrad | X16: Open | Y16: Open | AI16: 472BSS | AJ16: Applications/Tools | AK16: OPEN | AR16: 1 | AS16: Open | AT16: Open
B17: 15 | C17: T14 | D17: 472 | E17: NA | I17: BSS | J17: Development and unit testing | K17: Feasibility API response from OSS for service provisioning request | N17: Open | S17: 29-08-2025: Feaibility API is already integrated with BSS and demonstrated in GIBB demo and it is applicable for all products. 26-06-2025: Artifacts submitted. Closure review is pending with TFIBER | V17: Manoj Nibrad | X17: Open | Y17: Open | AI17: 472BSS | AJ17: Applications/Tools | AK17: OPEN | AR17: 1 | AS17: Open | AT17: Open
B18: 16 | C18: T15 | D18: 472 | E18: NA | I18: BSS | J18: Development and unit testing | K18: SMS notification, email gateway, Field engineer mobile app readiness | N18: Open | S18: 29-08-2025: Integration is already completed and applicable for all product same has demonstrated to TFIBER during GIBB demo session. 26-06-2025: Artifacts submitted. Closure review is pending with TFIBER | V18: Manoj Nibrad | X18: Open | Y18: Open | AI18: 472BSS | AJ18: Applications/Tools | AK18: OPEN | AR18: 1 | AS18: Open | AT18: Open
B19: 17 | C19: T16 | D19: 472 | E19: NA | I19: BSS | J19: Development and unit testing | K19: Service Assurance and trouble tickets | N19: Open | S19: 29-08-2025: Integration with Service Manager is done for technical ticket and BSS have functionality to handle the non-technical ticket in BSS itself. BSS team will demonstrate this functionality to TFIBER. Sanjay Sir needs to confirm demo date. 26-06-2025: Artifacts submitted. Closure review is pending with TFIBER | V19: Manoj Nibrad | X19: Open | Y19: Open | AI19: 472BSS | AJ19: Applications/Tools | AK19: OPEN | AR19: 1 | AS19: Open | AT19: Open
B20: 18 | C20: T17 | D20: 472 | E20: NA | I20: BSS | J20: Development and unit testing | K20: Customer Self care portal development for T-CELL, T-NET, L0 | N20: Open | S20: 29-08-2025: Webportal is available. BSS team needs to demonstrate to TFIBER team. Sanjay Sir needs to confirm demo date. 26-06-2025: Artifacts submitted. Closure review is pending with TFIBER | V20: Manoj Nibrad | X20: Open | Y20: Open | AI20: 472BSS | AJ20: Applications/Tools | AK20: OPEN | AR20: 1 | AS20: Open | AT20: Open
B21: 19 | C21: T18 | D21: 472 | E21: NA | I21: BSS | J21: Integration | K21: Integration modules Like on board Un-Assist & dependent module to be completed for all products from system to be initiated a workshop and to be closed in next 2 Weeks | N21: Open | S21: 29-08-2025: Seek input from Business team (Uday) and deploy post assisted completion. 26-06-2025: Input awaited from TFIBER | V21: Manoj Nibrad | X21: Open | Y21: Open | AI21: 472BSS | AJ21: Applications/Tools | AK21: OPEN | AR21: 1 | AS21: Open | AT21: Open
B22: 20 | C22: T19 | D22: 472 | E22: NA | I22: BSS | J22: MoM Action | K22: T-Cell service definition for workflow implementation in BSS for creating Spoke primary and secondary | N22: Open | S22: 29-08-2025:Update product concept note similar to GIBB and share with TFIBER for review 26-06-2025: We can deliver this post getting product concept note from TFIBER | V22: Manoj Nibrad | X22: Open | Y22: Open | AI22: 472BSS | AJ22: Applications/Tools | AK22: OPEN | AR22: 1 | AS22: Open | AT22: Open
B23: 21 | C23: T20 | D23: 472 | E23: NA | I23: BSS | J23: Development and unit testing | K23: Rules for primary and secondary spoke implementation in BSS- - GP with shortest distance will be primary - To display dropdown and concerned user group to select and confirm | N23: Open | S23: #N/A | V23: Manoj Nibrad | X23: Open | Y23: Open | AI23: 472BSS | AJ23: Applications/Tools | AK23: OPEN | AP23: #N/A | AR23: 1 | AS23: Open | AT23: Open
B24: 22 | C24: T21 | D24: 472 | E24: NA | I24: BSS | J24: MoM Action | K24: BSS firewall ports required for Security compliance | N24: Open | S24: BSS has to forward list of Port as per deiffrent modules of application | V24: Sarmendra | X24: Open | Y24: WIP | AI24: 472BSS | AJ24: Applications/Tools | AK24: OPEN | AR24: 1 | AS24: Open | AT24: Open
B25: 23 | C25: T22 | D25: 472 | E25: NA | I25: BSS | J25: Security | K25: Roadmap for password policy implementation in CSP | N25: Open | S25: Ciriteria for Paswword policy hase been Shared wioth BSS team . BSS team has to implement and submit report for verifications. | V25: Sarmendra | X25: Open | Y25: WIP | AI25: 472BSS | AJ25: Applications/Tools | AK25: OPEN | AR25: 1 | AS25: Open | AT25: Open
B26: 24 | C26: T23 | D26: 472 | E26: NA | I26: BSS | J26: Security | K26: DMZ requirements for CSP | N26: Open | S26: IP amd URL required by BSS foir NAT through DMZ has been Completed | V26: Sarmendra | X26: Open | Y26: WIP | AI26: 472BSS | AJ26: Applications/Tools | AK26: OPEN | AR26: 1 | AS26: Open | AT26: Open
B27: 25 | C27: T24 | D27: 472 | E27: NA | I27: BSS | J27: MoM Action | K27: PoP location confirmation usergroup for connectivity to O&M | N27: Open | S27: 29-08-2025: Seek input from O&M team (Umesh) 26-06-2025: Input awaited from TFIBER | V27: Manoj Nibrad | X27: Open | Y27: Open | AI27: 472BSS | AJ27: Applications/Tools | AK27: OPEN | AR27: 1 | AS27: Open | AT27: Open
B28: 26 | C28: T25 | D28: 472 | E28: NA | I28: BSS | J28: MoM Action | K28: Product concept note configuration in BSS queries to be shared | N28: Open | S28: 29-08-2025: Queries to be prepared and share with TFIBER for discussion. 17-07-2025: Business Team of TFIBER needs to finalize and confirm all product. 26-06-2025: Need Product concept note from TFIBER | V28: Manoj Nibrad | X28: Open | Y28: Open | AI28: 472BSS | AJ28: Applications/Tools | AK28: OPEN | AR28: 1 | AS28: Open | AT28: Open
B29: 27 | C29: T26 | D29: 472 | E29: NA | I29: BSS | J29: MoM Action | K29: Location id logic for NSO provisioning | N29: Open | S29: 29-08-2025: Ciruit ID logic PPT shared by Sivakumar, needs to use and implement in BSS. 26-06-2025: Timeline 30th July is considering NSO support is available in 2-3 days | V29: Manoj Nibrad | X29: Open | Y29: Open | AI29: 472BSS | AJ29: Applications/Tools | AK29: OPEN | AR29: 1 | AS29: Open | AT29: Open
B30: 28 | C30: T27 | D30: 472 | E30: NA | I30: BSS | J30: Integration | K30: Tariff plan parameters viz. 5G, 4G finalisation. (BSS should capture QOS parameter & Requirements) | N30: Open | S30: 29-08-2025: Product Can be configured in BSS product catalogue Demo to be given to TFIBER 26-06-2025: Input awaited from TFIBER | V30: Manoj Nibrad | X30: Open | Y30: Open | AI30: 472BSS | AJ30: Applications/Tools | AK30: OPEN | AR30: 1 | AS30: Open | AT30: Open
B31: 29 | C31: T28 | D31: 472 | E31: NA | I31: IP/MPLS | J31: Functional AT | K31: Internal AT 83% complete. Waiting Cisco to update data sent by Vikram and then we will submit to TPA ( for pending cases, we just need a maintanence window to test as it is impacting activity) This is for ISE | N31: Open | S31: FAT documents were submitted to TPA , However it has some common observation which will be discussed with TPA team by Mr Sharma. Subsequently , correction will be made in FAT doc | V31: Sarmendra | X31: Open | Y31: WIP | AI31: 472IP/MPLS | AJ31: IPMPLS | AK31: OPEN | AR31: 1 | AS31: Open | AT31: Open
B32: 30 | C32: T29 | D32: 472 | E32: NA | I32: IP/MPLS | J32: Functional AT | K32: CSM is having memory issues. Need to sort it out before we do AT. Working on settling that with Cisco. Memory will be allocated and tested in the first week of July | N32: Open | S32: CSM has been replaced by ASDM | V32: Sarmendra | X32: Open | Y32: WIP | AI32: 472IP/MPLS | AJ32: IPMPLS | AK32: OPEN | AR32: 1 | AS32: Open | AT32: Open
B33: 31 | C33: T30 | D33: 472 | E33: NA | I33: IP/MPLS | J33: Functional AT | K33: Internal AT 72% complete. Waiting on Cisco to update data sent by Vikram and then we will submit to TPA. ( for pending cases, we just need a maintanence window to test as it is impacting activity) | N33: Open | S33: FAT documents were submitted to TPA , However it has some common observation which will be discussed with TPA team by Mr Sharma. Subsequently , correction will be made in FAT doc | V33: Sarmendra | X33: Open | Y33: WIP | AI33: 472IP/MPLS | AJ33: IPMPLS | AK33: OPEN | AR33: 1 | AS33: Open | AT33: Open
B34: 32 | C34: T31 | D34: 472 | E34: NA | I34: Security & Regulatory Compliance | J34: Security | K34: Internal Audit for all applications | N34: Open | S34: Application audited partally , howver PT audit couldnot be done due to lack of necessary tools. Same has been requested with LTTS team , but it could not be materialised. | V34: Sarmendra | X34: Open | Y34: WIP | AI34: 472Security & Regulatory Compliance | AJ34: Security | AK34: OPEN | AR34: 1 | AS34: Open | AT34: Open
B35: 33 | C35: T32 | D35: 472 | E35: NA | I35: Security & Regulatory Compliance | J35: Security | K35: Internal audit for network elements | N35: Open | S35: Network elemants auditted including NOC end points , However PT for same is pending. | V35: Sarmendra | X35: Open | Y35: WIP | AI35: 472Security & Regulatory Compliance | AJ35: Security | AK35: OPEN | AR35: 1 | AS35: Open | AT35: Open
... B38: 36 | C38: T35 | D38: 472 | E38: NA | I38: IP/MPLS | J38: Security | K38: external audit for network elements(Tfiber will be arranging a partner for third party audit) | N38: Open | S38: Awaited TSTG Audit party to engage | V38: Sarmendra | X38: Open | Y38: DEPENDENCY(Client/Ext.) | AI38: 472IP/MPLS | AJ38: IPMPLS | AK38: OPEN | AR38: 1 | AS38: Open | AT38: Open
B39: 37 | C39: T36 | D39: 472 | E39: NA | I39: Security & Regulatory Compliance | J39: Security | K39: Physical user access | N39: Open | S39: Has completed , Artefacts will be resubmitted. | V39: Sarmendra | X39: Open | Y39: REOPENED | AB39: \\172.28.9.34\Artefacts_T-Fiber TNOC Tracker\NW-Security\T36 | AI39: 472Security & Regulatory Compliance | AJ39: Security | AK39: OPEN | AP39: \\172.28.9.34\Artefacts_T-Fiber TNOC Tracker\NW-Security\T36 | AR39: 1 | AS39: Open | AT39: Open
B40: 38 | C40: T37 | D40: 472 | E40: NA | I40: Security & Regulatory Compliance | J40: Security | K40: Virtual user access-VPN | N40: Open | S40: Has completed , Artefacts will be resubmitted. | V40: Sarmendra | X40: Open | Y40: REOPENED | AI40: 472Security & Regulatory Compliance | AJ40: Security | AK40: OPEN | AR40: 1 | AS40: Open | AT40: Open
B41: 39 | C41: T38 | D41: 472 | E41: NA | I41: Security & Regulatory Compliance | J41: Security | K41: Role based severity access | N41: Open | S41: Completed and Review pending. Artfacts submitted | V41: Sarmendra | X41: Open | Y41: WIP | AI41: 472Security & Regulatory Compliance | AJ41: Security | AK41: OPEN | AR41: 1 | AS41: Open | AT41: Open
B42: 40 | C42: T39 | D42: 472 | E42: NA | I42: Security & Regulatory Compliance | J42: Security | K42: ISE integration with Cisco elements | N42: Open | S42: Artefacts will be submitted. | V42: Sarmendra | Y42: CLOSURE REVIEW PENDING | AI42: 472Security & Regulatory Compliance | AJ42: Security | AK42: OPEN | AP42: Artefacts to be Submitted | AR42: 1 | AS42: Completed but Verification undrer Process | AT42: Completed but Verification undrer Process
B43: 41 | C43: T40 | D43: 472 | E43: NA | I43: Security & Regulatory Compliance | J43: Regulatory | K43: Regulatory Compliance with respect DoT policies 1. Security Policy-Complied 2. Security Architecture of Telecom Network-Complied 3. Information Security Risk Assessment and Risk Treatment processes and their implementation plan-WIP, Target: Dec 2024 reviewed with customer. 4. Recruitment processes and employee's record-WIP, Target:12-10-2025 5. Controls for effectiveness of security management-WIP, Target: 28 -02-2025 6. Evidence of monitoring, measurement results and management reviews of security management-WIP, Target: 28-02-2025 7. Security Audit programs and audit results-Complied 8. Inventory management and classification of information assets and their handling Completed 9. Procedure for responding to information and network security incidents-WIP, Target: 28-02-2025 - SIRT reviewed 10. Main S/W updation and changes-WIP, Target: 28-02-2025 11. Supply chain of products (HW/SW). To be taken from manufacturer/supplier-Communicated to Sekhar. WIP, Target: 14-02-2025 12. SW details and documentation obtained from manufacturers/supplier-Communicated to Sekhar WIP, Target: 14-02-2025 13. O&M procedures in the form of manual-O&M manual and OEM wise manuals WIP, Target: 14-02-2025 14. Processes for internal and external communication relevant to the security management-WIP, Target: 07-3-2025 | N43: Open | S43: Confirmation of purchase of ISE. License needed to upgrade for HA | V43: Sarmendra | X43: Open | Y43: DEPENDENCY(Client/Ext.) | AI43: 472Security & Regulatory Compliance | AJ43: Security | AK43: OPEN | AP43: #VALUE! | AR43: 1 | AS43: Open | AT43: Open
B44: 42 | C44: T41 | D44: 472 | E44: NA | I44: DC-IT | J44: Servers and Strorage (Deployment and Installations) | K44: 1. Compute & Storage | N44: Open | S44: 11-Oct-25: As per the OEM's/SME's request, storage is allocated as per requirements. Artifacts are Captured. OEM Confirmation Emails to be captured as a Reference. | V44: Ravi Kishore | X44: Open | Y44: REOPENED | AB44: \\172.28.9.34\share drive\Artefacts_T-Fiber TNOC Tracker\DC IT-Infra\Artifact for - T41 | AI44: 472DC-IT | AJ44: Network | AK44: OPEN | AR44: 1 | AS44: Open | AT44: Open
B45: 43 | C45: T42 | D45: 472 | E45: NA | I45: DC-IT | J45: Servers and Strorage (Deployment and Installations) | K45: 2. Virtulization | N45: Colosed | V45: Ravi Kishore | Y45: COMPLETED & APPROVED | Z45: AD-UT-Tfiber | AA45: 45791 | AB45: \\172.28.9.34\share drive\Artefacts_T-Fiber TNOC Tracker\DC IT-Infra\Artifact for -T42 | AI45: 472DC-IT | AJ45: Network | AK45: CLOSED | AO45: 45791 | AP45: \\172.28.9.34\share drive\Artefacts_T-Fiber TNOC Tracker\DC IT-Infra\Artifact for -T42 | AR45: 1 | AS45: Completed & Approved | AT45: Closed before june-2025
B46: 44 | C46: T43 | D46: 472 | E46: NA | I46: DC-IT | J46: Servers and Strorage (Deployment and Installations) | K46: 3. Anti-virus | N46: Colosed | V46: Ravi Kishore | Y46: COMPLETED & APPROVED | Z46: AD-UT-Tfiber | AA46: 45791 | AB46: \\172.28.9.34\share drive\Artefacts_T-Fiber TNOC Tracker\DC IT-Infra\Artifact for -T43 | AI46: 472DC-IT | AJ46: Network | AK46: CLOSED | AO46: 45791 | AP46: \\172.28.9.34\share drive\Artefacts_T-Fiber TNOC Tracker\DC IT-Infra\Artifact for -T43 | AR46: 1 | AS46: Completed & Approved | AT46: Closed before june-2025
B47: 45 | C47: T44 | D47: 472 | E47: NA | I47: DC-IT | J47: Servers and Strorage (Deployment and Installations) | K47: 4. VM's Deployment Application Installations | N47: Colosed | V47: Ravi Kishore | Y47: COMPLETED & APPROVED | Z47: AD-UT-Tfiber | AA47: 45791 | AB47: \\172.28.9.34\share drive\Artefacts_T-Fiber TNOC Tracker\DC IT-Infra\Artifact for -T44 | AI47: 472DC-IT | AJ47: Network | AK47: CLOSED | AO47: 45791 | AP47: \\172.28.9.34\share drive\Artefacts_T-Fiber TNOC Tracker\DC IT-Infra\Artifact for -T44 | AR47: 1 | AS47: Completed & Approved | AT47: Closed before june-2025
B48: 46 | C48: T45 | D48: 472 | E48: NA | I48: DC-IT | J48: Commvault Backup | K48: Application Installation | N48: Colosed | V48: Ravi Kishore | Y48: COMPLETED & APPROVED | Z48: AD-UT-Tfiber | AA48: 45791 | AB48: \\172.28.9.34\Artefacts_T-Fiber TNOC Tracker\DC IT-Infra\Artifact for - T45 | AI48: 472DC-IT | AJ48: Network | AK48: CLOSED | AO48: 45791 | AP48: \\172.28.9.34\Artefacts_T-Fiber TNOC Tracker\DC IT-Infra\Artifact for - T45 | AR48: 1 | AS48: Completed & Approved | AT48: Closed before june-2025
B49: 47 | C49: T46 | D49: 472 | E49: NA | I49: DC-IT | J49: Commvault Backup | K49: Application Configuration | N49: Colosed | V49: Ravi Kishore | Y49: COMPLETED & APPROVED | Z49: AD-UT-Tfiber | AA49: 45791 | AB49: \\172.28.9.34\Artefacts_T-Fiber TNOC Tracker\DC IT-Infra\Artifact for - T46 | AI49: 472DC-IT | AJ49: Network | AK49: CLOSED | AO49: 45791 | AP49: \\172.28.9.34\Artefacts_T-Fiber TNOC Tracker\DC IT-Infra\Artifact for - T46 | AR49: 1 | AS49: Completed & Approved | AT49: Closed before june-2025
B50: 48 | C50: T47 | D50: 472 | E50: NA | I50: DC-IT | J50: Commvault Backup | K50: Application Installation AT | N50: Colosed | V50: Ravi Kishore | Y50: COMPLETED & APPROVED | Z50: AD-UT-Tfiber | AA50: 45791 | AB50: \\172.28.9.34\Artefacts_T-Fiber TNOC Tracker\DC IT-Infra\Artifact for - T47 | AI50: 472DC-IT | AJ50: Network | AK50: CLOSED | AO50: 45791 | AP50: \\172.28.9.34\Artefacts_T-Fiber TNOC Tracker\DC IT-Infra\Artifact for - T47 | AR50: 1 | AS50: Completed & Approved | AT50: Closed before june-2025
B51: 49 | C51: T48 | D51: 472 | E51: NA | I51: DC-IT | J51: Commvault Backup | K51: Application Functional AT | N51: Open | S51: Working on the Extra Test cases which are received from the TPA & T-Fiber. | V51: Ravi Kishore | X51: Open | Y51: WIP | AB51: \\172.28.9.34\Artefacts_T-Fiber TNOC Tracker\DC IT-Infra\Artifact for - T48 | AI51: 472DC-IT | AJ51: Network | AK51: OPEN | AR51: 1 | AS51: Open | AT51: Open
B52: 50 | C52: T49 | D52: 472 | E52: NA | I52: DC-IT | J52: LLD | K52: LLD Approved conditionally with few punch points. Updated LLD to be submitted | N52: Open | S52: Working on DC IT-Infra Server and storage-MoM Points received from the T-Fiber. | V52: Ravi Kishore | X52: Open | Y52: WIP | AB52: \\172.28.9.34\Artefacts_T-Fiber TNOC Tracker\DC IT-Infra\Artifact for - T49 | AI52: 472DC-IT | AJ52: Network | AK52: OPEN | AR52: 1 | AS52: Open | AT52: Open
B53: 51 | C53: T50 | D53: 472 | E53: NA | I53: DC-IT | J53: MoM Action | K53: Radware , A10 Configuration file needed to be shared to RaviKishore | N53: Open | S53: Artfacts submitted . point Closure on 10 Jul 25 | V53: Sarmendra | Y53: COMPLETED & APPROVED | AB53: \\172.28.9.34\Artefacts_T-Fiber TNOC Tracker\NW-Security\T50 | AI53: 472DC-IT | AJ53: Network | AK53: CLOSED | AP53: \\172.28.9.34\Artefacts_T-Fiber TNOC Tracker\NW-Security\T50 | AR53: 1 | AS53: Completed & Approved | AT53: Closed after June
B54: 52 | C54: T51 | D54: 472 | E54: NA | I54: DC-IT | J54: Commvault Backup | K54: Backup retention and Backup activity (such as when incremental backup,full backup are scheduled and time duration required to complete such backup). Application Wise Backup Retention should be as per DOT Guidelines | N54: Colosed | V54: Ravi Kishore | Y54: COMPLETED & APPROVED | Z54: AD-UT-Tfiber | AA54: 45791 | AB54: \\172.28.9.34\Artefacts_T-Fiber TNOC Tracker\DC IT-Infra\Artifact for - T51 | AI54: 472DC-IT | AJ54: Network | AK54: CLOSED | AO54: 45791 | AP54: \\172.28.9.34\Artefacts_T-Fiber TNOC Tracker\DC IT-Infra\Artifact for - T51 | AR54: 1 | AS54: Completed & Approved | AT54: Closed before june-2025
B55: 53 | C55: T52 | D55: 472 | E55: NA | I55: DC-IT | J55: Commvault Backup | K55: Backup solution should have hot , cold and archieve storage inorder to decrease the backup size/capacity in long run. | N55: Colosed | V55: Ravi Kishore | Y55: COMPLETED & APPROVED | Z55: AD-UT-Tfiber | AA55: 45791 | AB55: \\172.28.9.34\share drive\Artefacts_T-Fiber TNOC Tracker\DC IT-Infra\Artifact for - T52 | AI55: 472DC-IT | AJ55: Network | AK55: CLOSED | AO55: 45791 | AP55: \\172.28.9.34\share drive\Artefacts_T-Fiber TNOC Tracker\DC IT-Infra\Artifact for - T52 | AR55: 1 | AS55: Completed & Approved | AT55: Closed before june-2025
B56: 54 | C56: T53 | D56: 472 | E56: NA | I56: DC-IT | J56: SSD storage migration – EPNM/PI | K56: EPNM/PI VMs migration to SSD Storage | N56: Colosed | V56: Ravi Kishore | Y56: COMPLETED & APPROVED | Z56: AD-UT-Tfiber | AA56: 45791 | AB56: \\172.28.9.34\share drive\Artefacts_T-Fiber TNOC Tracker\DC IT-Infra\Artifact for - T53 | AI56: 472DC-IT | AJ56: Network | AK56: CLOSED | AO56: 45791 | AP56: \\172.28.9.34\share drive\Artefacts_T-Fiber TNOC Tracker\DC IT-Infra\Artifact for - T53 | AR56: 1 | AS56: Completed & Approved | AT56: Closed before june-2025
B57: 55 | C57: T54 | D57: 472 | E57: NA | I57: DC-IT | J57: SSD storage migration – ISE/FMC | K57: ISE & FMC VMs migration to SSD Storage | N57: Colosed | V57: Ravi Kishore | Y57: COMPLETED & APPROVED | Z57: AD-UT-Tfiber | AA57: 45791 | AB57: \\172.28.9.34\share drive\Artefacts_T-Fiber TNOC Tracker\DC IT-Infra\Artifact for - T54 | AI57: 472DC-IT | AJ57: Network | AK57: CLOSED | AO57: 45791 | AP57: \\172.28.9.34\share drive\Artefacts_T-Fiber TNOC Tracker\DC IT-Infra\Artifact for - T54 | AR57: 1 | AS57: Completed & Approved | AT57: Closed before june-2025
B58: 56 | C58: T55 | D58: 472 | E58: NA | I58: DC-IT | J58: MoM Action | K58: VM Placing should be verified & rectified, Same service VM needs to be placed in different Physical Server/host. | N58: Colosed | V58: Ravi Kishore | Y58: COMPLETED & APPROVED | Z58: AD-UT-Tfiber | AA58: 45791 | AB58: \\172.28.9.34\share drive\Artefacts_T-Fiber TNOC Tracker\DC IT-Infra\Artifact for - T55 | AI58: 472DC-IT | AJ58: Network | AK58: CLOSED | AO58: 45791 | AP58: \\172.28.9.34\share drive\Artefacts_T-Fiber TNOC Tracker\DC IT-Infra\Artifact for - T55 | AR58: 1 | AS58: Completed & Approved | AT58: Closed before june-2025
B59: 57 | C59: T56 | D59: 472 | E59: NA | I59: DC-IT | J59: MoM Action | K59: SOP documents needs to be provided | N59: Open | S59: SOP documents submitted to Operations team. Remaining pending documents to be prepared periodically. | V59: Ravi Kishore | X59: Open | Y59: REOPENED | AB59: \\172.28.9.34\share drive\Artefacts_T-Fiber TNOC Tracker\DC IT-Infra\Artifact for - T56 | AI59: 472DC-IT | AJ59: Network | AK59: OPEN | AR59: 1 | AS59: Open | AT59: Open
B60: 58 | C60: T57 | D60: 472 | E60: NA | I60: DC-IT | J60: LLD | K60: Approved conditionally with few punch points. Updated LLD to be submitted | N60: Open | S60: 14-Aug-25 : Discussion was done with TPA and Tfiber and submitted updated LLD document. 18-Jun-25 : Updated DC Network LLD submitted on 18-Jun-25 for TFiber review | T60: L&T | V60: RS Rao | Y60: COMPLETED & APPROVED | AI60: 472DC-IT | AJ60: Network | AK60: CLOSED | AO60: 45883 | AP60: \\172.28.9.34\Artefacts_T-Fiber TNOC Tracker\IPMPLS\DC Network LLD V1.7 14-Aug-2025.pdf | AR60: 1 | AS60: Completed & Approved | AT60: Closed after June
B61: 59 | C61: T58 | D61: 472 | E61: NA | I61: DC-IT | J61: Cisco EPNM | K61: Cisco EPNM infrastructure AT | N61: Open | S61: 22-Sep-25: IPMPLS Domain team to submit detailed remarks on raised queries. 08-Jul-2025 - Sandeep will come back by EoD today on extension of Cisco support renewal 01-Jul-25 : Revised FAT documents submission pending (TPA observations to be included) OEM(Cisco) suport is required to show the new test cases, Inputs provided to OEM on 14th May & 30th Jun. OEM onboarding is in progress & LnT Contracts team coordinating | T61: L&T | U61: RS Rao | V61: RS Rao | X61: Open | Y61: Open | AI61: 472DC-IT | AJ61: Network | AK61: OPEN | AR61: 1 | AS61: Open | AT61: Open
B62: 60 | C62: T59 | D62: 472 | E62: NA | I62: DC-IT | J62: Cisco PI | K62: Cisco prime infrastructure AT | N62: Open | S62: 22-Sep-25: IPMPLS Domain team to submit detailed remarks on raised queries. 08-Jul-2025 - Sandeep will come back by EoD today on extension of Cisco support renewal 01-Jul-25 : Revised FAT documents submission pending (TPA observations to be included) OEM(Cisco) suport is required to show the new test cases, Inputs provided to OEM on 14th May & 30th Jun. OEM onboarding is in progress & LnT Contracts team is coordinating | T62: L&T | U62: RS Rao | V62: RS Rao | X62: Open | Y62: Open | AI62: 472DC-IT | AJ62: Network | AK62: OPEN | AR62: 1 | AS62: Open | AT62: Open
B63: 61 | C63: T60 | D63: 472 | E63: NA | I63: DC-IT | J63: NTP | K63: Installation | N63: Colosed | V63: RS Rao | Y63: COMPLETED & APPROVED | Z63: AD-UT-Tfiber | AA63: 45782 | AB63: \\172.28.9.34\Artefacts_T-Fiber TNOC Tracker\IPMPLS\Primary NTP - T60,T61,T62.pdf \\172.28.9.34\Artefacts_T-Fiber TNOC Tracker\IPMPLS\Secondary NTP - T60,T61,T62.pdf | AI63: 472DC-IT | AJ63: Network | AK63: CLOSED | AO63: 45782 | AP63: \\172.28.9.34\Artefacts_T-Fiber TNOC Tracker\IPMPLS\Primary NTP - T60,T61,T62.pdf \\172.28.9.34\Artefacts_T-Fiber TNOC Tracker\IPMPLS\Secondary NTP - T60,T61,T62.pdf | AR63: 1 | AS63: Completed & Approved | AT63: Closed before june-2025
B64: 62 | C64: T61 | D64: 472 | E64: NA | I64: DC-IT | J64: NTP | K64: Configuration | N64: Colosed | V64: RS Rao | Y64: COMPLETED & APPROVED | Z64: AD-UT-Tfiber | AA64: 45782 | AB64: \\172.28.9.34\Artefacts_T-Fiber TNOC Tracker\IPMPLS\Primary NTP - T60,T61,T62.pdf \\172.28.9.34\Artefacts_T-Fiber TNOC Tracker\IPMPLS\Secondary NTP - T60,T61,T62.pdf | AI64: 472DC-IT | AJ64: Network | AK64: CLOSED | AO64: 45782 | AP64: \\172.28.9.34\Artefacts_T-Fiber TNOC Tracker\IPMPLS\Primary NTP - T60,T61,T62.pdf \\172.28.9.34\Artefacts_T-Fiber TNOC Tracker\IPMPLS\Secondary NTP - T60,T61,T62.pdf | AR64: 1 | AS64: Completed & Approved | AT64: Closed before june-2025
B65: 63 | C65: T62 | D65: 472 | E65: NA | I65: DC-IT | J65: NTP | K65: NTP Installation AT | N65: Colosed | V65: RS Rao | Y65: COMPLETED & APPROVED | Z65: AD-UT-Tfiber | AA65: 45782 | AB65: \\172.28.9.34\Artefacts_T-Fiber TNOC Tracker\IPMPLS\Primary NTP - T60,T61,T62.pdf \\172.28.9.34\Artefacts_T-Fiber TNOC Tracker\IPMPLS\Secondary NTP - T60,T61,T62.pdf | AI65: 472DC-IT | AJ65: Network | AK65: CLOSED | AO65: 45782 | AP65: \\172.28.9.34\Artefacts_T-Fiber TNOC Tracker\IPMPLS\Primary NTP - T60,T61,T62.pdf \\172.28.9.34\Artefacts_T-Fiber TNOC Tracker\IPMPLS\Secondary NTP - T60,T61,T62.pdf | AR65: 1 | AS65: Completed & Approved | AT65: Closed before june-2025
B66: 64 | C66: T63 | D66: 472 | E66: NA | I66: DC-IT | J66: NTP | K66: NTP Functional AT | N66: Open | V66: RS Rao | Y66: COMPLETED & APPROVED | Z66: AD-UT-Tfiber | AA66: 45841 | AB66: \\172.28.9.34\Artefacts_T-Fiber TNOC Tracker\IPMPLS\NTP FAT & Acceptance - T63.pdf | AI66: 472DC-IT | AJ66: Network | AK66: CLOSED | AO66: 45841 | AP66: \\172.28.9.34\Artefacts_T-Fiber TNOC Tracker\IPMPLS\NTP FAT & Acceptance - T63.pdf | AR66: 1 | AS66: Completed & Approved | AT66: Closed after June
B67: 65 | C67: T64 | D67: 472 | E67: NA | I67: DC-IT | J67: Functional AT | K67: DC Network Infra AT | N67: Open | S67: 22-Sep-25: IPMPLS Domain team to submit detailed remarks on raised queries. 08-Jul-2025 - Sandeep will come back by EoD today on extension of Cisco support renewal 01-Jul-25 : Revised FAT documents submission pending (TPA observations to be included) OEM(Cisco) suport is required to show the new test cases, Inputs provided to OEM on 14th May & 30th Jun. OEM onboarding is in progress & LnT Contracts team is coordinating | T67: L&T | U67: RS Rao | V67: RS Rao | X67: Open | Y67: Open | AI67: 472DC-IT | AJ67: Network | AK67: OPEN | AR67: 1 | AS67: Open | AT67: Open
B68: 66 | C68: T65 | D68: 472 | E68: NA | I68: DR | J68: Servers and Strorage (Deployment and Installations) | K68: Virtulization | N68: Colosed | V68: Ravi Kishore | Y68: COMPLETED & APPROVED | Z68: AD-UT-Tfiber | AA68: 45791 | AB68: \\172.28.9.34\share drive\Artefacts_T-Fiber TNOC Tracker\DR\Artifact for - T65 | AI68: 472DR | AJ68: DR | AK68: CLOSED | AO68: 45791 | AP68: \\172.28.9.34\share drive\Artefacts_T-Fiber TNOC Tracker\DR\Artifact for - T65 | AR68: 1 | AS68: Completed & Approved | AT68: Closed before june-2025
B69: 67 | C69: T66 | D69: 472 | E69: NA | I69: DR | J69: DC (TNOC-DR) | K69: Network Readiness | N69: Colosed | V69: Ravi Kishore | Y69: COMPLETED & APPROVED | Z69: AD-UT-Tfiber | AA69: 45791 | AB69: \\172.28.9.34\Artefacts_T-Fiber TNOC Tracker\DR\Artifact for - T66 | AI69: 472DR | AJ69: DR | AK69: CLOSED | AO69: 45791 | AP69: \\172.28.9.34\Artefacts_T-Fiber TNOC Tracker\DR\Artifact for - T66 | AR69: 1 | AS69: Completed & Approved | AT69: Closed before june-2025
B70: 68 | C70: T67 | D70: 472 | E70: NA | I70: DR | J70: Mahbubnagar-DR | K70: Network Readiness | N70: Colosed | V70: Ravi Kishore | Y70: COMPLETED & APPROVED | Z70: AD-UT-Tfiber | AA70: 45791 | AB70: \\172.28.9.34\share drive\Artefacts_T-Fiber TNOC Tracker\DR\Artifact for -T67 | AI70: 472DR | AJ70: DR | AK70: CLOSED | AO70: 45791 | AP70: \\172.28.9.34\Artefacts_T-Fiber TNOC Tracker\DR\Artifact for - T66 | AR70: 1 | AS70: Completed & Approved | AT70: Closed before june-2025
B71: 69 | C71: T68 | D71: 472 | E71: NA | I71: DR | J71: Design & Documentation | K71: LLD: Approved conditionally with few punch points. Updated LLD to be submitted | N71: Open | S71: Working on additional points shared by Tfiber. | V71: Ravi Kishore | X71: Open | Y71: WIP | AB71: \\172.28.9.34\Artefacts_T-Fiber TNOC Tracker\DR\Artifact for -T68 | AI71: 472DR | AJ71: DR | AK71: OPEN | AR71: 1 | AS71: Open | AT71: Open
B72: 70 | C72: T69 | D72: 472 | E72: NA | I72: DR | J72: Design & Documentation | K72: HLD: Revised solution to submitted | N72: Open | S72: Working on additional points shared by Tfiber. | V72: Ravi Kishore | X72: Open | Y72: WIP | AB72: \\172.28.9.34\Artefacts_T-Fiber TNOC Tracker\DR\Artifact for -T69 | AI72: 472DR | AJ72: DR | AK72: OPEN | AR72: 1 | AS72: Open | AT72: Open
B73: 71 | C73: T70 | D73: 472 | E73: NA | I73: DR | J73: Design & Documentation | K73: DC-DR redunancy Test | N73: Colosed | V73: Ravi Kishore | Y73: COMPLETED & APPROVED | Z73: AD-UT-Tfiber | AA73: 45791 | AB73: \\172.28.9.34\share drive\Artefacts_T-Fiber TNOC Tracker\DR\Artifact for - T70 | AI73: 472DR | AJ73: DR | AK73: CLOSED | AO73: 45791 | AP73: \\172.28.9.34\share drive\Artefacts_T-Fiber TNOC Tracker\DR\Artifact for - T70 | AR73: 1 | AS73: Completed & Approved | AT73: Closed before june-2025
B74: 72 | C74: T71 | D74: 472 | E74: NA | I74: DR | J74: MoM Action | K74: UTM Features (DR FW) | N74: Open | S74: Meeting scheduled with CTRL S to verify the UTM features | V74: Sarmendra | X74: Open | Y74: WIP | AI74: 472DR | AJ74: DR | AK74: OPEN | AR74: 1 | AS74: Open | AT74: Open
B75: 73 | C75: T72 | D75: 472 | E75: NA | I75: DR | J75: MoM Action | K75: To configure LACP between L3 Switch and Core Router | N75: Open | S75: 11-Oct-25: CtrlS has to give proposal for procurement for addtional BoQ. IT infra SME need to Re-intiate a mail to get BoQ 22-Sep-25: The existing switch which was placed at DR by CtrlS doesnt have feature on LACP Bundling. CtrlS is planning to relplace the exising switch with LACP supported switch. DC Infra admin need to provide tentative timelines for replacement. 08-Jul-2025 Sandeep will ensure on CTRL-S support and update by EoD 01-Jul-25 : Ticket (SR01301726) raised with CtrlS on 27-Jun, Config & testing to be carried out. This is additional task as per CtrlS and commercials may be involved. LnT Contracts team also talking to CtrlS account team to complete the task. 24-Dec-25 : SR01036770 opened with CtrlS for LACP configuration and it is not O&M activity as per CtrlS ops. team. escalated to LnT Contracts team for supoort. | T75: CtrlS | U75: Venkat | V75: Ravi Kishore | X75: Open | Y75: WIP | AI75: 472DR | AJ75: DR | AK75: OPEN | AR75: 1 | AS75: Open | AT75: Open
B76: 74 | C76: T73 | D76: 472 | E76: NA | I76: DR | J76: MoM Action | K76: To configure LACP between Core Router and Firewall | N76: Open | S76: 11-Oct-25: CtrlS has to give proposal for procurement for addtional BoQ. IT infra SME need to Re-intiate a mail to get BoQ 22-Sep-25: The existing switch which was placed at DR by CtrlS doesnt have feature on LACP Bundling. CtrlS is planning to relplace the exising switch with LACP supported switch. DC Infra admin need to provide tentative timelines for replacement. 01-Jul-25 : Ticket (SR01301726) raised with CtrlS on 27-Jun, Config & testing to be carried out. This is additional task as per CtrlS and commercials may be involved. LnT Contracts team also talking to CtrlS account team to complete the task. 24-Dec-25 : SR01036770 opened with CtrlS for LACP configuration and it is not O&M activity as per CtrlS ops. team. escalated to LnT Contracts team for supoort. | T76: CtrlS | U76: Venkat | V76: Ravi Kishore | X76: Open | Y76: WIP | AI76: 472DR | AJ76: DR | AK76: OPEN | AR76: 1 | AS76: Open | AT76: Open
B77: 75 | C77: T74 | D77: 472 | E77: NA | I77: DR | J77: MoM Action | K77: To configure LACP between Firewall and L2 Switch | N77: Open | S77: 11-Oct-25: CtrlS has to give proposal for procurement for addtional BoQ. IT infra SME need to Re-intiate a mail to get BoQ 22-Sep-25: The existing switch which was placed at DR by CtrlS doesnt have feature on LACP Bundling. CtrlS is planning to relplace the exising switch with LACP supported switch. DC Infra admin need to provide tentative timelines for replacement. 01-Jul-25 : Ticket (SR01301726) raised with CtrlS on 27-Jun, Config & testing to be carried out. This is additional task as per CtrlS and commercials may be involved. LnT Contracts team also talking to CtrlS account team to complete the task. 24-Dec-25 : SR01036770 opened with CtrlS for LACP configuration and it is not O&M activity as per CtrlS ops. team. escalated to LnT Contracts team for supoort. | T77: CtrlS | U77: Venkat | V77: Ravi Kishore | X77: Open | Y77: WIP | AI77: 472DR | AJ77: DR | AK77: OPEN | AR77: 1 | AS77: Open | AT77: Open
B78: 76 | C78: T75 | D78: 472 | E78: NA | I78: DR | J78: MoM Action | K78: To confirm on backups for DR Virtual machines | N78: Colosed | V78: Ravi Kishore | Y78: COMPLETED & APPROVED | Z78: AD-UT-Tfiber | AA78: 45791 | AB78: \\172.28.9.34\share drive\Artefacts_T-Fiber TNOC Tracker\DR\Artifact for - T75 | AI78: 472DR | AJ78: DR | AK78: CLOSED | AO78: 45791 | AP78: \\172.28.9.34\share drive\Artefacts_T-Fiber TNOC Tracker\DR\Artifact for - T75 | AR78: 1 | AS78: Completed & Approved | AT78: Closed before june-2025
B79: 77 | C79: T76 | D79: 472 | E79: NA | I79: DR | J79: MoM Action | K79: Backup storage to 25 TB | N79: Colosed | V79: Ravi Kishore | Y79: COMPLETED & APPROVED | Z79: AD-UT-Tfiber | AA79: 45791 | AB79: \\172.28.9.34\share drive\Artefacts_T-Fiber TNOC Tracker\DR\Artifact for - T76 | AI79: 472DR | AJ79: DR | AK79: CLOSED | AO79: 45791 | AP79: \\172.28.9.34\share drive\Artefacts_T-Fiber TNOC Tracker\DR\Artifact for - T76 | AR79: 1 | AS79: Completed & Approved | AT79: Closed before june-2025
B80: 78 | C80: T77 | D80: 472 | E80: NA | I80: DR | J80: MoM Action | K80: To submit the SOPs for DC-DR switchover, DC-DR failover and failback | N80: Open | S80: Tejas, Nokia, GIS & Ciena MCP documnets are received. Remaining all Applications domains SOP's to be updated. | V80: Ravi Kishore | X80: Open | Y80: REOPENED | AB80: \\172.28.9.34\share drive\Artefacts_T-Fiber TNOC Tracker\DR\Artifact for - T77 | AI80: 472DR | AJ80: DR | AK80: OPEN | AR80: 1 | AS80: Open | AT80: Open
B81: 79 | C81: T78 | D81: 472 | E81: NA | I81: DR | J81: MoM Action | K81: to monitor the DR Servers | N81: Open | S81: DR servers monitoring through DR vCentre happening. DR is maintained by CtrlS team as per contract. Feasibility to be checked to integrated through OSS OBM. | V81: Ravi Kishore | X81: Open | Y81: WIP | AB81: \\172.28.9.34\share drive\Artefacts_T-Fiber TNOC Tracker\DR\Artifact for - T78 | AI81: 472DR | AJ81: DR | AK81: OPEN | AR81: 1 | AS81: Open | AT81: Open
B82: 80 | C82: T79 | D82: 472 | E82: NA | I82: DR | J82: MoM Action | K82: To confirm that DNS switchover between DC and DR locations should be automatic | N82: Colosed | V82: Ravi Kishore | Y82: COMPLETED & APPROVED | Z82: AD-UT-Tfiber | AA82: 45791 | AB82: \\172.28.9.34\Artefacts_T-Fiber TNOC Tracker\DR\Artifact for - T79 | AI82: 472DR | AJ82: DR | AK82: CLOSED | AO82: 45791 | AP82: \\172.28.9.34\Artefacts_T-Fiber TNOC Tracker\DR\Artifact for - T79 | AR82: 1 | AS82: Completed & Approved | AT82: Closed before june-2025
B83: 81 | C83: T80 | D83: 472 | E83: NA | I83: DR | J83: MoM Action | K83: Mahubnagar as NTP | N83: Colosed | V83: RS Rao | Y83: COMPLETED & APPROVED | Z83: AD-UT-Tfiber | AA83: 45782 | AB83: \\172.28.9.34\Artefacts_T-Fiber TNOC Tracker\IPMPLS\Primary NTP - T60,T61,T62.pdf \\172.28.9.34\Artefacts_T-Fiber TNOC Tracker\IPMPLS\Secondary NTP - T60,T61,T62.pdf | AI83: 472DR | AJ83: DR | AK83: CLOSED | AO83: 45782 | AP83: \\172.28.9.34\Artefacts_T-Fiber TNOC Tracker\IPMPLS\Primary NTP - T60,T61,T62.pdf \\172.28.9.34\Artefacts_T-Fiber TNOC Tracker\IPMPLS\Secondary NTP - T60,T61,T62.pdf | AR83: 1 | AS83: Completed & Approved | AT83: Closed before june-2025
B84: 82 | C84: T81 | D84: 472 | E84: NA | I84: DR | J84: Configuration | K84: All application to be migrated to implement DR LB configuration | N84: Open | S84: 11-Oct-25: Approved DR HLD document to be shared with T Fiber for further discussion. Noikia app is integrated with DR LB . Balance application migration on DR LB is in Pipeline | V84: Ravi Kishore | X84: Open | Y84: WIP | AI84: 472DR | AJ84: DR | AK84: OPEN | AR84: 1 | AS84: Open | AT84: Open
B85: 83 | C85: T82 | D85: 472 | E85: NA | I85: DR | J85: MoM Action | K85: To confirm the applications which support Veem Replication for Reconfiguration | N85: Colosed | V85: Ravi Kishore | Y85: COMPLETED & APPROVED | Z85: AD-UT-Tfiber | AA85: 45791 | AB85: \\172.28.9.34\share drive\Artefacts_T-Fiber TNOC Tracker\DR\Artifact for - T82 | AI85: 472DR | AJ85: DR | AK85: CLOSED | AO85: 45791 | AP85: \\172.28.9.34\share drive\Artefacts_T-Fiber TNOC Tracker\DR\Artifact for - T82 | AR85: 1 | AS85: Completed & Approved | AT85: Closed before june-2025
B86: 84 | C86: T83 | D86: 472 | E86: NA | I86: DWDM | J86: Network Deployment & integration | K86: Zonal Links Integration (12/15) | N86: Open | S86: 20-Sep-25: Nirmal, Jainoor, Gudihatnoor & Bhimni RFE pending due to forest permission 31-July-2025:As per discussion with Ramanaiah sir, need to discuss these points with T Fiber Project team for further action, till that time this point kept on hold Depend on 04 Facilities RFE in Pkg-C Asifabad - Warangal & Karimnagar - Asifabad - Links integrated as per interim plan, actual integration pending Nizamabad - Asifabad - E2E link integration pending 28th-Apr'25: As per Sandeep Sanmani - Forest permission still pending 6/25/2025: Status is same no visibility on forest permission, Target date would be D+21 05-July-25: No progress on the forest permission | T86: T Fiber | U86: Srinivas Jukuri(Project) | V86: Suresh Kumar | X86: Open | Y86: DEPENDENCY(Client/Ext.) | AI86: 472DWDM | AJ86: DWDM | AK86: OPEN | AR86: 1 | AS86: Open | AT86: Open
B87: 85 | C87: T84 | D87: 472 | E87: NA | I87: DWDM | J87: Network Deployment & integration | K87: Nodes Live & Operational (67/71) | N87: Open | S87: 31-July-2025:As per discussion with Ramanaiah sir, need to discuss these points with T Fiber Project team for further action, till that time this point kept on hold Nirmal, Jainoor, Gudihatnoor & Bhimni RFE pending due to forest permission 28th-Apr'25: As per Sandeep Sanmani - Forest permission still pending 15-06-25: No progress on the permission, target - D+15 05-July-25: No progress on the forest permission | T87: T Fiber | U87: Srinivas Jukuri(Project) | V87: Suresh Kumar | X87: Open | Y87: DEPENDENCY(Client/Ext.) | AI87: 472DWDM | AJ87: DWDM | AK87: OPEN | AR87: 1 | AS87: Open | AT87: Open
B88: 86 | C88: T85 | D88: 472 | E88: NA | I88: DWDM | J88: Network Deployment & integration | K88: Zonal Rings readiness with 1+R protection (5/7) | N88: Open | S88: 31-July-2025:As per discussion with Ramanaiah sir, need to discuss these points with T Fiber Project team for further action, till that time this point kept on hold 02 rings depend on 04 Facilities RFE readiness in Pkg-C, which is pending due to forest permission 28th-Apr'25: As per Sandeep Sanmani - Forest permission still pending 6/25/2025: No visibility on forest permission, target date would be D+30 05-July-25: No progress on the forest permission | T88: T Fiber | U88: Srinivas Jukuri(Project) | V88: Suresh Kumar | X88: Open | Y88: DEPENDENCY(Client/Ext.) | AI88: 472DWDM | AJ88: DWDM | AK88: OPEN | AR88: 1 | AS88: Open | AT88: Open
B89: 87 | C89: T86 | D89: 472 | E89: NA | I89: DWDM | J89: Network Deployment & AT Status | K89: Nodal AT (67/71) | N89: Open | S89: 31-July-2025:As per discussion with Ramanaiah sir, need to discuss these points with T Fiber Project team for further action, till that time this point kept on hold Nirmal, Jainoor, Gudihatnoor & Bhimni RFE pending due to forest permission 28th-Apr'25: As per Sandeep Sanmani - Forest permission still pending 15-06-25: No progress on the permission, target - D+15 05-July-25: No progress on the forest permission | T89: T Fiber | U89: Srinivas Jukuri(Project) | V89: Suresh Kumar | X89: Open | Y89: DEPENDENCY(Client/Ext.) | AI89: 472DWDM | AJ89: DWDM | AK89: OPEN | AR89: 1 | AS89: Open | AT89: Open
B90: 88 | C90: T87 | D90: 472 | E90: NA | I90: DWDM | J90: Network Deployment & integration | K90: Mandal Ring Integration through OADM | N90: Open | S90: 31-July-2025:As per discussion with Ramanaiah sir, need to discuss these points with T Fiber Project team for further action, till that time this point kept on hold Mandal services are provisioned (10G) as per integration plan by all packages 6/25/2025: 203 services provisioned out of 270 planned. Remaining can be provisioned as per the requirement | T90: T Fiber | U90: Srinivas Jukuri(Project) | V90: Suresh Kumar | X90: Open | Y90: DEPENDENCY(Client/Ext.) | AI90: 472DWDM | AJ90: DWDM | AK90: OPEN | AR90: 1 | AS90: Open | AT90: Open
B91: 89 | C91: T88 | D91: 472 | E91: NA | I91: DWDM | J91: Network Deployment & AT Status | K91: Zonal Link AT (7/15) | N91: Open | S91: 31-July-2025:As per discussion with Ramanaiah sir, need to discuss these points with T Fiber Project team for further action, till that time this point kept on hold 04 Link AT's approved by T Fiber and 03 Link AT's pending due to letter from Ciena awaited (No impact due to ILA to OADM upgradation) 05 Link AT pending due to high losses in the spans, depend on all packages 02 Links integrated as per interim plan, so not considered for Link AT 20May'25: Declaration letter submitted to T Fiber for 03 links AT approval 25-06-2025: Dependancy on field, no progress. 30-June-2025: As discussed in the meeting, need to arrange meeting with all stakeholders | T91: All Packages | V91: Suresh Kumar | X91: Open | Y91: DEPENDENCY(Client/Ext.) | AI91: 472DWDM | AJ91: DWDM | AK91: OPEN | AN91: 20-Sep-25: Mr.Suresh will update the status | AR91: 1 | AS91: Open | AT91: Open
B92: 90 | C92: T89 | D92: 472 | E92: NA | I92: DWDM | J92: Design & Documentation | K92: HLD (Revised) with OADM Solution | N92: Colosed | V92: Suresh Kumar | Y92: COMPLETED & APPROVED | Z92: AD-UT-Tfiber | AA92: 45783 | AB92: \\172.28.9.34\Artefacts_T-Fiber TNOC Tracker\DWDM\Artefact - T89 | AI92: 472DWDM | AJ92: DWDM | AK92: CLOSED | AO92: 45783 | AP92: \\172.28.9.34\Artefacts_T-Fiber TNOC Tracker\DWDM\Artefact - T89 | AR92: 1 | AS92: Completed & Approved | AT92: Closed before june-2025
B93: 91 | C93: T90 | D93: 472 | E93: NA | I93: DWDM | J93: Design & Documentation | K93: LLD (Revised) with OADM Solution (Ciena) | N93: Colosed | V93: Suresh Kumar | Y93: COMPLETED & APPROVED | Z93: AD-UT-Tfiber | AA93: 45783 | AB93: \\172.28.9.34\Artefacts_T-Fiber TNOC Tracker\DWDM\Artefact - T90 | AI93: 472DWDM | AJ93: DWDM | AK93: CLOSED | AO93: 45783 | AP93: \\172.28.9.34\Artefacts_T-Fiber TNOC Tracker\DWDM\Artefact - T90 | AR93: 1 | AS93: Completed & Approved | AT93: Closed before june-2025
B94: 92 | C94: T91 | D94: 472 | E94: NA | I94: DWDM | J94: Design & Documentation | K94: Nodal ATP | N94: Colosed | V94: Suresh Kumar | Y94: COMPLETED & APPROVED | Z94: AD-UT-Tfiber | AA94: 45783 | AB94: \\172.28.9.34\Artefacts_T-Fiber TNOC Tracker\DWDM\Artefact - T91 & T92 | AI94: 472DWDM | AJ94: DWDM | AK94: CLOSED | AO94: 45783 | AP94: \\172.28.9.34\Artefacts_T-Fiber TNOC Tracker\DWDM\Artefact - T91 & T92 | AR94: 1 | AS94: Completed & Approved | AT94: Closed before june-2025
B95: 93 | C95: T92 | D95: 472 | E95: NA | I95: DWDM | J95: Design & Documentation | K95: Link ATP | N95: Colosed | V95: Suresh Kumar | Y95: COMPLETED & APPROVED | Z95: AD-UT-Tfiber | AA95: 45783 | AB95: \\172.28.9.34\Artefacts_T-Fiber TNOC Tracker\DWDM\Artefact - T91 & T92 | AI95: 472DWDM | AJ95: DWDM | AK95: CLOSED | AO95: 45783 | AP95: \\172.28.9.34\Artefacts_T-Fiber TNOC Tracker\DWDM\Artefact - T91 & T92 | AR95: 1 | AS95: Completed & Approved | AT95: Closed before june-2025
B96: 94 | C96: T93 | D96: 472 | E96: NA | I96: DWDM | J96: Design & Documentation | K96: Ring ATP | N96: Colosed | V96: Suresh Kumar | Y96: COMPLETED & APPROVED | Z96: AD-UT-Tfiber | AA96: 45783 | AB96: \\172.28.9.34\Artefacts_T-Fiber TNOC Tracker\DWDM\Artefact - T93 | AI96: 472DWDM | AJ96: DWDM | AK96: CLOSED | AO96: 45783 | AP96: \\172.28.9.34\Artefacts_T-Fiber TNOC Tracker\DWDM\Artefact - T93 | AR96: 1 | AS96: Completed & Approved | AT96: Closed before june-2025
B97: 95 | C97: T94 | D97: 472 | E97: NA | I97: DWDM | J97: Design & Documentation | K97: DWDM EMS (MCP) Functional ATP | N97: Open | S97: 20-Sep-25: MCP FAT document submitted to TPA on XX-XX-XXXX. Meeting need to be scheduled on 22-Sep-25 with TPA to get the clarifications on delay. 13-Sep-25: Response awaited from TPA team 29-August-2025: Spoken with Mr. Bijju, response awaited 26-July-25: FAT document approval pending 08-July-2025: 1. MCP FAT document prepared as per RFP requirements and TPA remarks 2. 100G traffic throughput will be shown during Ring ATP 07-July-2025: 1. SME not aware of MCP FAT Check list, but prepared FAT document and sent to TPA for validation 05-July-2025: Submitted AT document to T Fiber TPA 30-June-2025: target to submit by 2nd July'25, based on OEM reply Revised version to be submitted as per T Fiber remarks on 29th Apr'25 | T97: TPA | U97: Biju | V97: Suresh Kumar | X97: Open | Y97: WIP | AI97: 472DWDM | AJ97: DWDM | AK97: OPEN | AN97: Pending from TPA | AR97: 1 | AS97: Open | AT97: Open
B98: 96 | C98: T95 | D98: 472 | E98: NA | I98: DWDM | J98: Integration with OSS | K98: DWDM Network Alarms Integration | N98: Colosed | V98: Suresh Kumar | Y98: COMPLETED & APPROVED | Z98: AD-UT-Tfiber | AA98: 45783 | AB98: \\172.28.9.34\Artefacts_T-Fiber TNOC Tracker\DWDM\Artefact - T95 | AI98: 472DWDM | AJ98: DWDM | AK98: CLOSED | AO98: 45783 | AP98: \\172.28.9.34\Artefacts_T-Fiber TNOC Tracker\DWDM\Artefact - T95 | AR98: 1 | AS98: Completed & Approved | AT98: Closed before june-2025
B99: 97 | C99: T96 | D99: 472 | E99: NA | I99: DWDM | J99: Integration with OSS | K99: Hardware Inventory Integration in HPE OSS | N99: Colosed | V99: Suresh Kumar | Y99: COMPLETED & APPROVED | Z99: AD-UT-Tfiber | AA99: 45783 | AB99: \\172.28.9.34\Artefacts_T-Fiber TNOC Tracker\DWDM\Artefact - T96 | AI99: 472DWDM | AJ99: DWDM | AK99: CLOSED | AO99: 45783 | AP99: \\172.28.9.34\Artefacts_T-Fiber TNOC Tracker\DWDM\Artefact - T96 | AR99: 1 | AS99: Completed & Approved | AT99: Closed before june-2025
B100: 98 | C100: T97 | D100: 472 | E100: NA | I100: DWDM | J100: Integration with OSS | K100: DWDM Network Topology | N100: Open | S100: 26-July-2025: HPE conveyed that Topology border unable to make bold or hilight 12-July-2025: Update awaited from HPE 07-July-2025: Topology is visible but border is not highlighted. HP checking for the possibility to impose of border map on topology. Required 02 weeks post confirmation 05-July-2025: In discussion with HPE, required 02 weeks post confirmation, 21st July 30-June-2025: As discussed with Suresh P checking with HPE. Tentative date: 16th July. As discussed in the meeting, call to be arranged along with OSS SME and HP team | T100: HPE | U100: Anand | V100: Suresh Kumar | X100: Open | Y100: DEPENDENCY(Client/Ext.) | AI100: 472DWDM | AJ100: DWDM | AK100: OPEN | AR100: 1 | AS100: Open | AT100: Open
B101: 99 | C101: T98 | D101: 472 | E101: NA | I101: DWDM | J101: Integration with OSS | K101: Auto Ticket & RCA for Fiber Cuts | N101: Colosed | V101: Suresh Kumar | Y101: COMPLETED & APPROVED | Z101: AD-UT-Tfiber | AA101: 45783 | AB101: \\172.28.9.34\Artefacts_T-Fiber TNOC Tracker\DWDM\Artefact - T98 | AI101: 472DWDM | AJ101: DWDM | AK101: CLOSED | AO101: 45783 | AP101: \\172.28.9.34\Artefacts_T-Fiber TNOC Tracker\DWDM\Artefact - T98 | AR101: 1 | AS101: Completed & Approved | AT101: Closed before june-2025
B102: 100 | C102: T99 | D102: 472 | E102: NA | I102: DWDM | J102: Integration with OSS | K102: Auto Ticket & RCA for Hardware Failures | N102: Open | V102: Suresh Kumar | Y102: COMPLETED & APPROVED | AI102: 472DWDM | AJ102: DWDM | AK102: Open | AP102: \\172.28.9.34\Artefacts_T-Fiber TNOC Tracker\DWDM\Artefact - T99 | AR102: 1 | AS102: Completed & Approved | AT102: Closed after June
B103: 101 | C103: T100 | D103: 472 | E103: NA | I103: DWDM | J103: Integration with OSS | K103: Auto Ticket & RCA for Infra Failures | N103: Open | S103: 20-Sep-25: Required configuration changes was done by HPE team. DWDM team will validate and confirm by 23-Sep-25 13-09-25: Few issues observed, corrected by HP. Validation is in progress 10-08-2025: HP team confirmed cause of failure updated, validation is in progress 26-July-2025: Raised the concerns to HP team, cause of failure yet to update by them, Target date awaited9 12-July-2025: Configuration updated in production and RCA TT's for node down are generating. But having issue in cause of failure, same informed to HP team. Target date - 18-07-25 05-July-2025: Cofiguration in production planned on 8th July'25 30-June-25: WIP with HPE, target date 09-07-25 As discussed in the meeting, call to be arranged along with OSS SME and HP team 15-06-2025: WIP with HPE, target date 30-06-2025 21-05-2025: RCA Yet to be started by HPE, date: 30th June 2025 30APR'25: Node down Auto TT is ok but RCA pending | T103: L&T | V103: Suresh Kumar | Y103: COMPLETED & APPROVED | AI103: 472DWDM | AJ103: DWDM | AK103: CLOSED | AO103: 45923 | AP103: \\172.28.9.34\Artefacts_T-Fiber TNOC Tracker\DWDM\Artefact 100 | AR103: 1 | AS103: Completed & Approved | AT103: Closed after June
...

Sheet MOM-Summary
A3: Sum of Qty | B3: Column Labels
A4: Row Labels | B4: Closed after June | C4: Closed before june-2025 | D4: Completed but Verification undrer Process | E4: Open | F4: Grand Total
A5: Ahmad | B5: 21 | C5: 18 | E5: 9 | F5: 48
A6: Jayant Madavi | D6: 9 | E6: 47 | F6: 56
A7: Kaushalendra Kumar | D7: 103 | E7: 44 | F7: 147
A8: Manoj Nibrad | E8: 371 | F8: 371
A9: Ravi Kishore | B9: 4 | C9: 1 | D9: 4 | E9: 6 | F9: 15
A10: RS Rao | B10: 1 | C10: 2 | F10: 3
A11: S Kodali | E11: 30 | F11: 30
A12: Sarmendra | D12: 16 | E12: 126 | F12: 142
A13: Sayyad Pasha | B13: 1 | C13: 1 | E13: 3 | F13: 5
A14: Siva Kumar | B14: 57 | E14: 36 | F14: 93
A15: Sivaprasad | B15: 142 | C15: 22 | E15: 144 | F15: 308
A16: Srinivas Kommreddy | D16: 3 | F16: 3
A17: Suresh Kumar | B17: 1 | E17: 2 | F17: 3
A18: Suresh Pawar | D18: 37 | E18: 15 | F18: 52
A19: TFiber | D19: 2 | F19: 2
A20: Grand Total | B20: 227 | C20: 44 | D20: 174 | E20: 833 | F20: 1278

Sheet MOM-Detailed Sheet
B2: Slno | C2: UniqueID | D2: Category | E2: Meeting Date | F2: Priority | G2: Ramana | H2: Ramana-Domain | I2: Domain | J2: Sub-Domain | K2: Action Point | L2: Impact | M2: Priority | N2: Baseline Status | O2: xx | P2: Application | Q2: Module | R2: Remarks | S2: Remarks | T2: Organization | U2: Owner | V2: Owner(L&T) | W2: Target Date to Complete | X2: Open | Y2: Revised Status (L&T) As on 18-Sep-2025 | Z2: Approved BY (TF) | AA2: Approval Date(TF) | AB2: Link of evidences | AC2: R | AD2: S | AE2: T | AF2: U | AG2: V | AH2: W | AI2: X | AJ2: Tfiber-Cat | AK2: Derived Status (L&T) | AL2: OSS | AM2: OSS Remarks | AN2: Ramana Remarks as on 19-Sep-2025 | AO2: T Fiber Appoved Date | AP2: Artefacts | AQ2: Target Date | AR2: Qty | AS2: Ramana-Remarks | AT2: Updated on 13-Oct-2025
B3: 472 | C3: M1 | D3: MOM | E3: 44963 | I3: NOC Operationalization | J3: Dashboards | K3: Submit a fortnightly report (Kanban chart) for monitoring all activities in TNOC, including OSS, BSS, NSO, etc. | M3: Critical | N3: Open | P3: OSS Dashboards | R3: Closed | S3: 23-Sep-25: Approved shall be closed | V3: Sivaprasad | Y3: COMPLETED & APPROVED | AI3: MOMNOC Operationalization | AJ3: Network | AK3: CLOSED | AO3: 45923 | AP3: Artefacts not Required | AR3: 1 | AS3: Completed & Approved | AT3: Closed after June
B4: 473 | C4: M10 | D4: MOM | E4: 45019 | I4: GIS | J4: Resource Related | K4: Evaluation of License Sufficiency and Ramp-Up Plan | M4: Critical | N4: Open | P4: OSS Dashboards | S4: TFIBER is a critical dependency for closing the GIS licenses | V4: Kaushalendra Kumar | X4: Open | Y4: Open | AI4: MOMGIS | AJ4: Applications/Tools | AK4: OPEN | AP4: #N/A | AR4: 1 | AS4: Open | AT4: Open
B5: 474 | C5: M100 | D5: MOM | E5: 45139 | I5: Helpdesk | J5: Handbook & SOPs | K5: Call Escalation Recording Process | M5: Critical | N5: open | R5: Closed | S5: 25-Sep-25: Artefacts to be uploaded | V5: Siva Kumar | Y5: COMPLETED & APPROVED | AI5: MOMHelpdesk | AJ5: Helpdesk (Contact Center) | AK5: CLOSED | AO5: 45924 | AP5: \\172.28.9.34\Artefacts_T-Fiber TNOC Tracker\HELPDESK\M100 | AR5: 1 | AS5: Completed & Approved | AT5: Closed after June
B6: 475 | C6: M1000 | D6: MOM | E6: 45316 | I6: WFM | K6: Adopt WFM by packages B & C and procure licenses | M6: Critical | N6: Open | S6: TFIBER is a critical dependency for closing the WFM license | V6: Kaushalendra Kumar | X6: Open | Y6: Open | AI6: MOMWFM | AJ6: Applications/Tools | AK6: OPEN | AP6: #N/A | AR6: 1 | AS6: Open | AT6: Open
B7: 476 | C7: M1001 | D7: MOM | E7: 45316 | I7: Field Related | K7: Complete implementation of Mandal rings for NoFN PH-1 to declare District Go-Live | M7: Critical | N7: Open | S7: MR-06 & MR-25 Open due to ROW issue Rest all closed. | V7: S Kodali | X7: Open | Y7: Open | AI7: MOMField Related | AJ7: Field Related issues | AK7: OPEN | AN7: Project Team | AP7: #N/A | AR7: 1 | AS7: Open | AT7: Open
B8: 477 | C8: M1002 | D8: MOM | E8: 45316 | I8: Field Related | K8: Restore all social welfare and tribal welfare schools to serviceable condition | M8: Critical | N8: Open | S8: Ongoing process as per priority from clients | V8: S Kodali | X8: Open | Y8: Open | AI8: MOMField Related | AJ8: Field Related issues | AK8: OPEN | AN8: Ongoing operations, O&M Team | AP8: #N/A | AR8: 1 | AS8: Open | AT8: Open
B9: 478 | C9: M1003 | D9: MOM | E9: 45316 | I9: Field Related | K9: Complete all GI connectivity by March '24 and secure GI payments | M9: Critical | N9: Open | S9: Completed for | V9: S Kodali | X9: Open | Y9: Open | AI9: MOMField Related | AJ9: Field Related issues | AK9: OPEN | AN9: Project Team | AP9: #N/A | AR9: 1 | AS9: Open | AT9: Open
B10: 479 | C10: M1004 | D10: MOM | E10: 45316 | I10: Field Related | K10: Focus on top 4 priorities for network readiness | M10: Critical | N10: Open | V10: S Kodali | X10: Open | Y10: Open | AI10: MOMField Related | AJ10: Field Related issues | AK10: OPEN | AN10: Project Team | AP10: #N/A | AR10: 1 | AS10: Open | AT10: Open
B11: 480 | C11: M1005 | D11: MOM | E11: 45316 | I11: Field Related | K11: Make the network ready for service review by State IT&EC Minister | M11: Critical | N11: Open | V11: S Kodali | X11: Open | Y11: Open | AI11: MOMField Related | AJ11: Field Related issues | AK11: OPEN | AN11: Project Team | AP11: #N/A | AR11: 1 | AS11: Open | AT11: Open
B12: 481 | C12: M1006 | D12: MOM | E12: 45335 | I12: Field Related | K12: Issue with status of Sangareddy district E2E completion | M12: Critical | N12: Open | S12: 9 Mandal E2E completed , 2 WIP , balance 12 Mandal target by Dec'25 2 mandals BER/ ROW permission issue/not feasable | V12: S Kodali | X12: Open | Y12: Open | AI12: MOMField Related | AJ12: Field Related issues | AK12: OPEN | AN12: Project Team | AP12: #N/A | AR12: 1 | AS12: Open | AT12: Open
B13: 482 | C13: M1007 | D13: MOM | E13: 45335 | I13: Field Related | K13: Status of GP migrations and POP completion | M13: Critical | N13: Open | S13: 3520 GPs Completed as work front released till date. | V13: S Kodali | X13: Open | Y13: Open | AI13: MOMField Related | AJ13: Field Related issues | AK13: OPEN | AN13: Project Team | AP13: #N/A | AR13: 1 | AS13: Open | AT13: Open
B14: 483 | C14: M1008 | D14: MOM | E14: 45335 | I14: Field Related | K14: Pending mandals for End-End AT | M14: Critical | N14: Open | S14: 42 mandals WIP as per work front availability | V14: S Kodali | X14: Open | Y14: Open | AI14: MOMField Related | AJ14: Field Related issues | AK14: OPEN | AN14: Project Team | AP14: #N/A | AR14: 1 | AS14: Open | AT14: Open
B15: 484 | C15: M1009 | D15: MOM | E15: 45335 | I15: Security & Regulatory Compliance | J15: Regulatory Compliance | K15: Non-compliance with IP-MAC binding | M15: Critical | N15: Open | S15: Port winding is possible , however it will cause difficulty with field units. need brainstormig before deployment of Mac binding | V15: Sarmendra | X15: Open | Y15: Open | AI15: MOMSecurity & Regulatory Compliance | AJ15: Security | AK15: OPEN | AP15: #N/A | AR15: 1 | AS15: Open | AT15: Open
B16: 485 | C16: M101 | D16: MOM | E16: 45139 | I16: Helpdesk | J16: User Experience | K16: Missed Call Feature on WhatsApp | M16: Critical | N16: open | R16: WIP | S16: 11-Sep-25: Existing product will not Support | T16: L&T | U16: Shiva kumar | V16: Siva Kumar | X16: Open | Y16: WIP | AI16: MOMHelpdesk | AJ16: Helpdesk (Contact Center) | AK16: OPEN | AR16: 1 | AS16: Open | AT16: Open
B17: 486 | C17: M1010 | D17: MOM | E17: 45335 | I17: OEM Related | K17: Issues with application integration | M17: Critical | N17: Open | R17: WIP | T17: L&T | U17: Sivaprasad | V17: Sivaprasad | X17: Open | Y17: WIP | AI17: MOMOEM Related | AJ17: OEM Related Issues | AK17: OPEN | AR17: 1 | AS17: Open | AT17: Open
B18: 487 | C18: M1011 | D18: MOM | E18: 45335 | I18: Security & Regulatory Compliance | J18: Regulatory Compliance | K18: Review of submitted policy documents | M18: Critical | N18: Open | S18: 02 Policy has been cleared by TPA . Work on balance policy is in process | V18: Sarmendra | X18: Open | Y18: Open | AI18: MOMSecurity & Regulatory Compliance | AJ18: Security | AK18: OPEN | AP18: #N/A | AR18: 1 | AS18: Open | AT18: Open
